Workbook

Sheet 年终奖分配明细表-国内
A1: 分配模式：人民币 (Currency: CNY) | AB1: =AC3-AC4 | AC1: T+T0 | AD1: =AE3-AE4 | AO1: =AP3-AP4 | AU1: =AV3-AV4 | AW1: =AX3-AX4 | AY1: =AZ3-AZ4
AC2: CNY | AE2: CNY | AP2: CNY | AV2: CNY | AX2: CNY | AZ2: CNY
A3: 请勿隐藏绿色可调整列 | U3: 总额度 (Total) | AC3: 100
A4: Please DO NOT hide the Green column ! | U4: 已用额度 (Assigned) | AC4: 100 | AE4: =ROUND(AD9+AE7+IF(ISREF(INDIRECT("'年终奖分配明细表-海外'!A1")),'年终奖分配明细表-海外'!AD9,0),0) | AP4: =ROUND(AO9+AP7+IF(ISREF(INDIRECT("'年终奖分配明细表-海外'!A1")),'年终奖分配明细表-海外'!AO9,0),0) | AV4: =ROUND(AU9+AV7+IF(ISREF(INDIRECT("'年终奖分配明细表-海外'!A1")),'年终奖分配明细表-海外'!AU9,0),0) | AX4: =ROUND(AW9+AX7+IF(ISREF(INDIRECT("'年终奖分配明细表-海外'!A1")),'年终奖分配明细表-海外'!AW9,0),0) | AZ4: =ROUND(AY9+AZ7+IF(ISREF(INDIRECT("'年终奖分配明细表-海外'!A1")),'年终奖分配明细表-海外'!AY9,0),0)
U5: 剩余额度 (Remaining) | AC5: =AC3-AC4 | AE5: =AE3-AE4 | AP5: =AP3-AP4 | AV5: =AV3-AV4 | AX5: =AX3-AX4 | AZ5: =AZ3-AZ4
AO6: =AP1 | AU6: =AV1 | AW6: =AX1 | AY6: =AZ1
A7: 请勿删除第一行到第七行！！！ | AB7: 21426647 | AC7: =AC3-AB7 | AE7: =AE3-AD7 | AP7: =AP3-AO7 | AV7: =AV3-AU7 | AX7: =AX3-AW7 | AZ7: =AZ3-AY7
E8: ="@@CURRENCY_CNY" | AC8: h+TkhcC+k1K03NEzw7PIuIzvrKpz8sw2bC8IRy/wu0I=
A9: 2 | G9: @@CD_g1qT4RWZn8PvzqzsvsSlZ1HoevUBl8dinYL8/H7Cw9JN1xdebvU/xUsX4kOF/8om | AB9: =SUM(AA14:AA128)+SUM(AC14:AC128) | AD9: =SUM(AE14:AE128) | AO9: =SUM(AP14:AP128) | AU9: =SUM(AV14:AV128) | AW9: =SUM(AX14:AX128) | AY9: =SUM(AZ14:AZ128)
H10: 基本信息 (Basic Info) | AC10: 本次奖金 (Bonus of This Year) | AO10: ="本次"&AP1 | AQ10: 本次合计 (Total of This Year) | BA10: 备注信息 (Remarks) | BG10: 辅助信息 (Additional Info) | BP10: 上年度参考信息 (Reference Info of Last Year) | CG10: 包信息 (Pool Info) | CI10: 自定义标签 (Custom Labels)
A11: Name | B11: Legal Name | C11: Staff ID | D11: Department | E11: Sub Organization of the Department | F11: 2nd-Level Org. Under Department | G11: Organization | H11: Onboarding Date | I11: Employment Type | J11: Job function | K11: Position | L11: Professional grade | M11: Managerial grade | N11: Talent Tier | O11: 2024 Talent Tier | P11: Talent Tier Change in Last 2 Years | Q11: 2025 H1/H2 Performance Ratings | R11: 2025 H1/H2 Customized Performance Ratings | S11: 2024 H1/H2 Performance Ratings | T11: Performance Change in Last 2 Years | U11: Current Monthly Salary (CNY) | V11: Target Bonus % | W11: Payroll Currency | X11: Time Proration Factor | Y11: Base Amount of Annual Bonus (CNY) | Z11: Base Amount of Target Bonus (CNY) | AA11: Target Bonus (T) (CNY) | AB11: Special Bonus (T0) Suggestion (CNY) | AC11: Actual Special Bonus (T0) (CNY) | AD11: =IF(ISBLANK(AD12),"预留",AD12)&CHAR(10)&"Suggestion"&CHAR(10)&"(CNY)" | AE11: =IF(ISBLANK(AD12),"预留",AD12)&CHAR(10)&"Submission"&CHAR(10)&"(CNY)" | AF11: Total Project Bonus (CNY) | AG11: T+T0 Bonus (CNY) | AH11: T+T0 Bonus Index | AI11: T+T0+Project Bonus Amount (CNY) | AJ11: T+T0+Project Bonus Index | AK11: Suggested T+T0+Project Bonus Index | AL11: Vs. 2024 T+T0+Project Bonus (CNY) | AM11: Target+Project Bonus Index | AN11: Suggested Target+Project Bonus Index | AO11: Incremental Profit Sharing Incentive Suggestion(CNY) (CNY) | AP11: =AO12&CHAR(10)&"Submission"&CHAR(10)&"(CNY)" | AQ11: Total Bonus Payout | AR11: Total Payout Index (China) | AS11: Vs. 2024 Total Bonus Payout | AT11: Total Payout Index (Overseas) | AU11: =IF(ISBLANK(AU12),"预留",AU12)&CHAR(10)&"Suggestion"&CHAR(10)&"(CNY)" | AV11: =AU12&CHAR(10)&"Submission"&CHAR(10)&"(CNY)" | AW11: =IF(ISBLANK(AW12),"预留",AW12)&CHAR(10)&"Suggestion"&CHAR(10)&"(CNY)" | AX11: =AW12&CHAR(10)&"Submission"&CHAR(10)&"(CNY)" | AY11: =IF(ISBLANK(AY12),"预留",AY12)&CHAR(10)&"Suggestion"&CHAR(10)&"(CNY)" | AZ11: =AY12&CHAR(10)&"Submission"&CHAR(10)&"(CNY)" | BA11: Allocation Remarks | BB11: Historical Remarks | BC11: C&B G Remarks | BD11: Remarks from HRBP | BE11: Compensation-Performance Consistency | BF11: Allocation Alert | BG11: Promised Bonus (CNY) | BH11: Bonus Paid During the Year (CNY) | BI11: Remarks about Paid Bonus | BJ11: Non-deductible Leave Days % | BK11: Leave Days Remarks | BL11: Time Proration Factor of 2024 Annual Bonus | BM11: Base Amount of 2024 Annual Bonus (CNY) | BN11: Base Amount of 2024 Target Bonus (CNY) | BO11: Monthly Salary in 2024 (CNY) | BP11: 2024 H1/H2 Performance Ratings | BQ11: 2024 Talent Tier | BR11: 2024 T+T0 Bonus (CNY) | BS11: 2024 T+T0 Bonus Index | BT11: 2024 Total Project Bonus (CNY) | BU11: 2024 T+T0+Project Bonus (CNY) | BV11: 2024 T+T0+Project Bonus Index | BW11: 2024 Target+Project Bonus Index | BX11: 2024 Incremental Incentive (CNY) | BY11: 2024 Total Bonus Payout (CNY) | BZ11: 2024 Total Payout Index (China) | CA11: 2024 Total Payout Index (Overseas) | CB11: 2024 Service Bonus (CNY) | CC11: 2024 One- time Incremental Incentive (CNY) | CD11: 2024 Special Grant (CNY) | CE11: 2024 Non-deductible Leave Days % | CF11: 2024 Salary Structure Change | CG11: Pool name | CH11: Pool Owner | CI11: Salary Structure Change | CJ11: Sheet Split Tag | CK11: Region | CL11: Country/Region | CM11: Continent Region | CN11: LCY Exchange Rate | CO11: Termination/Transfer Label | CP11: Organization Label | CQ11: Performance Label | CR11: Job Grade Label | CS11: Talent Tier Label | CT11: New Job System Label | CU11: Serious violations of the Sunshine Code of Conduct | CV11: Good Overall Performance Rating with Underperform Contribution or Conduct Rating | CW11: Backup Label 2 | CX11: Backup Label 3 | CY11: Backup Label 4 | CZ11: Backup Label 5 | DA11: Backup Label 6 | DB11: Backup Label 7 | DC11: Backup Label 8
A12: @Name | D12: ="@@CR_12" | AC12: ="@B_"&AC8 | AE12: ="@B_"&AE8 | AP12: ="@B_"&AP8 | AV12: ="@B_"&AV8 | AX12: ="@B_"&AX8 | AZ12: ="@B_"&AZ8 | BA12: ="@Remark"
A13: 中英文名 | B13: 真实姓名 | C13: 员工ID | D13: 部门 | E13: 部门下一级组织 | F13: 部门下二级组织 | G13: 组织全称 | H13: 入职日期 | I13: 应聘类别 | J13: 发展通道 | K13: 专业职位 | L13: 专业职级 | M13: 管理职级 | N13: 2025 人才梯队 | O13: 2024 人才梯队 | P13: 两年梯队变化 | Q13: 2025绩效 H1/H2 | R13: 2025自定义绩效 H1/H2 | S13: 2024绩效 H1/H2 | T13: 两年绩效变化 | U13: 目前月薪 (CNY) | V13: 浮动比例 | W13: 发薪币种 | X13: 年终奖 时间系数 | Y13: 年终奖 基数 (CNY) | Z13: Target Bonus基数 (CNY) | AA13: 绩效奖金 (T) (CNY) | AB13: 下发 特别奖金 (T0) (CNY) | AC13: 提交 特别奖金 (T0) (CNY) | AD13: ="下发"&CHAR(10)&IF(ISBLANK(AE1),"预留Q",AE1)&"(CNY)" | AE13: ="提交"&CHAR(10)&IF(ISBLANK(AE1),"预留R",AE1)&"(CNY)" | AF13: 项目奖金 合计 (CNY) | AG13: (T+T0) 金额 (CNY) | AH13: (T+T0) 系数 | AI13: (T+T0+项目奖) 金额 (CNY) | AJ13: (T+T0+项目奖) 系数 | AK13: 下发建议 (T+T0+项目奖) 系数 | AL13: VS 2024 (T+T0+项目奖) 金额 | AM13: (Target Bonus+项目奖)系数 | AN13: 下发建议 (Target Bonus+项目奖)系数 | AO13: ="下发"&CHAR(10)&AP1&"(CNY)" | AP13: ="提交"&CHAR(10)&AP1&"(CNY)" | AQ13: 合计金额 (CNY) | AR13: 国内合计系数 | AS13: VS 2024 合计金额 | AT13: 海外合计系数 | AU13: ="下发"&CHAR(10)&AV1&"(CNY)" | AV13: ="提交"&CHAR(10)&AV1&"(CNY)" | AW13: ="下发"&CHAR(10)&AX1&"(CNY)" | AX13: ="提交"&CHAR(10)&AX1&"(CNY)" | AY13: ="下发"&CHAR(10)&AZ1&"(CNY)" | AZ13: ="提交"&CHAR(10)&AZ1&"(CNY)" | BA13: 当前环节 分配备注 | BB13: 前序环节 分配备注 | BC13: 薪酬经理备注 | BD13: BP备注 | BE13: 薪酬与评价 匹配度 | BF13: 分配规则 校验信息 | BG13: 承诺奖金 (CNY) | BH13: 已发放奖金 (CNY) | BI13: 已发放奖金备注 | BJ13: 长假期天数占比(未影响时间系数) | BK13: 假期备注 | BL13: 2024 年终奖 时间系数 | BM13: 2024 年终奖 基数 (CNY) | BN13: 2024 Target Bonus基数 (CNY) | BO13: 2024月薪 (CNY) | BP13: 2024绩效 H1/H2 | BQ13: 2024 人才梯队 | BR13: 2024 (T+T0) 金额 (CNY) | BS13: 2024 (T+T0) 系数 | BT13: 2024 项目奖合计 (CNY) | BU13: 2024 (T+T0+项目奖) 金额 (CNY) | BV13: 2024 (T+T0+项目奖) 系数 | BW13: 2024 (Target Bonus+项目奖)系数 | BX13: 2024 增量激励 (如有) (CNY) | BY13: 2024 合计金额 (CNY) | BZ13: 2024 国内合计系数 | CA13: 2024 海外合计系数 | CB13: 2024 服务奖(CNY) | CC13: 2024增量项目激励 (如有) (CNY) | CD13: 2024年末特别授予(如有) (CNY) | CE13: 2024 长假期天数占比(未影响时间系数) | CF13: 2024全年 薪酬结构 变化标识 | CG13: 包名称 | CH13: 包负责人 | CI13: 全年 薪酬结构 变化标识 | CJ13: 拆表标签 | CK13: 地区分类 | CL13: 国家/地区 | CM13: 区域 | CN13: 本币汇率 | CO13: 离职/调动 标签 | CP13: 组织标签 | CQ13: 绩效标签 | CR13: 职级标签 | CS13: 梯队标签 | CT13: 试点体系标签 | CU13: 是否阳光行为违规 | CV13: 绩效综合G且业绩/行为评级U | CW13: 补充标签2 | CX13: 补充标签3 | CY13: 补充标签4 | CZ13: 补充标签5 | DA13: 补充标签6 | DB13: 补充标签7 | DC13: 补充标签8
A14: edwardXu(徐帆国) | C14: 57792341 | D14: 风险管理和内部控制 | E14: WXG风控中心 | G14: S2职能系统－财经线/风险管理和内部控制/WXG风控中心 | H14: 39707 | I14: 社会招聘 | J14: 财经类－FN | K14: 风险管理 | L14: S9 | N14: T1# | Q14: U,G | U14: 34220.45 | V14: 0.083333 | W14: CNY | X14: 1 | Y14: 32767.06 | Z14: 0 | AA14: 34220.45 | AB14: 112980 | AC14: 0 | AF14: 0 | AG14: 147200.45 | AH14: 4.4923301 | AI14: 147200.45 | AJ14: 4.4923301 | AK14: 4.4923301 | AQ14: 147200.45 | AR14: 4.4923301 | AS14: 0.64760427 | BL14: 1 | BM14: 30610 | BN14: 0 | BO14: 33125 | BP14: G,G | BQ14: T1# | BR14: 181445 | BS14: 5.927638 | BT14: 45855 | BU14: 227300 | BV14: 7.4256779 | BY14: 227300 | BZ14: 7.4256779 | CP14: 风险管理和内部控制 | CQ14: 3,1 | CR14: 9 | CS14: T1# | CT14: N
A15: savannahZhong(钟倩思) | C15: 78647818 | D15: 审计监察 | E15: 金融审计组 | G15: S2职能系统－财经线/审计监察/金融审计组 | H15: 45139 | I15: 高校招聘 | J15: 财经类－FN | K15: 风险管理 | L15: S5 | N15: T1# | Q15: G,U | U15: 23014.25 | V15: 0.083333 | W15: CNY | X15: 1 | Y15: 21659.73 | Z15: 0 | AA15: 69042.75 | AB15: 75165 | AC15: 24895 | AF15: 0 | AG15: 169102.75 | AH15: 7.8072418 | AI15: 169102.75 | AJ15: 7.8072418 | AK15: 6.6578739 | AQ15: 169102.75 | AR15: 7.8072418 | AS15: 21.652081 | BL15: 0.41643836 | BM15: 18765 | BN15: 0 | BO15: 18765 | BP15: N,G | BQ15: T1# | BR15: 7810 | BS15: 0.41620037 | BT15: 0 | BU15: 7810 | BV15: 0.41620037 | BY15: 7810 | BZ15: 0.41620037 | CP15: 审计监察 | CQ15: 5,3 | CR15: 5 | CS15: T1# | CT15: N
A16: emmaZheng(郑苑) | C16: 37559092 | D16: 财会及报告管理部 | E16: 应收管理中心 | G16: S2职能系统－财经线/财会及报告管理部/应收管理中心 | H16: 41779 | I16: 社会招聘 | J16: 财经类－FN | K16: 会计 | L16: S11 | N16: T1# | Q16: G,G | U16: 53212.6 | V16: 0.083333 | W16: CNY | X16: 1 | Y16: 50216.55 | Z16: 0 | AA16: 106425.2 | AB16: 166610 | AC16: 67765 | AF16: 0 | AG16: 340800.2 | AH16: 6.7866112 | AI16: 340800.2 | AJ16: 6.7866112 | AK16: 5.4371557 | AQ16: 340800.2 | AR16: 6.7866112 | AS16: 1.0573678 | BL16: 1 | BM16: 44240 | BN16: 0 | BO16: 46890 | BP16: G,G | BQ16: T1# | BR16: 235640 | BS16: 5.3264014 | BT16: 86670 | BU16: 322310 | BV16: 7.2854882 | BY16: 322310 | BZ16: 7.2854882 | CP16: 财会及报告管理部 | CQ16: 3,3 | CR16: 11 | CS16: T1# | CT16: N
A17: edwardJia(贾平华) | C17: 14198066 | D17: FiT财务管理 | E17: 业务支持与分析中心 | G17: S2职能系统－财经线/FiT财务管理/业务支持与分析中心 | H17: 37710 | I17: 社会招聘 | J17: 财经类－FN | K17: 财务管理 | L17: S6 | N17: T1 | Q17: O,G | U17: 27937.2 | V17: 0.083333 | W17: CNY | X17: 1 | Y17: 26626.57 | Z17: 0 | AA17: 111748.8 | AB17: 68640 | AC17: 42535 | AF17: 0 | AG17: 222923.8 | AH17: 8.3722312 | AI17: 222923.8 | AJ17: 8.3722312 | AK17: 6.7747667 | AQ17: 222923.8 | AR17: 8.3722312 | AS17: 1.6884969 | BL17: 1 | BM17: 23850 | BN17: 0 | BO17: 25715 | BP17: G,G | BQ17: T1 | BR17: 80825 | BS17: 3.3888889 | BT17: 51200 | BU17: 132025 | BV17: 5.5356394 | BY17: 132025 | BZ17: 5.5356394 | CP17: FiT财务管理 | CQ17: 5,5 | CR17: 6 | CS17: T1 | CT17: N
A18: patrickJiang(姜彪国) | C18: 1336290 | D18: 风险管理和内部控制 | E18: CSIG风控中心 | G18: S2职能系统－财经线/风险管理和内部控制/CSIG风控中心 | H18: 42286 | I18: 社会招聘 | J18: 财经类－FN | K18: 风险管理 | L18: S9 | N18: T1 | Q18: O,G | U18: 54594.65 | V18: 0.083333 | W18: CNY | X18: 1 | Y18: 53257.31 | Z18: 0 | AA18: 109189.3 | AB18: 130245 | AC18: 76345 | AF18: 0 | AG18: 315779.3 | AH18: 5.9293137 | AI18: 315779.3 | AJ18: 5.9293137 | AK18: 4.4958016 | AQ18: 315779.3 | AR18: 5.9293137 | AS18: 1.3897513 | BL18: 1 | BM18: 45345 | BN18: 0 | BO18: 49295 | BP18: G,G | BQ18: T1 | BR18: 155765 | BS18: 3.4351086 | BT18: 71455 | BU18: 227220 | BV18: 5.0109163 | BY18: 227220 | BZ18: 5.0109163 | CP18: 风险管理和内部控制 | CQ18: 3,3 | CR18: 9 | CS18: T1 | CT18: N
A19: chloeLin(林琴悦) | C19: 2185561 | D19: CSIG财务管理 | E19: 公线及费用财务管理中心 | G19: S2职能系统－财经线/CSIG财务管理/公线及费用财务管理中心 | H19: 43514 | I19: 社会招聘 | J19: 财经类－FN | K19: 财务管理 | L19: S8 | N19: T1 | Q19: O,G | U19: 46114.8 | V19: 0.083333 | W19: CNY | X19: 1 | Y19: 42227.05 | Z19: 0 | AA19: 138344.4 | AB19: 108735 | AC19: 68175 | AF19: 0 | AG19: 315254.4 | AH19: 7.4656979 | AI19: 315254.4 | AJ19: 7.4656979 | AK19: 5.8512115 | AQ19: 315254.4 | AR19: 7.4656979 | AS19: 1.2007404 | BL19: 1 | BM19: 38825 | BN19: 0 | BO19: 40225 | BP19: G,G | BQ19: T1# | BR19: 218440 | BS19: 5.6262717 | BT19: 44110 | BU19: 262550 | BV19: 6.7623954 | BY19: 262550 | BZ19: 6.7623954 | CP19: CSIG财务管理 | CQ19: 5,3 | CR19: 8 | CS19: T1 | CT19: N
A20: abigailDong(董璐月) | C20: 15958390 | D20: 风险管理和内部控制 | E20: IEG风控中心 | G20: S2职能系统－财经线/风险管理和内部控制/IEG风控中心 | H20: 37998 | I20: 高校招聘 | J20: 财经类－FN | K20: 风险管理 | L20: S11 | N20: T1 | Q20: G,O | U20: 42014.3 | V20: 0.083333 | W20: CNY | X20: 1 | Y20: 40908.92 | Z20: 0 | AA20: 42014.3 | AB20: 104350 | AC20: 0 | AF20: 0 | AG20: 146364.3 | AH20: 3.5778089 | AI20: 146364.3 | AJ20: 3.5778089 | AK20: 3.5778089 | AQ20: 146364.3 | AR20: 3.5778089 | AS20: 0.5545993 | BL20: 1 | BM20: 35120 | BN20: 0 | BO20: 37910 | BP20: G,G | BQ20: T1# | BR20: 207955 | BS20: 5.9212699 | BT20: 55955 | BU20: 263910 | BV20: 7.5145216 | BY20: 263910 | BZ20: 7.5145216 | CP20: 风险管理和内部控制 | CQ20: 3,1 | CR20: 11 | CS20: T1 | CT20: N
A21: nicholasQiu(邱强) | C21: 19081982 | D21: 风险管理和内部控制 | E21: IEG风控中心 | G21: S2职能系统－财经线/风险管理和内部控制/IEG风控中心 | H21: 42461 | I21: 高校招聘 | J21: 财经类－FN | K21: 风险管理 | L21: S8 | N21: T2 | Q21: G,G | U21: 44043.7 | V21: 0.083333 | W21: CNY | X21: 1 | Y21: 41123.76 | Z21: 0 | AA21: 132131.1 | AB21: 51655 | AC21: 0 | AF21: 0 | AG21: 183786.1 | AH21: 4.4690977 | AI21: 183786.1 | AJ21: 4.4690977 | AK21: 4.4690977 | AQ21: 183786.1 | AR21: 4.4690977 | AS21: 1.1295317 | BL21: 1 | BM21: 35815 | BN21: 0 | BO21: 38760 | BP21: G,O | BQ21: T2 | BR21: 162710 | BS21: 4.5430685 | BT21: 0 | BU21: 162710 | BV21: 4.5430685 | BY21: 162710 | BZ21: 4.5430685 | CP21: 风险管理和内部控制 | CQ21: 5,3 | CR21: 8 | CS21: T2 | CT21: N
A22: matthewHou(侯勋宏) | C22: 81154958 | D22: 海外财经中心 | E22: 海外本地财务 | G22: S2职能系统－财经线/海外财经中心/海外本地财务 | H22: 41263 | I22: 社会招聘 | J22: 财经类－FN | K22: 财务管理 | L22: S11 | N22: T1 | Q22: G,G | U22: 51306.95 | V22: 0.083333 | W22: CNY | X22: 1 | Y22: 46207.44 | Z22: 0 | AA22: 102613.9 | AB22: 108165 | AC22: 98095 | AF22: 0 | AG22: 308873.9 | AH22: 6.6845058 | AI22: 308873.9 | AJ22: 6.6845058 | AK22: 4.5615793 | AQ22: 308873.9 | AR22: 6.6845058 | AS22: 2.2710481 | BL22: 1 | BM22: 42530 | BN22: 0 | BO22: 44415 | BP22: U,O | BQ22: T1 | BR22: 136005 | BS22: 3.1978603 | BT22: 0 | BU22: 136005 | BV22: 3.1978603 | BY22: 136005 | BZ22: 3.1978603 | CP22: 海外财经中心 | CQ22: 3,3 | CR22: 11 | CS22: T1 | CT22: N
A23: lillianTian(田青) | C23: 21911153 | D23: 财经IT管理部 | E23: 平台建设中心 | G23: S2职能系统－财经线/财经IT管理部/平台建设中心 | H23: 43026 | I23: 高校招聘 | J23: 技术研发类－TRD | K23: 应用开发 | L23: T9 | N23: T1 | Q23: G,U | U23: 51577.2 | V23: 0.083333 | W23: CNY | X23: 1 | Y23: 47257.05 | Z23: 0 | AA23: 103154.4 | AB23: 128330 | AC23: 60530 | AF23: 0 | AG23: 292014.4 | AH23: 6.179277 | AI23: 292014.4 | AJ23: 6.179277 | AK23: 4.8984099 | AQ23: 292014.4 | AR23: 6.179277 | AS23: 1.4390262 | BL23: 1 | BM23: 43545 | BN23: 0 | BO23: 46510 | BP23: G,G | BQ23: T1 | BR23: 142185 | BS23: 3.2652429 | BT23: 60740 | BU23: 202925 | BV23: 4.6601217 | BY23: 202925 | BZ23: 4.6601217 | CP23: 财经IT管理部 | CQ23: 3,3 | CR23: 9 | CS23: T1 | CT23: N
A24: louisYu(于梓) | C24: 60316002 | D24: 预算及职能系统财务管理部 | E24: 预算及职能系统财务管理部 | G24: S2职能系统－财经线/预算及职能系统财务管理部 | H24: 39619 | I24: 社会招聘 | J24: 财经类－FN | K24: 预算管理 | L24: S6 | N24: T1# | Q24: O,G | U24: 24152.75 | V24: 0.083333 | W24: CNY | X24: 1 | Y24: 22085.21 | Z24: 0 | AA24: 48305.5 | AB24: 81310 | AC24: 41850 | AF24: 0 | AG24: 171465.5 | AH24: 7.7638157 | AI24: 171465.5 | AJ24: 7.7638157 | AK24: 5.8688824 | AQ24: 171465.5 | AR24: 7.7638157 | AS24: 1.0804379 | BL24: 1 | BM24: 21715 | BN24: 0 | BO24: 23560 | BP24: G,G | BQ24: T1# | BR24: 120875 | BS24: 5.5664287 | BT24: 37825 | BU24: 158700 | BV24: 7.3083122 | BY24: 158700 | BZ24: 7.3083122 | CP24: 预算及职能系统财务管理部 | CQ24: 3,3 | CR24: 6 | CS24: T1# | CT24: N
A25: ameliaNiu(牛佳娜) | C25: 82693967 | D25: 预算及职能系统财务管理部 | E25: 预算管理中心 | G25: S2职能系统－财经线/预算及职能系统财务管理部/预算管理中心 | H25: 43762 | I25: 社会招聘 | J25: 财经类－FN | K25: 预算管理 | L25: S6 | N25: T1# | Q25: U,G | U25: 30766.2 | V25: 0.083333 | W25: CNY | X25: 1 | Y25: 30214.76 | Z25: 0 | AA25: 92298.6 | AB25: 98570 | AC25: 41985 | AF25: 0 | AG25: 232853.6 | AH25: 7.7066176 | AI25: 232853.6 | AJ25: 7.7066176 | AK25: 6.3170649 | AQ25: 232853.6 | AR25: 7.7066176 | AS25: 0.92457256 | BL25: 1 | BM25: 27535 | BN25: 0 | BO25: 29840 | BP25: O,G | BQ25: T1# | BR25: 192300 | BS25: 6.9838388 | BT25: 59550 | BU25: 251850 | BV25: 9.1465408 | BY25: 251850 | BZ25: 9.1465408 | CP25: 预算及职能系统财务管理部 | CQ25: 5,3 | CR25: 6 | CS25: T1# | CT25: N
... A39: wayneChang(常阳) | C39: 74666760 | D39: 预算及职能系统财务管理部 | E39: 预算管理中心 | G39: S2职能系统－财经线/预算及职能系统财务管理部/预算管理中心 | H39: 43256 | I39: 社会招聘 | J39: 财经类－FN | K39: 预算管理 | L39: S10 | N39: T1 | Q39: U,G | U39: 35677.4 | V39: 0.083333 | W39: CNY | X39: 1 | Y39: 34145.86 | Z39: 0 | AA39: 35677.4 | AB39: 86825 | AC39: 0 | AF39: 0 | AG39: 122502.4 | AH39: 3.5876209 | AI39: 122502.4 | AJ39: 3.5876209 | AK39: 3.5876209 | AQ39: 122502.4 | AR39: 3.5876209 | AS39: 0.9608785 | BL39: 1 | BM39: 28695 | BN39: 0 | BO39: 29060 | BP39: G,G | BQ39: T1 | BR39: 88665 | BS39: 3.0899111 | BT39: 38825 | BU39: 127490 | BV39: 4.4429343 | BY39: 127490 | BZ39: 4.4429343 | CP39: 预算及职能系统财务管理部 | CQ39: 3,1 | CR39: 10 | CS39: T1 | CT39: N
A40: kevinQian(钱峰阳) | C40: 91424281 | D40: 风险管理和内部控制 | E40: WXG风控中心 | G40: S2职能系统－财经线/风险管理和内部控制/WXG风控中心 | H40: 45377 | I40: 社会招聘 | J40: 财经类－FN | K40: 风险管理 | L40: S8 | N40: T2 | Q40: G,O | U40: 46653.7 | V40: 0.083333 | W40: CNY | X40: 0.767123 | Y40: 44279.38 | Z40: 0 | AA40: 35789.13 | AB40: 0 | AC40: 0 | AF40: 0 | AG40: 35789.13 | AH40: 0.80825725 | AI40: 35789.13 | AJ40: 0.80825725 | AK40: 0.80825725 | AQ40: 35789.13 | AR40: 0.80825725 | BM40: 0 | BN40: 0 | BO40: 0 | BR40: 0 | BT40: 0 | BU40: 0 | BY40: 0 | CP40: 风险管理和内部控制 | CQ40: 5,3 | CR40: 8 | CS40: T2 | CT40: N
A41: ariaZeng(曾璐莉) | C41: 88685121 | D41: 财经IT管理部 | E41: 业务开发中心 | G41: S2职能系统－财经线/财经IT管理部/业务开发中心 | H41: 36550 | I41: 社会招聘 | J41: 技术研发类－TRD | K41: 应用开发 | L41: T11 | N41: T1 | Q41: G,G | U41: 54850.25 | V41: 0.083333 | W41: CNY | X41: 1 | Y41: 50436.78 | Z41: 0 | AA41: 109700.5 | AB41: 123525 | AC41: 82735 | AF41: 0 | AG41: 315960.5 | AH41: 6.264486 | AI41: 315960.5 | AJ41: 6.264486 | AK41: 4.6241156 | AQ41: 315960.5 | AR41: 6.264486 | AS41: 0.94781989 | BL41: 1 | BM41: 46005 | BN41: 0 | BO41: 47660 | BP41: O,O | BQ41: T1 | BR41: 255790 | BS41: 5.5600478 | BT41: 77565 | BU41: 333355 | BV41: 7.2460602 | BY41: 333355 | BZ41: 7.2460602 | CP41: 财经IT管理部 | CQ41: 3,3 | CR41: 11 | CS41: T1 | CT41: N
A42: seanShi(施博力) | C42: 13692542 | D42: 财会及报告管理部 | E42: 账务中心 | G42: S2职能系统－财经线/财会及报告管理部/账务中心 | H42: 43674 | I42: 社会招聘 | J42: 财经类－FN | K42: 会计 | L42: S6 | N42: T1# | Q42: G,G | U42: 23356.65 | V42: 0.083333 | W42: CNY | X42: 1 | Y42: 21832.3 | Z42: 0 | AA42: 46713.3 | AB42: 71115 | AC42: 29115 | AF42: 0 | AG42: 146943.3 | AH42: 6.730546 | AI42: 146943.3 | AJ42: 6.730546 | AK42: 5.3969715 | AQ42: 146943.3 | AR42: 6.730546 | AS42: 1.12209 | BL42: 1 | BM42: 19835 | BN42: 0 | BO42: 20055 | BP42: G,G | BQ42: T1# | BR42: 104160 | BS42: 5.2513234 | BT42: 26795 | BU42: 130955 | BV42: 6.6022183 | BY42: 130955 | BZ42: 6.6022183 | CP42: 财会及报告管理部 | CQ42: 3,3 | CR42: 6 | CS42: T1# | CT42: N
A43: kennethShi(施彪志) | C43: 83510684 | D43: FiT财务管理 | E43: 业务支持与分析中心 | G43: S2职能系统－财经线/FiT财务管理/业务支持与分析中心 | H43: 37145 | I43: 社会招聘 | J43: 财经类－FN | K43: 财务管理 | L43: S6 | N43: T1# | Q43: G,G | U43: 37008.1 | V43: 0.083333 | W43: CNY | X43: 1 | Y43: 34065.36 | Z43: 0 | AA43: 74016.2 | AB43: 111945 | AC43: 71085 | AF43: 0 | AG43: 257046.2 | AH43: 7.5456769 | AI43: 257046.2 | AJ43: 7.5456769 | AK43: 5.458953 | AQ43: 257046.2 | AR43: 7.5456769 | AS43: 1.0672903 | BL43: 1 | BM43: 32010 | BN43: 0 | BO43: 32285 | BP43: O,G | BQ43: T1# | BR43: 196995 | BS43: 6.1541706 | BT43: 43845 | BU43: 240840 | BV43: 7.5238988 | BY43: 240840 | BZ43: 7.5238988 | CP43: FiT财务管理 | CQ43: 3,3 | CR43: 6 | CS43: T1# | CT43: N
A44: dianeGuo(郭怡) | C44: 34945004 | D44: CSIG财务管理 | E44: 产品财务管理中心 | G44: S2职能系统－财经线/CSIG财务管理/产品财务管理中心 | H44: 40737 | I44: 社会招聘 | J44: 财经类－FN | K44: 财务管理 | L44: S5 | N44: T2 | Q44: G,G | U44: 19312.85 | V44: 0.083333 | W44: CNY | X44: 1 | Y44: 18658.16 | Z44: 0 | AA44: 38625.7 | AB44: 27795 | AC44: 0 | AF44: 0 | AG44: 66420.7 | AH44: 3.5598741 | AI44: 66420.7 | AJ44: 3.5598741 | AK44: 3.5598741 | AQ44: 66420.7 | AR44: 3.5598741 | AS44: 1.1443952 | BL44: 1 | BM44: 15915 | BN44: 0 | BO44: 17085 | BP44: G,G | BQ44: T2 | BR44: 58040 | BS44: 3.646874 | BT44: 0 | BU44: 58040 | BV44: 3.646874 | BY44: 58040 | BZ44: 3.646874 | CP44: CSIG财务管理 | CQ44: 3,3 | CR44: 5 | CS44: T2 | CT44: N
A45: geraldJiang(江立) | C45: 47476377 | D45: 财经投资并购及管理部 | E45: 财经投资并购及管理部 | G45: S2职能系统－财经线/财经投资并购及管理部 | H45: 39276 | I45: 高校招聘 | J45: 财经类－FN | K45: 投资并购 | L45: S9 | N45: T2 | Q45: G,G | U45: 42167.25 | V45: 0.083333 | W45: CNY | X45: 1 | Y45: 41478.02 | Z45: 0 | AA45: 84334.5 | AB45: 52235 | AC45: 0 | AF45: 0 | AG45: 136569.5 | AH45: 3.2925752 | AI45: 136569.5 | AJ45: 3.2925752 | AK45: 3.2925752 | AQ45: 136569.5 | AR45: 3.2925752 | AS45: 0.9049132 | BL45: 1 | BM45: 36430 | BN45: 0 | BO45: 36930 | BP45: G,O | BQ45: T2 | BR45: 150920 | BS45: 4.1427395 | BT45: 0 | BU45: 150920 | BV45: 4.1427395 | BY45: 150920 | BZ45: 4.1427395 | CP45: 财经投资并购及管理部 | CQ45: 3,3 | CR45: 9 | CS45: T2 | CT45: N
A46: samanthaLu(卢娇) | C46: 16699560 | D46: CDG财务管理 | E46: 综合财务管理中心 | G46: S2职能系统－财经线/CDG财务管理/综合财务管理中心 | H46: 40499 | I46: 社会招聘 | J46: 财经类－FN | K46: 财务管理 | L46: S9 | N46: T2 | Q46: G,G | U46: 52890.75 | V46: 0.083333 | W46: CNY | X46: 1 | Y46: 52143.33 | Z46: 0 | AA46: 105781.5 | AB46: 71240 | AC46: 0 | AF46: 0 | AG46: 177021.5 | AH46: 3.3949021 | AI46: 177021.5 | AJ46: 3.3949021 | AK46: 3.3949021 | AQ46: 177021.5 | AR46: 3.3949021 | AS46: 0.88774855 | BL46: 1 | BM46: 47065 | BN46: 0 | BO46: 47475 | BP46: O,G | BQ46: T2 | BR46: 199405 | BS46: 4.2368002 | BT46: 0 | BU46: 199405 | BV46: 4.2368002 | BY46: 199405 | BZ46: 4.2368002 | CP46: CDG财务管理 | CQ46: 3,3 | CR46: 9 | CS46: T2 | CT46: N
A47: amandaHuang(黄琪) | C47: 53009758 | D47: 应收账款管理中心 | E47: 应收管理1组 | G47: S2职能系统－财经线/应收账款管理中心/应收管理1组 | H47: 42236 | I47: 社会招聘 | J47: 财经类－FN | K47: 会计 | L47: S9 | N47: T2 | Q47: G,G | U47: 40910.55 | V47: 0.083333 | W47: CNY | X47: 1 | Y47: 38691.58 | Z47: 0 | AA47: 81821.1 | AB47: 44380 | AC47: 0 | AF47: 0 | AG47: 126201.1 | AH47: 3.26172 | AI47: 126201.1 | AJ47: 3.26172 | AK47: 3.26172 | AQ47: 126201.1 | AR47: 3.26172 | AS47: 1.0202191 | BL47: 1 | BM47: 36280 | BN47: 0 | BO47: 39725 | BP47: G,G | BQ47: T2 | BR47: 123700 | BS47: 3.4095921 | BT47: 0 | BU47: 123700 | BV47: 3.4095921 | BY47: 123700 | BZ47: 3.4095921 | CP47: 应收账款管理中心 | CQ47: 3,3 | CR47: 9 | CS47: T2 | CT47: N
A48: rebeccaQin(秦娟茜) | C48: 73675670 | D48: 可持续社会价值事业部财务管理 | E48: 可持续社会价值事业部财务管理 | G48: S2职能系统－财经线/可持续社会价值事业部财务管理 | H48: 42222 | I48: 高校招聘 | J48: 财经类－FN | K48: 财务管理 | L48: S12 | M48: L1-2 | N48: T1# | Q48: G,O | U48: 74713.15 | V48: 0.083333 | W48: CNY | X48: 1 | Y48: 73759.27 | Z48: 0 | AA48: 224139.45 | AB48: 225785 | AC48: 105815 | AF48: 15650 | AG48: 555739.45 | AH48: 7.5345031 | AI48: 571389.45 | AJ48: 7.7466798 | AK48: 6.3120805 | AQ48: 571389.45 | AR48: 7.7466798 | AS48: 1.0907085 | BL48: 1 | BM48: 66850 | BN48: 0 | BO48: 70875 | BP48: O,G | BQ48: T1# | BR48: 429750 | BS48: 6.4285714 | BT48: 94120 | BU48: 523870 | BV48: 7.8364996 | BY48: 523870 | BZ48: 7.8364996 | CP48: 可持续社会价值事业部财务管理 | CQ48: 5,3 | CR48: 12 | CS48: T1# | CT48: N
A49: stephenGao(高霖) | C49: 90270227 | D49: 董事会办公室 | E49: 董事会办公室 | G49: S2职能系统－财经线/董事会办公室 | H49: 37912 | I49: 社会招聘 | J49: 财经类－FN | K49: 公司秘书 | L49: S10 | N49: T1# | Q49: G,G | U49: 57296.75 | V49: 0.083333 | W49: CNY | X49: 1 | Y49: 52389.44 | Z49: 0 | AA49: 114593.5 | AB49: 175805 | AC49: 85420 | AF49: 0 | AG49: 375818.5 | AH49: 7.1735544 | AI49: 375818.5 | AJ49: 7.1735544 | AK49: 5.5430732 | AQ49: 375818.5 | AR49: 7.1735544 | AS49: 1.1033852 | BL49: 1 | BM49: 46200 | BN49: 0 | BO49: 49720 | BP49: G,G | BQ49: T1# | BR49: 268260 | BS49: 5.8064935 | BT49: 72345 | BU49: 340605 | BV49: 7.3724026 | BY49: 340605 | BZ49: 7.3724026 | CP49: 董事会办公室 | CQ49: 3,3 | CR49: 10 | CS49: T1# | CT49: N
A50: aaliyahZheng(郑英红) | C50: 22423058 | D50: IEG财务管理 | E50: IEG Global Finance | G50: S2职能系统－财经线/IEG财务管理/IEG Global Finance | H50: 37919 | I50: 社会招聘 | J50: 财经类－FN | K50: 财务管理 | M50: L3-2 | N50: T1# | Q50: G,G | U50: 69269.75 | V50: 0.083333 | W50: CNY | X50: 1 | Y50: 66474.84 | Z50: 0 | AA50: 138539.5 | AB50: 210995 | AC50: 121000 | AF50: 35580 | AG50: 470534.5 | AH50: 7.0783848 | AI50: 506114.5 | AJ50: 7.6136249 | AK50: 5.7933874 | AQ50: 506114.5 | AR50: 7.6136249 | AS50: 0.99965336 | BL50: 1 | BM50: 61615 | BN50: 0 | BO50: 64965 | BP50: G,O | BQ50: T1# | BR50: 402995 | BS50: 6.540534 | BT50: 103295 | BU50: 506290 | BV50: 8.2169926 | BY50: 506290 | BZ50: 8.2169926 | CP50: IEG财务管理 | CQ50: 3,3 | CR50: L3-2 | CS50: T1# | CT50: N
A51: walterQian(钱豪彤) | C51: 64672773 | D51: 预算及职能系统财务管理部 | E51: S系统财务管理组 | G51: S2职能系统－财经线/预算及职能系统财务管理部/S系统财务管理组 | H51: 39998 | I51: 高校招聘 | J51: 财经类－FN | K51: 预算管理 | L51: S9 | N51: T1# | Q51: G,O | U51: 56008.55 | V51: 0.083333 | W51: CNY | X51: 1 | Y51: 53386.03 | Z51: 0 | AA51: 168025.65 | AB51: 172480 | AC51: 64985 | AF51: 0 | AG51: 405490.65 | AH51: 7.5954449 | AI51: 405490.65 | AJ51: 7.5954449 | AK51: 6.3781789 | AQ51: 405490.65 | AR51: 7.5954449 | AS51: 1.9558685 | BL51: 1 | BM51: 50355 | BN51: 0 | BO51: 51325 | BP51: G,U | BQ51: T1# | BR51: 207320 | BS51: 4.1171681 | BT51: 0 | BU51: 207320 | BV51: 4.1171681 | BY51: 207320 | BZ51: 4.1171681 | CP51: 预算及职能系统财务管理部 | CQ51: 5,3 | CR51: 9 | CS51: T1# | CT51: N
A52: juliaLiao(廖雪瑶) | C52: 31719584 | D52: 税务部 | E52: 印章及文档管理组 | G52: S2职能系统－财经线/税务部/印章及文档管理组 | H52: 39421 | I52: 高校招聘 | J52: 财经类－FN | K52: 税务 | L52: S8 | N52: T2 | Q52: G,G | U52: 28976.2 | V52: 0.083333 | W52: CNY | X52: 1 | Y52: 27708.19 | Z52: 0 | AA52: 57952.4 | AB52: 34945 | AC52: 0 | AF52: 0 | AG52: 92897.4 | AH52: 3.3527055 | AI52: 92897.4 | AJ52: 3.3527055 | AK52: 3.3527055 | AQ52: 92897.4 | AR52: 3.3527055 | AS52: 1.1078338 | BL52: 1 | BM52: 24100 | BN52: 0 | BO52: 26240 | BP52: U,O | BQ52: T2 | BR52: 83855 | BS52: 3.4794606 | BT52: 0 | BU52: 83855 | BV52: 3.4794606 | BY52: 83855 | BZ52: 3.4794606 | CP52: 税务部 | CQ52: 3,3 | CR52: 8 | CS52: T2 | CT52: N
A53: marcusWei(魏松坚) | C53: 76307882 | D53: 财经IT管理部 | E53: 业务开发中心 | G53: S2职能系统－财经线/财经IT管理部/业务开发中心 | H53: 41314 | I53: 社会招聘 | J53: 技术研发类－TRD | K53: 应用开发 | L53: T7 | N53: T1 | Q53: G,G | U53: 31298 | V53: 0.083333 | W53: CNY | X53: 1 | Y53: 29306.23 | Z53: 0 | AA53: 62596 | AB53: 72315 | AC53: 38065 | AF53: 0 | AG53: 172976 | AH53: 5.9023627 | AI53: 172976 | AJ53: 5.9023627 | AK53: 4.6034922 | AQ53: 172976 | AR53: 5.9023627 | AS53: 1.2019735 | BL53: 1 | BM53: 27970 | BN53: 0 | BO53: 30180 | BP53: G,G | BQ53: T1 | BR53: 90595 | BS53: 3.2390061 | BT53: 53315 | BU53: 143910 | BV53: 5.1451555 | BY53: 143910 | BZ53: 5.1451555 | CP53: 财经IT管理部 | CQ53: 3,3 | CR53: 7 | CS53: T1 | CT53: N
A54: miaYu(于静) | C54: 59592158 | D54: CDG财务管理 | E54: 子公司财务管理组 | G54: S2职能系统－财经线/CDG财务管理/子公司财务管理组 | H54: 38797 | I54: 社会招聘 | J54: 财经类－FN | K54: 财务管理 | L54: S11 | N54: T1# | Q54: G,G | U54: 54160.8 | V54: 0.083333 | W54: CNY | X54: 1 | Y54: 50393.3 | Z54: 0 | AA54: 108321.6 | AB54: 181945 | AC54: 54645 | AF54: 0 | AG54: 344911.6 | AH54: 6.844394 | AI54: 344911.6 | AJ54: 6.844394 | AK54: 5.7600237 | AQ54: 344911.6 | AR54: 6.844394 | AS54: 1.9294674 | BL54: 1 | BM54: 43645 | BN54: 0 | BO54: 44275 | BP54: G,U | BQ54: T1# | BR54: 178760 | BS54: 4.0957727 | BT54: 0 | BU54: 178760 | BV54: 4.0957727 | BY54: 178760 | BZ54: 4.0957727 | CP54: CDG财务管理 | CQ54: 3,3 | CR54: 11 | CS54: T1# | CT54: N
A55: ellaMa(马曦) | C55: 81821398 | D55: 风险管理和内部控制 | E55: PCG风控中心 | G55: S2职能系统－财经线/风险管理和内部控制/PCG风控中心 | H55: 45600 | I55: 社会招聘 | J55: 财经类－FN | K55: 风险管理 | L55: S7 | N55: T1# | Q55: N,N | U55: 40465.4 | V55: 0.083333 | W55: CNY | X55: 0.156164 | Y55: 40465.4 | Z55: 0 | AA55: 6319.24 | AB55: 0 | AC55: 0 | AF55: 0 | AG55: 6319.24 | AH55: 0.15616403 | AI55: 6319.24 | AJ55: 0.15616403 | AK55: 0.15616403 | AQ55: 6319.24 | AR55: 0.15616403 | BM55: 0 | BN55: 0 | BO55: 0 | BR55: 0 | BT55: 0 | BU55: 0 | BY55: 0 | CP55: 风险管理和内部控制 | CR55: 7 | CS55: T1# | CT55: N
A56: evelynRen(任晶) | C56: 73942639 | D56: 行政支持中心 | E56: 秘书组 | G56: S2职能系统－财经线/行政支持中心/秘书组 | H56: 42099 | I56: 高校招聘 | J56: 财经类－FN | K56: 公司秘书 | L56: S8 | N56: T2 | Q56: G,G | U56: 44799.65 | V56: 0.083333 | W56: CNY | X56: 1 | Y56: 41547.05 | Z56: 0 | AA56: 89599.3 | AB56: 62255 | AC56: 0 | AF56: 0 | AG56: 151854.3 | AH56: 3.654996 | AI56: 151854.3 | AJ56: 3.654996 | AK56: 3.654996 | AQ56: 151854.3 | AR56: 3.654996 | AS56: 0.85880726 | BL56: 1 | BM56: 37995 | BN56: 0 | BO56: 39930 | BP56: O,G | BQ56: T2 | BR56: 176820 | BS56: 4.6537702 | BT56: 0 | BU56: 176820 | BV56: 4.6537702 | BY56: 176820 | BZ56: 4.6537702 | CP56: 行政支持中心 | CQ56: 3,3 | CR56: 8 | CS56: T2 | CT56: N
A57: penelopeGong(龚玲) | C57: 67957145 | D57: CFO办公室 | E57: 管理决策委员会 | G57: S2职能系统－财经线/CFO办公室/管理决策委员会 | H57: 45202 | I57: 社会招聘 | J57: 财经类－FN | K57: 投资者关系 | L57: S10 | N57: T1 | Q57: G,U | U57: 36092.25 | V57: 0.083333 | W57: CNY | X57: 1 | Y57: 34170.37 | Z57: 0 | AA57: 36092.25 | AB57: 76195 | AC57: 0 | AF57: 0 | AG57: 112287.25 | AH57: 3.2860999 | AI57: 112287.25 | AJ57: 3.2860999 | AK57: 3.2860999 | AQ57: 112287.25 | AR57: 3.2860999 | AS57: 14.842994 | BL57: 0.24383562 | BM57: 31040 | BN57: 0 | BO57: 31040 | BP57: N,G | BQ57: T1 | BR57: 7565 | BS57: 0.24371778 | BT57: 0 | BU57: 7565 | BV57: 0.24371778 | BY57: 7565 | BZ57: 0.24371778 | CP57: CFO办公室 | CQ57: 3,1 | CR57: 10 | CS57: T1 | CT57: N
A58: johnnyHong(洪国文) | C58: 1185225 | D58: 风险管理和内部控制 | E58: WXG风控中心 | G58: S2职能系统－财经线/风险管理和内部控制/WXG风控中心 | H58: 45140 | I58: 社会招聘 | J58: 财经类－FN | K58: 风险管理 | L58: S10 | N58: T2 | Q58: U,O | U58: 45198.7 | V58: 0.083333 | W58: CNY | X58: 1 | Y58: 44369.12 | Z58: 0 | AA58: 90397.4 | AB58: 60325 | AC58: 0 | AF58: 0 | AG58: 150722.4 | AH58: 3.3970113 | AI58: 150722.4 | AJ58: 3.3970113 | AK58: 3.3970113 | AQ58: 150722.4 | AR58: 3.3970113 | AS58: 9.3038519 | BL58: 0.41369863 | BM58: 39165 | BN58: 0 | BO58: 39165 | BP58: N,G | BQ58: T1# | BR58: 16200 | BS58: 0.41363462 | BT58: 0 | BU58: 16200 | BV58: 0.41363462 | BY58: 16200 | BZ58: 0.41363462 | CP58: 风险管理和内部控制 | CQ58: 5,1 | CR58: 10 | CS58: T2 | CT58: N
A59: elijahFan(范天骏) | C59: 1284819 | D59: S2人力资源中心 | E59: S2人力资源中心 | G59: S2职能系统－财经线/S2人力资源中心 | H59: 36501 | I59: 社会招聘 | J59: 财经类－FN | K59: 财经系统交付管理 | L59: S12 | N59: T2 | Q59: O,G | U59: 73282.2 | V59: 0.083333 | W59: CNY | X59: 1 | Y59: 66356.53 | Z59: 0 | AA59: 219846.6 | AB59: 87700 | AC59: 0 | AF59: 0 | AG59: 307546.6 | AH59: 4.6347601 | AI59: 307546.6 | AJ59: 4.6347601 | AK59: 4.6347601 | AQ59: 307546.6 | AR59: 4.6347601 | AS59: 1.997445 | BL59: 1 | BM59: 58965 | BN59: 0 | BO59: 64085 | BP59: G,U | BQ59: T2 | BR59: 153970 | BS59: 2.61121 | BT59: 0 | BU59: 153970 | BV59: 2.61121 | BY59: 153970 | BZ59: 2.61121 | CP59: S2人力资源中心 | CQ59: 5,3 | CR59: 12 | CS59: T2 | CT59: N
A60: katherineDuan(段畅苑) | C60: 90032706 | D60: 反舞弊调查部 | E60: 海外反舞弊工作组 | G60: S2职能系统－财经线/反舞弊调查部/海外反舞弊工作组 | H60: 43694 | I60: 高校招聘 | J60: 财经类－FN | K60: 风险管理 | L60: S5 | N60: T2 | Q60: O,G | U60: 17822.05 | V60: 0.083333 | W60: CNY | X60: 1 | Y60: 16296.29 | Z60: 0 | AA60: 53466.15 | AB60: 20935 | AC60: 0 | AF60: 0 | AG60: 74401.15 | AH60: 4.5655269 | AI60: 74401.15 | AJ60: 4.5655269 | AK60: 4.5655269 | AQ60: 74401.15 | AR60: 4.5655269 | AS60: 1.2665103 | BL60: 1 | BM60: 15605 | BN60: 0 | BO60: 16895 | BP60: U,O | BQ60: T2 | BR60: 58745 | BS60: 3.7644986 | BT60: 0 | BU60: 58745 | BV60: 3.7644986 | BY60: 58745 | BZ60: 3.7644986 | CP60: 反舞弊调查部 | CQ60: 5,3 | CR60: 5 | CS60: T2 | CT60: N
A61: richardWei(魏炜锐) | C61: 15306183 | D61: CSIG财务管理 | E61: 公线及费用财务管理中心 | G61: S2职能系统－财经线/CSIG财务管理/公线及费用财务管理中心 | H61: 41270 | I61: 高校招聘 | J61: 财经类－FN | K61: 财务管理 | L61: S9 | N61: T1 | Q61: O,G | U61: 55391.6 | V61: 0.083333 | W61: CNY | X61: 1 | Y61: 51738.61 | Z61: 0 | AA61: 166174.8 | AB61: 134960 | AC61: 92295 | AF61: 0 | AG61: 393429.8 | AH61: 7.6041819 | AI61: 393429.8 | AJ61: 7.6041819 | AK61: 5.820311 | AQ61: 393429.8 | AR61: 7.6041819 | AS61: 2.9861844 | BL61: 1 | BM61: 49410 | BN61: 0 | BO61: 53475 | BP61: G,U | BQ61: T1 | BR61: 131750 | BS61: 2.6664643 | BT61: 0 | BU61: 131750 | BV61: 2.6664643 | BY61: 131750 | BZ61: 2.6664643 | CP61: CSIG财务管理 | CQ61: 5,3 | CR61: 9 | CS61: T1 | CT61: N
A62: carolYan(严梅) | C62: 68786878 | D62: FiT财务管理 | E62: 财经金融专项中心 | G62: S2职能系统－财经线/FiT财务管理/财经金融专项中心 | H62: 37672 | I62: 社会招聘 | J62: 财经类－FN | K62: 财务管理 | L62: S7 | N62: T1# | Q62: G,O | U62: 39345.25 | V62: 0.083333 | W62: CNY | X62: 1 | Y62: 36381.36 | Z62: 0 | AA62: 118035.75 | AB62: 119530 | AC62: 75160 | AF62: 0 | AG62: 312725.75 | AH62: 8.5957685 | AI62: 312725.75 | AJ62: 8.5957685 | AK62: 6.5298755 | AQ62: 312725.75 | AR62: 8.5957685 | AS62: 2.4558328 | BL62: 1 | BM62: 34045 | BN62: 0 | BO62: 36515 | BP62: G,G | BQ62: T2 | BR62: 127340 | BS62: 3.7403437 | BT62: 0 | BU62: 127340 | BV62: 3.7403437 | BY62: 127340 | BZ62: 3.7403437 | CP62: FiT财务管理 | CQ62: 5,3 | CR62: 7 | CS62: T1# | CT62: N
A63: allisonYin(尹舒) | C63: 72479052 | D63: 财经投资并购及管理部 | E63: 行业及项目管理中心 | G63: S2职能系统－财经线/财经投资并购及管理部/行业及项目管理中心 | H63: 43149 | I63: 社会招聘 | J63: 财经类－FN | K63: 投资并购 | L63: S8 | N63: T1# | Q63: U,G | U63: 34567.75 | V63: 0.083333 | W63: CNY | X63: 1 | Y63: 31684.34 | Z63: 0 | AA63: 34567.75 | AB63: 111160 | AC63: 0 | AF63: 0 | AG63: 145727.75 | AH63: 4.599362 | AI63: 145727.75 | AJ63: 4.599362 | AK63: 4.599362 | AQ63: 145727.75 | AR63: 4.599362 | AS63: 0.76323225 | BL63: 1 | BM63: 27825 | BN63: 0 | BO63: 29130 | BP63: G,G | BQ63: T1# | BR63: 152815 | BS63: 5.4920036 | BT63: 38120 | BU63: 190935 | BV63: 6.8619946 | BY63: 190935 | BZ63: 6.8619946 | CP63: 财经投资并购及管理部 | CQ63: 3,1 | CR63: 8 | CS63: T1# | CT63: N
A64: hannahDuan(段婧) | C64: 30248804 | D64: 风险管理和内部控制 | E64: PCG风控中心 | G64: S2职能系统－财经线/风险管理和内部控制/PCG风控中心 | H64: 39548 | I64: 社会招聘 | J64: 财经类－FN | K64: 风险管理 | M64: L3-3 | N64: T1 | Q64: U,G | U64: 80887.8 | V64: 0.083333 | W64: CNY | X64: 1 | Y64: 79263.77 | Z64: 0 | AA64: 80887.8 | AB64: 173290 | AC64: 0 | AF64: 8835 | AG64: 254177.8 | AH64: 3.2067337 | AI64: 263012.8 | AJ64: 3.318197 | AK64: 3.318197 | AQ64: 263012.8 | AR64: 3.318197 | AS64: 1.700972 | BL64: 1 | BM64: 70515 | BN64: 0 | BO64: 74150 | BP64: U,G | BQ64: T1 | BR64: 154625 | BS64: 2.1927959 | BT64: 0 | BU64: 154625 | BV64: 2.1927959 | BY64: 154625 | BZ64: 2.1927959 | CP64: 风险管理和内部控制 | CQ64: 3,1 | CR64: L3-3 | CS64: T1 | CT64: N
A65: donaldXie(谢松) | C65: 8849775 | D65: 风险管理和内部控制 | E65: CSIG风控中心 | G65: S2职能系统－财经线/风险管理和内部控制/CSIG风控中心 | H65: 43768 | I65: 社会招聘 | J65: 财经类－FN | K65: 风险管理 | L65: S6 | N65: T1 | Q65: O,G | U65: 26913.15 | V65: 0.083333 | W65: CNY | X65: 1 | Y65: 25049.76 | Z65: 0 | AA65: 80739.45 | AB65: 66765 | AC65: 47245 | AF65: 0 | AG65: 194749.45 | AH65: 7.7745036 | AI65: 194749.45 | AJ65: 7.7745036 | AK65: 5.8884576 | AQ65: 194749.45 | AR65: 7.7745036 | AS65: 1.447736 | BL65: 1 | BM65: 24180 | BN65: 0 | BO65: 25655 | BP65: G,G | BQ65: T1 | BR65: 83565 | BS65: 3.4559553 | BT65: 50955 | BU65: 134520 | BV65: 5.5632754 | BY65: 134520 | BZ65: 5.5632754 | CP65: 风险管理和内部控制 | CQ65: 5,3 | CR65: 6 | CS65: T1 | CT65: N
A66: sophieYe(叶姗) | C66: 21898482 | D66: CDG财务管理 | E66: AMS客户管理中心 | G66: S2职能系统－财经线/CDG财务管理/AMS客户管理中心 | H66: 41959 | I66: 社会招聘 | J66: 财经类－FN | K66: 财务管理 | L66: S7 | N66: T1# | Q66: G,G | U66: 32295.85 | V66: 0.083333 | W66: CNY | X66: 1 | Y66: 29479.95 | Z66: 0 | AA66: 64591.7 | AB66: 106095 | AC66: 35870 | AF66: 0 | AG66: 206556.7 | AH66: 7.0066842 | AI66: 206556.7 | AJ66: 7.0066842 | AK66: 5.789925 | AQ66: 206556.7 | AR66: 7.0066842 | AS66: 1.5119067 | BL66: 1 | BM66: 26030 | BN66: 0 | BO66: 28275 | BP66: G,G | BQ66: T1 | BR66: 90870 | BS66: 3.490972 | BT66: 45750 | BU66: 136620 | BV66: 5.2485594 | BY66: 136620 | BZ66: 5.2485594 | CP66: CDG财务管理 | CQ66: 3,3 | CR66: 7 | CS66: T1# | CT66: N
A67: teresaQin(秦娜姗) | C67: 56287234 | D67: 财经IT管理部 | E67: 国际业务支持中心 | G67: S2职能系统－财经线/财经IT管理部/国际业务支持中心 | H67: 43578 | I67: 社会招聘 | J67: 技术研发类－TRD | K67: 应用开发 | L67: T8 | N67: T2 | Q67: G,G | U67: 40851.95 | V67: 0.083333 | W67: CNY | X67: 1 | Y67: 38290.87 | Z67: 0 | AA67: 81703.9 | AB67: 41250 | AC67: 0 | AF67: 0 | AG67: 122953.9 | AH67: 3.21105 | AI67: 122953.9 | AJ67: 3.21105 | AK67: 3.21105 | AQ67: 122953.9 | AR67: 3.21105 | AS67: 1.1392004 | BL67: 1 | BM67: 32710 | BN67: 0 | BO67: 32735 | BP67: G,G | BQ67: T2 | BR67: 107930 | BS67: 3.2996026 | BT67: 0 | BU67: 107930 | BV67: 3.2996026 | BY67: 107930 | BZ67: 3.2996026 | CP67: 财经IT管理部 | CQ67: 3,3 | CR67: 8 | CS67: T2 | CT67: N
A68: ellieCao(曹珊) | C68: 232081 | D68: CDG财务管理 | E68: CDG财务管理 | G68: S2职能系统－财经线/CDG财务管理 | H68: 38861 | I68: 高校招聘 | J68: 财经类－FN | K68: 财务管理 | L68: S6 | N68: T2 | Q68: G,G | U68: 26240.85 | V68: 0.083333 | W68: CNY | X68: 1 | Y68: 24685.06 | Z68: 0 | AA68: 52481.7 | AB68: 26755 | AC68: 0 | AF68: 0 | AG68: 79236.7 | AH68: 3.2099051 | AI68: 79236.7 | AJ68: 3.2099051 | AK68: 3.2099051 | AQ68: 79236.7 | AR68: 3.2099051 | AS68: 0.79304108 | BL68: 1 | BM68: 23075 | BN68: 0 | BO68: 24045 | BP68: O,G | BQ68: T2 | BR68: 99915 | BS68: 4.3300108 | BT68: 0 | BU68: 99915 | BV68: 4.3300108 | BY68: 99915 | BZ68: 4.3300108 | CP68: CDG财务管理 | CQ68: 3,3 | CR68: 6 | CS68: T2 | CT68: N
A69: aaliyahJia(贾静) | C69: 6715894 | D69: 风险管理和内部控制 | E69: WXG风控中心 | G69: S2职能系统－财经线/风险管理和内部控制/WXG风控中心 | H69: 44509 | I69: 社会招聘 | J69: 财经类－FN | K69: 风险管理 | L69: S7 | N69: T1# | Q69: G,G | U69: 27998.8 | V69: 0.083333 | W69: CNY | X69: 1 | Y69: 27506.56 | Z69: 0 | AA69: 55997.6 | AB69: 95960 | AC69: 36150 | AF69: 0 | AG69: 188107.6 | AH69: 6.838645 | AI69: 188107.6 | AJ69: 6.838645 | AK69: 5.5244131 | AQ69: 188107.6 | AR69: 6.838645 | AS69: 1.7269461 | BL69: 1 | BM69: 23675 | BN69: 0 | BO69: 24345 | BP69: G,O | BQ69: T2 | BR69: 108925 | BS69: 4.6008448 | BT69: 0 | BU69: 108925 | BV69: 4.6008448 | BY69: 108925 | BZ69: 4.6008448 | CP69: 风险管理和内部控制 | CQ69: 3,3 | CR69: 7 | CS69: T1# | CT69: N
A70: judithShi(石茜青) | C70: 87007219 | D70: 财经投资并购及管理部 | E70: 行业及项目管理中心 | G70: S2职能系统－财经线/财经投资并购及管理部/行业及项目管理中心 | H70: 36341 | I70: 社会招聘 | J70: 财经类－FN | K70: 投资并购 | L70: S8 | N70: Others | Q70: G,G | U70: 50342.95 | V70: 0.083333 | W70: CNY | X70: 1 | Y70: 46146.18 | Z70: 0 | AA70: 100685.9 | AB70: 46320 | AC70: 0 | AF70: 0 | AG70: 147005.9 | AH70: 3.185657 | AI70: 147005.9 | AJ70: 3.185657 | AK70: 3.185657 | AQ70: 147005.9 | AR70: 3.185657 | AS70: 0.76739436 | BL70: 1 | BM70: 43800 | BN70: 0 | BO70: 47740 | BP70: G,O | BQ70: Others | BR70: 191565 | BS70: 4.3736301 | BT70: 0 | BU70: 191565 | BV70: 4.3736301 | BY70: 191565 | BZ70: 4.3736301 | CP70: 财经投资并购及管理部 | CQ70: 3,3 | CR70: 8 | CS70: Others | CT70: N
A71: dylanQin(秦宇胜) | C71: 97156558 | D71: 预算及职能系统财务管理部 | E71: 预算管理中心 | G71: S2职能系统－财经线/预算及职能系统财务管理部/预算管理中心 | H71: 41411 | I71: 社会招聘 | J71: 财经类－FN | K71: 预算管理 | L71: S5 | N71: T1 | Q71: U,G | U71: 19998.85 | V71: 0.083333 | W71: CNY | X71: 1 | Y71: 18479.36 | Z71: 0 | AA71: 19998.85 | AB71: 41360 | AC71: 0 | AF71: 0 | AG71: 61358.85 | AH71: 3.3203991 | AI71: 61358.85 | AJ71: 3.3203991 | AK71: 3.3203991 | AQ71: 61358.85 | AR71: 3.3203991 | AS71: 0.67135894 | BL71: 1 | BM71: 17550 | BN71: 0 | BO71: 18850 | BP71: G,G | BQ71: T1 | BR71: 60325 | BS71: 3.4373219 | BT71: 31070 | BU71: 91395 | BV71: 5.2076923 | BY71: 91395 | BZ71: 5.2076923 | CP71: 预算及职能系统财务管理部 | CQ71: 3,1 | CR71: 5 | CS71: T1 | CT71: N
A72: bryanCai(蔡彤博) | C72: 49464189 | D72: 财会及报告管理部 | E72: 账务中心 | G72: S2职能系统－财经线/财会及报告管理部/账务中心 | H72: 41280 | I72: 高校招聘 | J72: 财经类－FN | K72: 会计 | L72: S10 | N72: T2 | Q72: G,U | U72: 64701.95 | V72: 0.083333 | W72: CNY | X72: 1 | Y72: 63132.21 | Z72: 0 | AA72: 64701.95 | AB72: 92650 | AC72: 0 | AF72: 0 | AG72: 157351.95 | AH72: 2.4924195 | AI72: 157351.95 | AJ72: 2.4924195 | AK72: 2.4924195 | AQ72: 157351.95 | AR72: 2.4924195 | AS72: 0.82734082 | BL72: 1 | BM72: 57970 | BN72: 0 | BO72: 60340 | BP72: G,G | BQ72: T2 | BR72: 190190 | BS72: 3.2808349 | BT72: 0 | BU72: 190190 | BV72: 3.2808349 | BY72: 190190 | BZ72: 3.2808349 | CP72: 财会及报告管理部 | CQ72: 3,1 | CR72: 10 | CS72: T2 | CT72: N
A73: andrewSu(苏斌锋) | C73: 18789816 | D73: FiT财务管理 | E73: 结算支持中心 | G73: S2职能系统－财经线/FiT财务管理/结算支持中心 | H73: 41574 | I73: 社会招聘 | J73: 财经类－FN | K73: 财务管理 | L73: S8 | N73: T1# | Q73: O,G | U73: 45232.2 | V73: 0.083333 | W73: CNY | X73: 1 | Y73: 43458.61 | Z73: 0 | AA73: 135696.6 | AB73: 152910 | AC73: 89280 | AF73: 0 | AG73: 377886.6 | AH73: 8.6953218 | AI73: 377886.6 | AJ73: 8.6953218 | AK73: 6.6409533 | AQ73: 377886.6 | AR73: 8.6953218 | AS73: 4.3853615 | BL73: 1 | BM73: 36395 | BN73: 0 | BO73: 37115 | BP73: G,U | BQ73: T2 | BR73: 86170 | BS73: 2.3676329 | BT73: 0 | BU73: 86170 | BV73: 2.3676329 | BY73: 86170 | BZ73: 2.3676329 | CP73: FiT财务管理 | CQ73: 5,3 | CR73: 8 | CS73: T1# | CT73: N
A74: harryHe(何松浩) | C74: 38943694 | D74: 风险管理和内部控制 | E74: IEG风控中心 | G74: S2职能系统－财经线/风险管理和内部控制/IEG风控中心 | H74: 38512 | I74: 高校招聘 | J74: 财经类－FN | K74: 风险管理 | L74: S7 | N74: Others | Q74: G,U | U74: 44533.85 | V74: 0.083333 | W74: CNY | X74: 1 | Y74: 41356.88 | Z74: 0 | AA74: 44533.85 | AB74: 40920 | AC74: 0 | AF74: 0 | AG74: 85453.85 | AH74: 2.0662548 | AI74: 85453.85 | AJ74: 2.0662548 | AK74: 2.0662548 | AQ74: 85453.85 | AR74: 2.0662548 | AS74: 0.46662944 | BL74: 1 | BM74: 38455 | BN74: 0 | BO74: 40980 | BP74: G,O | BQ74: T2 | BR74: 183130 | BS74: 4.7621896 | BT74: 0 | BU74: 183130 | BV74: 4.7621896 | BY74: 183130 | BZ74: 4.7621896 | CP74: 风险管理和内部控制 | CQ74: 3,1 | CR74: 7 | CS74: Others | CT74: N
A75: kyleJiang(江博宏) | C75: 41583343 | D75: 财经IT管理部 | E75: 公共支持中心 | G75: S2职能系统－财经线/财经IT管理部/公共支持中心 | H75: 38081 | I75: 社会招聘 | J75: 技术研发类－TRD | K75: 应用开发 | L75: T10 | N75: T1 | Q75: G,G | U75: 43452.1 | V75: 0.083333 | W75: CNY | X75: 1 | Y75: 41920.9 | Z75: 0 | AA75: 86904.2 | AB75: 94945 | AC75: 44970 | AF75: 0 | AG75: 226819.2 | AH75: 5.4106472 | AI75: 226819.2 | AJ75: 5.4106472 | AK75: 4.3379126 | AQ75: 226819.2 | AR75: 5.4106472 | AS75: 1.4844188 | BL75: 1 | BM75: 35860 | BN75: 0 | BO75: 37275 | BP75: G,O | BQ75: Others | BR75: 152800 | BS75: 4.2610151 | BT75: 0 | BU75: 152800 | BV75: 4.2610151 | BY75: 152800 | BZ75: 4.2610151 | CP75: 财经IT管理部 | CQ75: 3,3 | CR75: 10 | CS75: T1 | CT75: N
A76: brooklynHu(胡青茹) | C76: 96303989 | D76: CFO办公室 | E76: 财经专业通道委员会 | G76: S2职能系统－财经线/CFO办公室/财经专业通道委员会 | H76: 37496 | I76: 社会招聘 | J76: 财经类－FN | K76: 投资者关系 | L76: S9 | N76: Others | Q76: G,O | U76: 40525.65 | V76: 0.083333 | W76: CNY | X76: 1 | Y76: 39383.95 | Z76: 0 | AA76: 121576.95 | AB76: 25660 | AC76: 0 | AF76: 0 | AG76: 147236.95 | AH76: 3.7385013 | AI76: 147236.95 | AJ76: 3.7385013 | AK76: 3.7385013 | AQ76: 147236.95 | AR76: 3.7385013 | AS76: 1.1891209 | BL76: 1 | BM76: 35100 | BN76: 0 | BO76: 36800 | BP76: G,G | BQ76: Others | BR76: 123820 | BS76: 3.5276353 | BT76: 0 | BU76: 123820 | BV76: 3.5276353 | BY76: 123820 | BZ76: 3.5276353 | CP76: CFO办公室 | CQ76: 5,3 | CR76: 9 | CS76: Others | CT76: N
... A85: sharonShao(邵红沁) | C85: 95581555 | D85: 财经IT管理部 | E85: 国际业务支持中心 | G85: S2职能系统－财经线/财经IT管理部/国际业务支持中心 | H85: 41880 | I85: 社会招聘 | J85: 技术研发类－TRD | K85: 应用开发 | L85: T11 | N85: T1 | Q85: O,O | U85: 51992.2 | V85: 0.083333 | W85: CNY | X85: 1 | Y85: 50755.01 | Z85: 0 | AA85: 207968.8 | AB85: 123280 | AC85: 75745 | AF85: 0 | AG85: 406993.8 | AH85: 8.0187907 | AI85: 406993.8 | AJ85: 8.0187907 | AK85: 6.5264257 | AQ85: 406993.8 | AR85: 8.0187907 | AS85: 1.4554466 | BL85: 1 | BM85: 43680 | BN85: 0 | BO85: 47510 | BP85: G,O | BQ85: T1 | BR85: 196660 | BS85: 4.5022894 | BT85: 82975 | BU85: 279635 | BV85: 6.4019002 | BY85: 279635 | BZ85: 6.4019002 | CP85: 财经IT管理部 | CQ85: 5,5 | CR85: 11 | CS85: T1 | CT85: N
A86: frankWan(万刚) | C86: 70233595 | D86: PCG财务管理 | E86: 应用宝财务管理组 | G86: S2职能系统－财经线/PCG财务管理/应用宝财务管理组 | H86: 38079 | I86: 社会招聘 | J86: 财经类－FN | K86: 财务管理 | M86: L2-2 | N86: T1 | Q86: U,G | U86: 47380.1 | V86: 0.083333 | W86: CNY | X86: 1 | Y86: 44789.85 | Z86: 0 | AA86: 47380.1 | AB86: 109095 | AC86: 0 | AF86: 13215 | AG86: 156475.1 | AH86: 3.4935393 | AI86: 169690.1 | AJ86: 3.7885838 | AK86: 3.7885838 | AQ86: 169690.1 | AR86: 3.7885838 | AS86: 0.72069015 | BL86: 1 | BM86: 40595 | BN86: 0 | BO86: 41025 | BP86: O,G | BQ86: T1 | BR86: 181045 | BS86: 4.4597857 | BT86: 54410 | BU86: 235455 | BV86: 5.8000985 | BY86: 235455 | BZ86: 5.8000985 | CP86: PCG财务管理 | CQ86: 3,1 | CR86: L2-2 | CS86: T1 | CT86: N
A87: gabrielHu(胡雄) | C87: 24456997 | D87: 预算及职能系统财务管理部 | E87: S系统财务管理组 | G87: S2职能系统－财经线/预算及职能系统财务管理部/S系统财务管理组 | H87: 37761 | I87: 高校招聘 | J87: 财经类－FN | K87: 预算管理 | L87: S8 | N87: T2 | Q87: G,G | U87: 45698.5 | V87: 0.083333 | W87: CNY | X87: 1 | Y87: 44354.48 | Z87: 0 | AA87: 91397 | AB87: 59415 | AC87: 0 | AF87: 0 | AG87: 150812 | AH87: 3.4001526 | AI87: 150812 | AJ87: 3.4001526 | AK87: 3.4001526 | AQ87: 150812 | AR87: 3.4001526 | AS87: 1.2249188 | BL87: 1 | BM87: 36575 | BN87: 0 | BO87: 39985 | BP87: G,G | BQ87: Others | BR87: 123120 | BS87: 3.3662338 | BT87: 0 | BU87: 123120 | BV87: 3.3662338 | BY87: 123120 | BZ87: 3.3662338 | CP87: 预算及职能系统财务管理部 | CQ87: 3,3 | CR87: 8 | CS87: T2 | CT87: N
A88: marthaJia(贾薇) | C88: 16145259 | D88: 预算及职能系统财务管理部 | E88: 预算管理中心 | G88: S2职能系统－财经线/预算及职能系统财务管理部/预算管理中心 | H88: 37051 | I88: 社会招聘 | J88: 财经类－FN | K88: 预算管理 | L88: S11 | N88: Others | Q88: G,O | U88: 56930.05 | V88: 0.083333 | W88: CNY | X88: 1 | Y88: 51513.4 | Z88: 0 | AA88: 170790.15 | AB88: 38835 | AC88: 0 | AF88: 0 | AG88: 209625.15 | AH88: 4.0693324 | AI88: 209625.15 | AJ88: 4.0693324 | AK88: 4.0693324 | AQ88: 209625.15 | AR88: 4.0693324 | AS88: 1.2159231 | BL88: 1 | BM88: 46205 | BN88: 0 | BO88: 50070 | BP88: G,G | BQ88: Others | BR88: 172400 | BS88: 3.7311979 | BT88: 0 | BU88: 172400 | BV88: 3.7311979 | BY88: 172400 | BZ88: 3.7311979 | CP88: 预算及职能系统财务管理部 | CQ88: 5,3 | CR88: 11 | CS88: Others | CT88: N
A89: albertGong(龚炜骏) | C89: 47206082 | D89: 在线视频财务管理中心 | E89: OVB长视频财务管理组 | G89: S2职能系统－财经线/在线视频财务管理中心/OVB长视频财务管理组 | H89: 41079 | I89: 社会招聘 | J89: 财经类－FN | K89: 财务管理 | L89: S7 | N89: T1# | Q89: O,G | U89: 41942.2 | V89: 0.083333 | W89: CNY | X89: 1 | Y89: 41513.74 | Z89: 0 | AA89: 125826.6 | AB89: 138185 | AC89: 53050 | AF89: 0 | AG89: 317061.6 | AH89: 7.6375099 | AI89: 317061.6 | AJ89: 7.6375099 | AK89: 6.3596197 | AQ89: 317061.6 | AR89: 7.6375099 | AS89: 2.2051857 | BL89: 1 | BM89: 35500 | BN89: 0 | BO89: 35550 | BP89: U,G | BQ89: T1# | BR89: 143780 | BS89: 4.0501408 | BT89: 0 | BU89: 143780 | BV89: 4.0501408 | BY89: 143780 | BZ89: 4.0501408 | CP89: 在线视频财务管理中心 | CQ89: 5,3 | CR89: 7 | CS89: T1# | CT89: N
A90: ericZhang(张辉健) | C90: 9332643 | D90: 风险管理和内部控制 | E90: CSIG风控中心 | G90: S2职能系统－财经线/风险管理和内部控制/CSIG风控中心 | H90: 43781 | I90: 社会招聘 | J90: 财经类－FN | K90: 风险管理 | L90: S8 | N90: T1 | Q90: G,G | U90: 29085.4 | V90: 0.083333 | W90: CNY | X90: 1 | Y90: 28255.85 | Z90: 0 | AA90: 58170.8 | AB90: 59200 | AC90: 39235 | AF90: 0 | AG90: 156605.8 | AH90: 5.5424204 | AI90: 156605.8 | AJ90: 5.5424204 | AK90: 4.1538584 | AQ90: 156605.8 | AR90: 5.5424204 | AS90: 1.2746687 | BL90: 1 | BM90: 24880 | BN90: 0 | BO90: 26045 | BP90: G,G | BQ90: T1 | BR90: 83630 | BS90: 3.3613344 | BT90: 39230 | BU90: 122860 | BV90: 4.9381029 | BY90: 122860 | BZ90: 4.9381029 | CP90: 风险管理和内部控制 | CQ90: 3,3 | CR90: 8 | CS90: T1 | CT90: N
A91: ellaQian(钱瑶) | C91: 83816533 | D91: 风险管理和内部控制 | E91: WXG风控中心 | G91: S2职能系统－财经线/风险管理和内部控制/WXG风控中心 | H91: 38526 | I91: 社会招聘 | J91: 财经类－FN | K91: 风险管理 | L91: S6 | N91: T1# | Q91: O,G | U91: 28259.6 | V91: 0.083333 | W91: CNY | X91: 1 | Y91: 26478.39 | Z91: 0 | AA91: 84778.8 | AB91: 93865 | AC91: 55465 | AF91: 0 | AG91: 234108.8 | AH91: 8.8415043 | AI91: 234108.8 | AJ91: 8.8415043 | AK91: 6.7467773 | AQ91: 234108.8 | AR91: 8.8415043 | AS91: 1.3298614 | BL91: 1 | BM91: 23170 | BN91: 0 | BO91: 23860 | BP91: O,G | BQ91: T1# | BR91: 152090 | BS91: 6.5640915 | BT91: 23950 | BU91: 176040 | BV91: 7.5977557 | BY91: 176040 | BZ91: 7.5977557 | CP91: 风险管理和内部控制 | CQ91: 5,3 | CR91: 6 | CS91: T1# | CT91: N
A92: harryWang(汪天) | C92: 80292865 | D92: 财经投资并购及管理部 | E92: 行业及项目管理中心 | G92: S2职能系统－财经线/财经投资并购及管理部/行业及项目管理中心 | H92: 36288 | I92: 高校招聘 | J92: 财经类－FN | K92: 投资并购 | L92: S6 | N92: T1 | Q92: G,G | U92: 28386.3 | V92: 0.083333 | W92: CNY | X92: 1 | Y92: 28008.74 | Z92: 0 | AA92: 56772.6 | AB92: 62470 | AC92: 39915 | AF92: 0 | AG92: 159157.6 | AH92: 5.6824263 | AI92: 159157.6 | AJ92: 5.6824263 | AK92: 4.2573354 | AQ92: 159157.6 | AR92: 5.6824263 | AS92: 1.4370889 | BL92: 1 | BM92: 23940 | BN92: 0 | BO92: 24200 | BP92: G,G | BQ92: T1 | BR92: 78655 | BS92: 3.2855054 | BT92: 32095 | BU92: 110750 | BV92: 4.6261487 | BY92: 110750 | BZ92: 4.6261487 | CP92: 财经投资并购及管理部 | CQ92: 3,3 | CR92: 6 | CS92: T1 | CT92: N
A93: maryKong(孔慧) | C93: 67874412 | D93: CDG财务管理 | E93: AMS收入支持中心 | G93: S2职能系统－财经线/CDG财务管理/AMS收入支持中心 | H93: 36786 | I93: 社会招聘 | J93: 财经类－FN | K93: 财务管理 | L93: S6 | N93: T1# | Q93: G,G | U93: 34558.4 | V93: 0.083333 | W93: CNY | X93: 1 | Y93: 31140.68 | Z93: 0 | AA93: 69116.8 | AB93: 115780 | AC93: 60785 | AF93: 0 | AG93: 245681.8 | AH93: 7.8894167 | AI93: 245681.8 | AJ93: 7.8894167 | AK93: 5.9374683 | AQ93: 245681.8 | AR93: 7.8894167 | AS93: 1.1904918 | BL93: 1 | BM93: 30525 | BN93: 0 | BO93: 31285 | BP93: G,G | BQ93: T1# | BR93: 165265 | BS93: 5.4140868 | BT93: 41105 | BU93: 206370 | BV93: 6.760688 | BY93: 206370 | BZ93: 6.760688 | CP93: CDG财务管理 | CQ93: 3,3 | CR93: 6 | CS93: T1# | CT93: N
A94: brooklynShao(邵芳薇) | C94: 57363896 | D94: CSIG财务管理 | E94: 综合财务管理中心 | G94: S2职能系统－财经线/CSIG财务管理/综合财务管理中心 | H94: 38079 | I94: 社会招聘 | J94: 财经类－FN | K94: 财务管理 | M94: L3-1 | N94: T1# | Q94: O,G | U94: 78638.05 | V94: 0.083333 | W94: CNY | X94: 1 | Y94: 76586.89 | Z94: 0 | AA94: 235914.15 | AB94: 252925 | AC94: 106545 | AF94: 72710 | AG94: 595384.15 | AH94: 7.7739695 | AI94: 668094.15 | AJ94: 8.7233487 | AK94: 7.3321837 | AQ94: 668094.15 | AR94: 8.7233487 | AS94: 4.51766 | BL94: 1 | BM94: 62915 | BN94: 0 | BO94: 66620 | BP94: G,U | BQ94: T2 | BR94: 147885 | BS94: 2.3505523 | BT94: 0 | BU94: 147885 | BV94: 2.3505523 | BY94: 147885 | BZ94: 2.3505523 | CP94: CSIG财务管理 | CQ94: 5,3 | CR94: L3-1 | CS94: T1# | CT94: N
A95: natalieLei(雷薇琳) | C95: 98812364 | D95: 财经IT管理部 | E95: 国际业务支持中心 | G95: S2职能系统－财经线/财经IT管理部/国际业务支持中心 | H95: 40510 | I95: 社会招聘 | J95: 技术研发类－TRD | K95: 应用开发 | L95: T7 | N95: T1 | Q95: G,G | U95: 27845.5 | V95: 0.083333 | W95: CNY | X95: 1 | Y95: 26101.71 | Z95: 0 | AA95: 55691 | AB95: 68185 | AC95: 51590 | AF95: 0 | AG95: 175466 | AH95: 6.7223948 | AI95: 175466 | AJ95: 6.7223948 | AK95: 4.745896 | AQ95: 175466 | AR95: 6.7223948 | AS95: 2.0213813 | BL95: 1 | BM95: 24605 | BN95: 0 | BO95: 26730 | BP95: G,G | BQ95: Others | BR95: 86805 | BS95: 3.5279415 | BT95: 0 | BU95: 86805 | BV95: 3.5279415 | BY95: 86805 | BZ95: 3.5279415 | CP95: 财经IT管理部 | CQ95: 3,3 | CR95: 7 | CS95: T1 | CT95: N
A96: avaLu(卢晗) | C96: 67313137 | D96: CDG财务管理 | E96: AMS客户管理中心 | G96: S2职能系统－财经线/CDG财务管理/AMS客户管理中心 | H96: 43605 | I96: 社会招聘 | J96: 财经类－FN | K96: 财务管理 | L96: S7 | N96: T1 | Q96: U,G | U96: 37585.4 | V96: 0.083333 | W96: CNY | X96: 1 | Y96: 34555.27 | Z96: 0 | AA96: 37585.4 | AB96: 91305 | AC96: 0 | AF96: 0 | AG96: 128890.4 | AH96: 3.7299781 | AI96: 128890.4 | AJ96: 3.7299781 | AK96: 3.7299781 | AQ96: 128890.4 | AR96: 3.7299781 | AS96: 0.70001575 | BL96: 1 | BM96: 31340 | BN96: 0 | BO96: 31625 | BP96: O,G | BQ96: T1 | BR96: 141740 | BS96: 4.5226548 | BT96: 42385 | BU96: 184125 | BV96: 5.8750798 | BY96: 184125 | BZ96: 5.8750798 | CP96: CDG财务管理 | CQ96: 3,1 | CR96: 7 | CS96: T1 | CT96: N
A97: rachelLiang(梁馨) | C97: 57318711 | D97: CSIG财务管理 | E97: 产品财务管理中心 | G97: S2职能系统－财经线/CSIG财务管理/产品财务管理中心 | H97: 41903 | I97: 社会招聘 | J97: 财经类－FN | K97: 财务管理 | L97: S9 | N97: T1 | Q97: G,G | U97: 49673.7 | V97: 0.083333 | W97: CNY | X97: 1 | Y97: 48753.32 | Z97: 0 | AA97: 99347.4 | AB97: 101730 | AC97: 59130 | AF97: 0 | AG97: 260207.4 | AH97: 5.3372242 | AI97: 260207.4 | AJ97: 5.3372242 | AK97: 4.1243837 | AQ97: 260207.4 | AR97: 5.3372242 | AS97: 0.95711989 | BL97: 1 | BM97: 40060 | BN97: 0 | BO97: 43430 | BP97: O,G | BQ97: T1 | BR97: 194335 | BS97: 4.8510984 | BT97: 77530 | BU97: 271865 | BV97: 6.7864453 | BY97: 271865 | BZ97: 6.7864453 | CP97: CSIG财务管理 | CQ97: 3,3 | CR97: 9 | CS97: T1 | CT97: N
A98: carolineYe(叶茜) | C98: 61654480 | D98: 财经IT管理部 | E98: 业务开发中心 | G98: S2职能系统－财经线/财经IT管理部/业务开发中心 | H98: 40307 | I98: 社会招聘 | J98: 技术研发类－TRD | K98: 应用开发 | L98: T10 | N98: Others | Q98: G,U | U98: 46332.75 | V98: 0.083333 | W98: CNY | X98: 1 | Y98: 42147.05 | Z98: 0 | AA98: 46332.75 | AB98: 32035 | AC98: 0 | AF98: 0 | AG98: 78367.75 | AH98: 1.8593887 | AI98: 78367.75 | AJ98: 1.8593887 | AK98: 1.8593887 | AQ98: 78367.75 | AR98: 1.8593887 | AS98: 0.57874418 | BL98: 1 | BM98: 39895 | BN98: 0 | BO98: 41000 | BP98: G,G | BQ98: Others | BR98: 135410 | BS98: 3.3941597 | BT98: 0 | BU98: 135410 | BV98: 3.3941597 | BY98: 135410 | BZ98: 3.3941597 | CP98: 财经IT管理部 | CQ98: 3,1 | CR98: 10 | CS98: Others | CT98: N
A99: juliaGao(高嘉涵) | C99: 36653069 | D99: PCG财务管理 | E99: 在线视频财务管理中心 | G99: S2职能系统－财经线/PCG财务管理/在线视频财务管理中心 | H99: 43864 | I99: 社会招聘 | J99: 财经类－FN | K99: 财务管理 | L99: S6 | N99: T1 | Q99: U,G | U99: 33394.25 | V99: 0.083333 | W99: CNY | X99: 1 | Y99: 30338.72 | Z99: 0 | AA99: 33394.25 | AB99: 78230 | AC99: 0 | AF99: 0 | AG99: 111624.25 | AH99: 3.679267 | AI99: 111624.25 | AJ99: 3.679267 | AK99: 3.679267 | AQ99: 111624.25 | AR99: 3.679267 | AS99: 0.9480169 | BL99: 1 | BM99: 26955 | BN99: 0 | BO99: 28455 | BP99: O,G | BQ99: Others | BR99: 117745 | BS99: 4.3682063 | BT99: 0 | BU99: 117745 | BV99: 4.3682063 | BY99: 117745 | BZ99: 4.3682063 | CP99: PCG财务管理 | CQ99: 3,1 | CR99: 6 | CS99: T1 | CT99: N
A100: loganLuo(罗坚) | C100: 19695058 | D100: 资金管理 | E100: 资金结算及风险控制中心 | G100: S2职能系统－财经线/资金管理/资金结算及风险控制中心 | H100: 43979 | I100: 高校招聘 | J100: 财经类－FN | K100: 资金管理 | L100: S5 | N100: T2 | Q100: G,O | U100: 23474.1 | V100: 0.083333 | W100: CNY | X100: 1 | Y100: 21269.32 | Z100: 0 | AA100: 70422.3 | AB100: 26485 | AC100: 0 | AF100: 0 | AG100: 96907.3 | AH100: 4.5562011 | AI100: 96907.3 | AJ100: 4.5562011 | AK100: 4.5562011 | AQ100: 96907.3 | AR100: 4.5562011 | AS100: 1.5717671 | BL100: 1 | BM100: 19375 | BN100: 0 | BO100: 19625 | BP100: G,G | BQ100: T2 | BR100: 61655 | BS100: 3.1821935 | BT100: 0 | BU100: 61655 | BV100: 3.1821935 | BY100: 61655 | BZ100: 3.1821935 | CP100: 资金管理 | CQ100: 5,3 | CR100: 5 | CS100: T2 | CT100: N
A101: juanHe(何强) | C101: 67678333 | D101: 预算及职能系统财务管理部 | E101: 预算管理中心 | G101: S2职能系统－财经线/预算及职能系统财务管理部/预算管理中心 | H101: 43196 | I101: 社会招聘 | J101: 财经类－FN | K101: 预算管理 | L101: S7 | N101: T2 | Q101: G,G | U101: 34087.65 | V101: 0.083333 | W101: CNY | X101: 1 | Y101: 32306.54 | Z101: 0 | AA101: 68175.3 | AB101: 43130 | AC101: 0 | AF101: 0 | AG101: 111305.3 | AH101: 3.4452869 | AI101: 111305.3 | AJ101: 3.4452869 | AK101: 3.4452869 | AQ101: 111305.3 | AR101: 3.4452869 | AS101: 0.83773228 | BL101: 1 | BM101: 29865 | BN101: 0 | BO101: 31850 | BP101: O,G | BQ101: T2 | BR101: 132865 | BS101: 4.4488532 | BT101: 0 | BU101: 132865 | BV101: 4.4488532 | BY101: 132865 | BZ101: 4.4488532 | CP101: 预算及职能系统财务管理部 | CQ101: 3,3 | CR101: 7 | CS101: T2 | CT101: N
A102: rileyLiao(廖琪) | C102: 64687592 | D102: 财会及报告管理部 | E102: 海外财会管理中心 | G102: S2职能系统－财经线/财会及报告管理部/海外财会管理中心 | H102: 36779 | I102: 高校招聘 | J102: 财经类－FN | K102: 会计 | L102: S9 | N102: T1 | Q102: G,O | U102: 43009.9 | V102: 0.083333 | W102: CNY | X102: 1 | Y102: 42550.79 | Z102: 0 | AA102: 129029.7 | AB102: 92060 | AC102: 49715 | AF102: 0 | AG102: 270804.7 | AH102: 6.3642696 | AI102: 270804.7 | AJ102: 6.3642696 | AK102: 5.1959012 | AQ102: 270804.7 | AR102: 6.3642696 | AS102: 1.4406038 | BL102: 1 | BM102: 36620 | BN102: 0 | BO102: 38495 | BP102: G,G | BQ102: T1 | BR102: 120180 | BS102: 3.2818132 | BT102: 67800 | BU102: 187980 | BV102: 5.1332605 | BY102: 187980 | BZ102: 5.1332605 | CP102: 财会及报告管理部 | CQ102: 5,3 | CR102: 9 | CS102: T1 | CT102: N
A103: lauraRen(任燕媛) | C103: 70106260 | D103: 审计监察 | E103: 海外业务审计组 | G103: S2职能系统－财经线/审计监察/海外业务审计组 | H103: 42815 | I103: 社会招聘 | J103: 财经类－FN | K103: 风险管理 | L103: S6 | N103: T2 | Q103: U,G | U103: 28624.45 | V103: 0.083333 | W103: CNY | X103: 1 | Y103: 26343.02 | Z103: 0 | AA103: 28624.45 | AB103: 29150 | AC103: 0 | AF103: 0 | AG103: 57774.45 | AH103: 2.1931597 | AI103: 57774.45 | AJ103: 2.1931597 | AK103: 2.1931597 | AQ103: 57774.45 | AR103: 2.1931597 | AS103: 0.51804035 | BL103: 1 | BM103: 23455 | BN103: 0 | BO103: 24930 | BP103: G,O | BQ103: T2 | BR103: 111525 | BS103: 4.7548497 | BT103: 0 | BU103: 111525 | BV103: 4.7548497 | BY103: 111525 | BZ103: 4.7548497 | CP103: 审计监察 | CQ103: 3,1 | CR103: 6 | CS103: T2 | CT103: N
A104: emilyHuang(黄雪) | C104: 74401342 | D104: 财会及报告管理部 | E104: 资产管理组 | G104: S2职能系统－财经线/财会及报告管理部/资产管理组 | H104: 37875 | I104: 社会招聘 | J104: 财经类－FN | K104: 会计 | L104: S5 | N104: T1# | Q104: U,G | U104: 29657.3 | V104: 0.083333 | W104: CNY | X104: 1 | Y104: 28200.75 | Z104: 0 | AA104: 29657.3 | AB104: 91695 | AC104: 0 | AF104: 0 | AG104: 121352.3 | AH104: 4.3031586 | AI104: 121352.3 | AJ104: 4.3031586 | AK104: 4.3031586 | AQ104: 121352.3 | AR104: 4.3031586 | AS104: 0.71339643 | BL104: 1 | BM104: 26000 | BN104: 0 | BO104: 26300 | BP104: G,G | BQ104: T1# | BR104: 132290 | BS104: 5.0880769 | BT104: 37815 | BU104: 170105 | BV104: 6.5425 | BY104: 170105 | BZ104: 6.5425 | CP104: 财会及报告管理部 | CQ104: 3,1 | CR104: 5 | CS104: T1# | CT104: N
A105: noraWang(王涵) | C105: 32477024 | D105: 财经IT管理部 | E105: 业务开发中心 | G105: S2职能系统－财经线/财经IT管理部/业务开发中心 | H105: 36861 | I105: 社会招聘 | J105: 技术研发类－TRD | K105: 应用开发 | L105: T12 | N105: T1 | Q105: G,G | U105: 61327.25 | V105: 0.083333 | W105: CNY | X105: 1 | Y105: 57608.93 | Z105: 0 | AA105: 122654.5 | AB105: 125660 | AC105: 95510 | AF105: 0 | AG105: 343824.5 | AH105: 5.9682501 | AI105: 343824.5 | AJ105: 5.9682501 | AK105: 4.3103474 | AQ105: 343824.5 | AR105: 5.9682501 | AS105: 2.0504801 | BL105: 1 | BM105: 50155 | BN105: 0 | BO105: 51355 | BP105: U,O | BQ105: T1 | BR105: 167680 | BS105: 3.343236 | BT105: 0 | BU105: 167680 | BV105: 3.343236 | BY105: 167680 | BZ105: 3.343236 | CP105: 财经IT管理部 | CQ105: 3,3 | CR105: 12 | CS105: T1 | CT105: N
A106: richardHe(何宇刚) | C106: 50938378 | D106: 审计监察 | E106: 常规审计组 | G106: S2职能系统－财经线/审计监察/常规审计组 | H106: 45011 | I106: 社会招聘 | J106: 财经类－FN | K106: 风险管理 | M106: L2-2 | N106: T2 | Q106: O,G | U106: 75193.5 | V106: 0.083333 | W106: CNY | X106: 1 | Y106: 68804.8 | Z106: 0 | AA106: 225580.5 | AB106: 111895 | AC106: 0 | AF106: 16975 | AG106: 337475.5 | AH106: 4.904825 | AI106: 354450.5 | AJ106: 5.1515374 | AK106: 5.1515374 | AQ106: 354450.5 | AR106: 5.1515374 | AS106: 7.0306556 | BL106: 0.76712329 | BM106: 63385 | BN106: 0 | BO106: 65725 | BP106: G,O | BQ106: T2 | BR106: 50415 | BS106: 0.79537746 | BT106: 0 | BU106: 50415 | BV106: 0.79537746 | BY106: 50415 | BZ106: 0.79537746 | CP106: 审计监察 | CQ106: 5,3 | CR106: L2-2 | CS106: T2 | CT106: N
A107: gregoryLiang(梁华梓) | C107: 89699150 | D107: CDG财务管理 | E107: CDG财务管理 | G107: S2职能系统－财经线/CDG财务管理 | H107: 37347 | I107: 高校招聘 | J107: 财经类－FN | K107: 财务管理 | L107: S9 | N107: T1 | Q107: G,G | U107: 42870 | V107: 0.083333 | W107: CNY | X107: 1 | Y107: 41833.29 | Z107: 0 | AA107: 85740 | AB107: 103815 | AC107: 72145 | AF107: 0 | AG107: 261700 | AH107: 6.2557834 | AI107: 261700 | AJ107: 6.2557834 | AK107: 4.5311999 | AQ107: 261700 | AR107: 6.2557834 | AS107: 1.5340876 | BL107: 1 | BM107: 34365 | BN107: 0 | BO107: 34615 | BP107: G,G | BQ107: T1 | BR107: 118680 | BS107: 3.4535137 | BT107: 51910 | BU107: 170590 | BV107: 4.9640623 | BY107: 170590 | BZ107: 4.9640623 | CP107: CDG财务管理 | CQ107: 3,3 | CR107: 9 | CS107: T1 | CT107: N
A108: karenQin(秦曼嫣) | C108: 96387865 | D108: FiT财务管理 | E108: 结算支持中心 | G108: S2职能系统－财经线/FiT财务管理/结算支持中心 | H108: 44788 | I108: 高校招聘 | J108: 财经类－FN | K108: 财务管理 | L108: S9 | N108: T1 | Q108: G,G | U108: 49212.75 | V108: 0.083333 | W108: CNY | X108: 1 | Y108: 45101.37 | Z108: 0 | AA108: 98425.5 | AB108: 111760 | AC108: 63090 | AF108: 0 | AG108: 273275.5 | AH108: 6.0591397 | AI108: 273275.5 | AJ108: 6.0591397 | AK108: 4.6602908 | AQ108: 273275.5 | AR108: 6.0591397 | AS108: 3.0074891 | BL108: 1 | BM108: 41250 | BN108: 0 | BO108: 43785 | BP108: G,U | BQ108: T1 | BR108: 90865 | BS108: 2.2027879 | BT108: 0 | BU108: 90865 | BV108: 2.2027879 | BY108: 90865 | BZ108: 2.2027879 | CP108: FiT财务管理 | CQ108: 3,3 | CR108: 9 | CS108: T1 | CT108: N
A109: donnaGao(高慧) | C109: 58410706 | D109: 行政支持中心 | E109: 秘书组 | G109: S2职能系统－财经线/行政支持中心/秘书组 | H109: 43638 | I109: 高校招聘 | J109: 财经类－FN | K109: 公司秘书 | L109: S9 | N109: T1 | Q109: G,G | U109: 38387.1 | V109: 0.083333 | W109: CNY | X109: 1 | Y109: 37977.01 | Z109: 0 | AA109: 76774.2 | AB109: 85615 | AC109: 56395 | AF109: 0 | AG109: 218784.2 | AH109: 5.7609643 | AI109: 218784.2 | AJ109: 5.7609643 | AK109: 4.275987 | AQ109: 218784.2 | AR109: 5.7609643 | AS109: 1.3966435 | BL109: 1 | BM109: 33365 | BN109: 0 | BO109: 34750 | BP109: G,G | BQ109: T1 | BR109: 111480 | BS109: 3.3412258 | BT109: 45170 | BU109: 156650 | BV109: 4.6950397 | BY109: 156650 | BZ109: 4.6950397 | CP109: 行政支持中心 | CQ109: 3,3 | CR109: 9 | CS109: T1 | CT109: N
A110: lauraYe(叶青) | C110: 75107083 | D110: 财会及报告管理部 | E110: 应收管理中心 | G110: S2职能系统－财经线/财会及报告管理部/应收管理中心 | H110: 36676 | I110: 社会招聘 | J110: 财经类－FN | K110: 会计 | L110: S7 | N110: T1 | Q110: O,G | U110: 36803.3 | V110: 0.083333 | W110: CNY | X110: 1 | Y110: 35816.59 | Z110: 0 | AA110: 110409.9 | AB110: 75480 | AC110: 46110 | AF110: 0 | AG110: 231999.9 | AH110: 6.4774424 | AI110: 231999.9 | AJ110: 6.4774424 | AK110: 5.1900502 | AQ110: 231999.9 | AR110: 6.4774424 | AS110: 1.3340611 | BL110: 1 | BM110: 29945 | BN110: 0 | BO110: 30985 | BP110: G,O | BQ110: T1 | BR110: 129145 | BS110: 4.31274 | BT110: 44760 | BU110: 173905 | BV110: 5.8074804 | BY110: 173905 | BZ110: 5.8074804 | CP110: 财会及报告管理部 | CQ110: 5,3 | CR110: 7 | CS110: T1 | CT110: N
A111: sophiaLi(李玉梦) | C111: 50280560 | D111: 财经投资并购及管理部 | E111: 行业及项目管理中心 | G111: S2职能系统－财经线/财经投资并购及管理部/行业及项目管理中心 | H111: 40062 | I111: 社会招聘 | J111: 财经类－FN | K111: 投资并购 | L111: S5 | N111: Others | Q111: O,G | U111: 26400.8 | V111: 0.083333 | W111: CNY | X111: 1 | Y111: 25727.4 | Z111: 0 | AA111: 79202.4 | AB111: 22265 | AC111: 0 | AF111: 0 | AG111: 101467.4 | AH111: 3.943943 | AI111: 101467.4 | AJ111: 3.943943 | AK111: 3.943943 | AQ111: 101467.4 | AR111: 3.943943 | AS111: 0.64883077 | BL111: 1 | BM111: 21280 | BN111: 0 | BO111: 22365 | BP111: G,G | BQ111: T1# | BR111: 114690 | BS111: 5.3895677 | BT111: 41695 | BU111: 156385 | BV111: 7.3489192 | BY111: 156385 | BZ111: 7.3489192 | CP111: 财经投资并购及管理部 | CQ111: 5,3 | CR111: 5 | CS111: Others | CT111: N
A112: kathrynLong(龙琳) | C112: 87603918 | D112: 财会及报告管理部 | E112: 应收管理中心 | G112: S2职能系统－财经线/财会及报告管理部/应收管理中心 | H112: 41264 | I112: 高校招聘 | J112: 财经类－FN | K112: 会计 | L112: S11 | N112: T1# | Q112: G,G | U112: 58206.55 | V112: 0.083333 | W112: CNY | X112: 1 | Y112: 52975.86 | Z112: 0 | AA112: 116413.1 | AB112: 190125 | AC112: 101595 | AF112: 0 | AG112: 408133.1 | AH112: 7.7041335 | AI112: 408133.1 | AJ112: 7.7041335 | AK112: 5.7863733 | AQ112: 408133.1 | AR112: 7.7041335 | AS112: 1.9151737 | BL112: 1 | BM112: 51105 | BN112: 0 | BO112: 51670 | BP112: U,G | BQ112: T1# | BR112: 213105 | BS112: 4.1699442 | BT112: 0 | BU112: 213105 | BV112: 4.1699442 | BY112: 213105 | BZ112: 4.1699442 | CP112: 财会及报告管理部 | CQ112: 3,3 | CR112: 11 | CS112: T1# | CT112: N
A113: elenaTan(谭涵) | C113: 37988504 | D113: 财会及报告管理部 | E113: 员工报销服务中心 | G113: S2职能系统－财经线/财会及报告管理部/员工报销服务中心 | H113: 43351 | I113: 高校招聘 | J113: 财经类－FN | K113: 会计 | L113: S11 | N113: T1 | Q113: G,O | U113: 49332.5 | V113: 0.083333 | W113: CNY | X113: 1 | Y113: 47536.53 | Z113: 0 | AA113: 147997.5 | AB113: 101525 | AC113: 95980 | AF113: 0 | AG113: 345502.5 | AH113: 7.2681473 | AI113: 345502.5 | AJ113: 7.2681473 | AK113: 5.2490685 | AQ113: 345502.5 | AR113: 7.2681473 | AS113: 1.4429305 | BL113: 1 | BM113: 41780 | BN113: 0 | BO113: 45010 | BP113: G,G | BQ113: T1 | BR113: 154580 | BS113: 3.6998564 | BT113: 84865 | BU113: 239445 | BV113: 5.7310914 | BY113: 239445 | BZ113: 5.7310914 | CP113: 财会及报告管理部 | CQ113: 5,3 | CR113: 11 | CS113: T1 | CT113: N
A114: ryanHong(洪海) | C114: 87411951 | D114: PCG财务管理 | E114: 财务规划及分析组 | G114: S2职能系统－财经线/PCG财务管理/财务规划及分析组 | H114: 40590 | I114: 高校招聘 | J114: 财经类－FN | K114: 财务管理 | L114: S7 | N114: Others | Q114: G,G | U114: 30366.15 | V114: 0.083333 | W114: CNY | X114: 1 | Y114: 27977.26 | Z114: 0 | AA114: 60732.3 | AB114: 21420 | AC114: 0 | AF114: 0 | AG114: 82152.3 | AH114: 2.9363955 | AI114: 82152.3 | AJ114: 2.9363955 | AK114: 2.9363955 | AQ114: 82152.3 | AR114: 2.9363955 | AS114: 2.1352125 | BL114: 1 | BM114: 25535 | BN114: 0 | BO114: 27695 | BP114: U,U | BQ114: Others | BR114: 38475 | BS114: 1.5067554 | BT114: 0 | BU114: 38475 | BV114: 1.5067554 | BY114: 38475 | BZ114: 1.5067554 | CP114: PCG财务管理 | CQ114: 3,3 | CR114: 7 | CS114: Others | CT114: N
A115: brooklynJiang(姜琴) | C115: 66031275 | D115: 应收账款管理中心 | E115: 应收管理2组 | G115: S2职能系统－财经线/应收账款管理中心/应收管理2组 | H115: 39907 | I115: 社会招聘 | J115: 财经类－FN | K115: 会计 | L115: S6 | N115: T1# | Q115: G,G | U115: 23903.55 | V115: 0.083333 | W115: CNY | X115: 1 | Y115: 22824.63 | Z115: 0 | AA115: 47807.1 | AB115: 82410 | AC115: 25535 | AF115: 0 | AG115: 155752.1 | AH115: 6.8238609 | AI115: 155752.1 | AJ115: 6.8238609 | AK115: 5.7051133 | AQ115: 155752.1 | AR115: 6.8238609 | AS115: 1.3896511 | BL115: 1 | BM115: 21425 | BN115: 0 | BO115: 23345 | BP115: G,G | BQ115: T1 | BR115: 77670 | BS115: 3.6252042 | BT115: 34410 | BU115: 112080 | BV115: 5.2312719 | BY115: 112080 | BZ115: 5.2312719 | CP115: 应收账款管理中心 | CQ115: 3,3 | CR115: 6 | CS115: T1# | CT115: N
A116: emilyHe(何诗) | C116: 31549065 | D116: IEG财务管理 | E116: 发行线财务管理组 | G116: S2职能系统－财经线/IEG财务管理/发行线财务管理组 | H116: 36964 | I116: 社会招聘 | J116: 财经类－FN | K116: 财务管理 | L116: S7 | N116: Others | Q116: G,O | U116: 41266.15 | V116: 0.083333 | W116: CNY | X116: 1 | Y116: 40601.33 | Z116: 0 | AA116: 123798.45 | AB116: 28270 | AC116: 0 | AF116: 0 | AG116: 152068.45 | AH116: 3.7454056 | AI116: 152068.45 | AJ116: 3.7454056 | AK116: 3.7454056 | AQ116: 152068.45 | AR116: 3.7454056 | AS116: 1.4117667 | BL116: 1 | BM116: 34420 | BN116: 0 | BO116: 35255 | BP116: G,G | BQ116: Others | BR116: 107715 | BS116: 3.1294306 | BT116: 0 | BU116: 107715 | BV116: 3.1294306 | BY116: 107715 | BZ116: 3.1294306 | CP116: IEG财务管理 | CQ116: 5,3 | CR116: 7 | CS116: Others | CT116: N
A117: dennisLv(吕华锐) | C117: 16709043 | D117: WXG财务管理 | E117: WXG财务管理 | G117: S2职能系统－财经线/WXG财务管理 | H117: 38985 | I117: 高校招聘 | J117: 财经类－FN | K117: 财务管理 | L117: S10 | N117: T1 | Q117: G,G | U117: 36422.85 | V117: 0.083333 | W117: CNY | X117: 1 | Y117: 35144.12 | Z117: 0 | AA117: 72845.7 | AB117: 82620 | AC117: 37895 | AF117: 0 | AG117: 193360.7 | AH117: 5.501936 | AI117: 193360.7 | AJ117: 5.501936 | AK117: 4.4236618 | AQ117: 193360.7 | AR117: 5.501936 | AS117: 1.0695321 | BL117: 1 | BM117: 30250 | BN117: 0 | BO117: 32065 | BP117: O,G | BQ117: T1 | BR117: 131275 | BS117: 4.3396694 | BT117: 49515 | BU117: 180790 | BV117: 5.9765289 | BY117: 180790 | BZ117: 5.9765289 | CP117: WXG财务管理 | CQ117: 3,3 | CR117: 10 | CS117: T1 | CT117: N
A118: walterDong(董超晨) | C118: 30880325 | D118: 财经IT管理部 | E118: 业务开发中心 | G118: S2职能系统－财经线/财经IT管理部/业务开发中心 | H118: 38852 | I118: 社会招聘 | J118: 技术研发类－TRD | K118: 应用开发 | L118: T7 | N118: T1# | Q118: G,G | U118: 31733.55 | V118: 0.083333 | W118: CNY | X118: 1 | Y118: 29159.21 | Z118: 0 | AA118: 63467.1 | AB118: 95885 | AC118: 62625 | AF118: 0 | AG118: 221977.1 | AH118: 7.6125896 | AI118: 221977.1 | AJ118: 7.6125896 | AK118: 5.4648977 | AQ118: 221977.1 | AR118: 7.6125896 | AS118: 1.2398877 | BL118: 1 | BM118: 28060 | BN118: 0 | BO118: 28745 | BP118: G,G | BQ118: T1# | BR118: 144770 | BS118: 5.1593015 | BT118: 34260 | BU118: 179030 | BV118: 6.3802566 | BY118: 179030 | BZ118: 6.3802566 | CP118: 财经IT管理部 | CQ118: 3,3 | CR118: 7 | CS118: T1# | CT118: N
... A132: ethanNiu(牛勇志) | C132: 53964320 | D132: PCG财务管理 | E132: 在线视频财务管理中心 | G132: S2职能系统－财经线/PCG财务管理/在线视频财务管理中心 | H132: 42787 | I132: 高校招聘 | J132: 财经类－FN | K132: 财务管理 | L132: S5 | N132: T1 | Q132: G,G | U132: 30340.25 | V132: 0.083333 | W132: CNY | X132: 1 | Y132: 28324.33 | Z132: 0 | AA132: 60680.5 | AB132: 62335 | AC132: 40705 | AF132: 0 | AG132: 163720.5 | AH132: 5.7802073 | AI132: 163720.5 | AJ132: 5.7802073 | AK132: 4.3431036 | AQ132: 163720.5 | AR132: 5.7802073 | AS132: 2.0695298 | BL132: 1 | BM132: 25000 | BN132: 0 | BO132: 25390 | BP132: G,G | BQ132: T2 | BR132: 79110 | BS132: 3.1644 | BT132: 0 | BU132: 79110 | BV132: 3.1644 | BY132: 79110 | BZ132: 3.1644 | CP132: PCG财务管理 | CQ132: 3,3 | CR132: 5 | CS132: T1 | CT132: N
A133: ralphTan(谭波) | C133: 70522497 | D133: 风险管理和内部控制 | E133: S系统风控组 | G133: S2职能系统－财经线/风险管理和内部控制/S系统风控组 | H133: 43895 | I133: 社会招聘 | J133: 财经类－FN | K133: 风险管理 | M133: L2-1 | N133: T2 | Q133: G,G | U133: 69362 | V133: 0.083333 | W133: CNY | X133: 1 | Y133: 67849.63 | Z133: 0 | AA133: 138724 | AB133: 75755 | AC133: 0 | AF133: 14740 | AG133: 214479 | AH133: 3.1610931 | AI133: 229219 | AJ133: 3.3783382 | AK133: 3.3783382 | AQ133: 229219 | AR133: 3.3783382 | AS133: 1.3170478 | BL133: 1 | BM133: 56765 | BN133: 0 | BO133: 57500 | BP133: G,G | BQ133: T2 | BR133: 174040 | BS133: 3.0659738 | BT133: 0 | BU133: 174040 | BV133: 3.0659738 | BY133: 174040 | BZ133: 3.0659738 | CP133: 风险管理和内部控制 | CQ133: 3,3 | CR133: L2-1 | CS133: T2 | CT133: N
A134: rebeccaWu(吴冰) | C134: 32997973 | D134: CSIG财务管理 | E134: 综合财务管理中心 | G134: S2职能系统－财经线/CSIG财务管理/综合财务管理中心 | H134: 38030 | I134: 高校招聘 | J134: 财经类－FN | K134: 财务管理 | L134: S10 | N134: T1 | Q134: G,G | U134: 46576.55 | V134: 0.083333 | W134: CNY | X134: 1 | Y134: 41936.75 | Z134: 0 | AA134: 93153.1 | AB134: 100445 | AC134: 50720 | AF134: 0 | AG134: 244318.1 | AH134: 5.8258711 | AI134: 244318.1 | AJ134: 5.8258711 | AK134: 4.6164307 | AQ134: 244318.1 | AR134: 5.8258711 | AS134: 0.82345163 | BL134: 1 | BM134: 41540 | BN134: 0 | BO134: 44095 | BP134: O,O | BQ134: T1 | BR134: 235880 | BS134: 5.6783823 | BT134: 60820 | BU134: 296700 | BV134: 7.1425132 | BY134: 296700 | BZ134: 7.1425132 | CP134: CSIG财务管理 | CQ134: 3,3 | CR134: 10 | CS134: T1 | CT134: N
...

Sheet 年终奖分配明细表-海外
A1: 分配模式：人民币 (Currency: CNY) | AC1: ='年终奖分配明细表-国内'!AC1 | AE1: ='年终奖分配明细表-国内'!AE1 | AP1: ='年终奖分配明细表-国内'!AP1 | AV1: ='年终奖分配明细表-国内'!AV1 | AX1: ='年终奖分配明细表-国内'!AX1 | AZ1: ='年终奖分配明细表-国内'!AZ1
AC2: ='年终奖分配明细表-国内'!AC2 | AE2: ='年终奖分配明细表-国内'!AE2 | AP2: ='年终奖分配明细表-国内'!AP2 | AV2: ='年终奖分配明细表-国内'!AV2 | AX2: ='年终奖分配明细表-国内'!AX2 | AZ2: ='年终奖分配明细表-国内'!AZ2
A3: 请勿隐藏绿色可调整列 | U3: 总额度 (Total) | AC3: ='年终奖分配明细表-国内'!AC3 | AE3: ='年终奖分配明细表-国内'!AE3 | AP3: ='年终奖分配明细表-国内'!AP3 | AV3: ='年终奖分配明细表-国内'!AV3 | AX3: ='年终奖分配明细表-国内'!AX3 | AZ3: ='年终奖分配明细表-国内'!AZ3
A4: Please DO NOT hide the Green column ! | U4: 已用额度 (Assigned) | AC4: ='年终奖分配明细表-国内'!AC4 | AE4: ='年终奖分配明细表-国内'!AE4 | AP4: ='年终奖分配明细表-国内'!AP4 | AV4: ='年终奖分配明细表-国内'!AV4 | AX4: ='年终奖分配明细表-国内'!AX4 | AZ4: ='年终奖分配明细表-国内'!AZ4
U5: 剩余额度 (Remaining) | AC5: ='年终奖分配明细表-国内'!AC5 | AE5: ='年终奖分配明细表-国内'!AE5 | AP5: ='年终奖分配明细表-国内'!AP5 | AV5: ='年终奖分配明细表-国内'!AV5 | AX5: ='年终奖分配明细表-国内'!AX5 | AZ5: ='年终奖分配明细表-国内'!AZ5
AP6: ='年终奖分配明细表-国内'!AP6
A7: 请勿删除第一行到第七行！！！
E8: ="@@CURRENCY_CNY" | AC8: ='年终奖分配明细表-国内'!AC8 | AE8: ='年终奖分配明细表-国内'!AE8 | AP8: ='年终奖分配明细表-国内'!AP8 | AV8: ='年终奖分配明细表-国内'!AV8 | AX8: ='年终奖分配明细表-国内'!AX8 | AZ8: ='年终奖分配明细表-国内'!AZ8
A9: 2 | G9: @@CD_g1qT4RWZn8PvzqzsvsSlZ1HoevUBl8dinYL8/H7Cw9JN1xdebvU/xUsX4kOF/8om | AB9: =SUM(AA14:AA20)+SUM(AC14:AC20) | AD9: =SUM(AE14:AE20) | AO9: =SUM(AP14:AP20) | AU9: =SUM(AV14:AV20) | AW9: =SUM(AX14:AX20) | AY9: =SUM(AZ14:AZ20)
H10: 基本信息 (Basic Info) | AC10: 本次奖金 (Bonus of This Year) | AO10: ="本次"&AP1 | AQ10: 本次合计 (Total of This Year) | BA10: 备注信息 (Remarks) | BG10: 辅助信息 (Additional Info) | BP10: 上年度参考信息 (Reference Info of Last Year) | CG10: 包信息 (Pool Info) | CI10: 自定义标签 (Custom Labels)
A11: Name | B11: Legal Name | C11: Staff ID | D11: Department | E11: Sub Organization of the Department | F11: 2nd-Level Org. Under Department | G11: Organization | H11: Onboarding Date | I11: Employment Type | J11: Job function | K11: Position | L11: Professional grade | M11: Managerial grade | N11: Talent Tier | O11: 2024 Talent Tier | P11: Talent Tier Change in Last 2 Years | Q11: 2025 H1/H2 Performance Ratings | R11: 2025 H1/H2 Customized Performance Ratings | S11: 2024 H1/H2 Performance Ratings | T11: Performance Change in Last 2 Years | U11: Current Monthly Salary (CNY) | V11: Target Bonus % | W11: Payroll Currency | X11: Time Proration Factor | Y11: Base Amount of Annual Bonus (CNY) | Z11: Base Amount of Target Bonus (CNY) | AA11: Target Bonus (T) (CNY) | AB11: Suggested Target Bonus (CNY) | AC11: Actual Target Bonus (CNY) | AD11: =IF(ISBLANK(AD12),"预留",AD12)&CHAR(10)&"Suggestion"&CHAR(10)&"(CNY)" | AE11: =IF(ISBLANK(AD12),"预留",AD12)&CHAR(10)&"Submission"&CHAR(10)&"(CNY)" | AF11: Total Project Bonus (CNY) | AG11: T+T0 Bonus (CNY) | AH11: T+T0 Bonus Index | AI11: Target+Project Bonus Amount (CNY) | AJ11: T+T0+Project Bonus Index | AK11: Suggested T+T0+Project Bonus Index | AL11: Vs. 2024 T+T0+Project Bonus | AM11: Target+Project Bonus Index | AN11: Suggested Target+Project Bonus Index | AO11: Incremental Profit Sharing Incentive Suggestion(CNY) (CNY) | AP11: =AO12&CHAR(10)&"Submission"&CHAR(10)&"(CNY)" | AQ11: Total Bonus Payout (CNY) | AR11: Total Payout Index (China) | AS11: Vs. 2024 Total Bonus Payout | AT11: Total Payout Index (Overseas) | AU11: =IF(ISBLANK(AU12),"预留",AU12)&CHAR(10)&"Suggestion"&CHAR(10)&"(CNY)" | AV11: =AU12&CHAR(10)&"Submission"&CHAR(10)&"(CNY)" | AW11: =IF(ISBLANK(AW12),"预留",AW12)&CHAR(10)&"Suggestion"&CHAR(10)&"(CNY)" | AX11: =AW12&CHAR(10)&"Submission"&CHAR(10)&"(CNY)" | AY11: =IF(ISBLANK(AY12),"预留",AY12)&CHAR(10)&"Suggestion"&CHAR(10)&"(CNY)" | AZ11: =AY12&CHAR(10)&"Submission"&CHAR(10)&"(CNY)" | BA11: Allocation Remarks | BB11: Historical Remarks | BC11: C&B G Remarks | BD11: Remarks from HRBP | BE11: Compensation-Performance Consistency | BF11: Allocation Alert | BG11: Promised Bonus (CNY) | BH11: Bonus Paid During the Year (CNY) | BI11: Remarks about Paid Bonus | BJ11: Non-deductible Leave Days % | BK11: Leave Days Remarks | BL11: Time Proration Factor of 2024 Annual Bonus | BM11: Base Amount of 2024 Annual Bonus (CNY) | BN11: Base Amount of 2024 Target Bonus (CNY) | BO11: Monthly Salary in 2024 (CNY) | BP11: 2024 H1/H2 Performance Ratings | BQ11: 2024 Talent Tier | BR11: 2024 Target Bonus (CNY) | BS11: 2024 T+T0 Bonus Index | BT11: 2024 Total Project Bonus (CNY) | BU11: 2024 Actual Target+Project Bonus (CNY) | BV11: 2024 T+T0+Project Bonus Index | BW11: 2024 Target+Project Bonus Index | BX11: 2024 Incremental Incentive (CNY) | BY11: 2024 Total Bonus Payout (CNY) | BZ11: 2024 Total Payout Index (China) | CA11: 2024 Total Payout Index (Overseas) | CB11: 2024 Service Bonus (CNY) | CC11: 2024 One- time Incremental Incentive (CNY) | CD11: 2024 Special Grant (CNY) | CE11: 2024 Non-deductible Leave Days % | CF11: 2024 Salary Structure Change | CG11: Pool name | CH11: Pool Owner | CI11: Salary Structure Change | CJ11: Sheet Split Tag | CK11: Region | CL11: Country/Region | CM11: Continent Region | CN11: LCY Exchange Rate | CO11: Termination/Transfer Label | CP11: Organization Label | CQ11: Performance Label | CR11: Job Grade Label | CS11: Talent Tier Label | CT11: New Job System Label | CU11: Serious violations of the Sunshine Code of Conduct | CV11: Good Overall Performance Rating with Underperform Contribution or Conduct Rating | CW11: Backup Label 2 | CX11: Backup Label 3 | CY11: Backup Label 4 | CZ11: Backup Label 5 | DA11: Backup Label 6 | DB11: Backup Label 7 | DC11: Backup Label 8
A12: @Name | D12: ="@@CR_12" | AC12: ="@B_"&AC8 | AE12: ="@B_"&AE8 | AP12: ="@B_"&AP8 | AV12: ="@B_"&AV8 | AX12: ="@B_"&AX8 | AZ12: ="@B_"&AZ8 | BA12: ="@Remark"
A13: 中英文名 | B13: 真实姓名 | C13: 员工ID | D13: 部门 | E13: 部门下一级组织 | F13: 部门下二级组织 | G13: 组织全称 | H13: 入职日期 | I13: 应聘类别 | J13: 发展通道 | K13: 专业职位 | L13: 专业职级 | M13: 管理职级 | N13: 2025 人才梯队 | O13: 2024 人才梯队 | P13: 两年梯队变化 | Q13: 2025绩效 H1/H2 | R13: 2025自定义绩效 H1/H2 | S13: 2024绩效 H1/H2 | T13: 两年绩效变化 | U13: 目前月薪 (CNY) | V13: 浮动比例 | W13: 发薪币种 | X13: 年终奖 时间系数 | Y13: 年终奖 基数 (CNY) | Z13: Target Bonus基数 (CNY) | AA13: 绩效奖金 (T) (CNY) | AB13: 下发 Target Bonus (CNY) | AC13: 提交 Target Bonus (CNY) | AD13: ="下发"&CHAR(10)&IF(ISBLANK(AE1),"预留Q",AE1)&"(CNY)" | AE13: ="提交"&CHAR(10)&IF(ISBLANK(AE1),"预留R",AE1)&"(CNY)" | AF13: 项目奖金 合计 (CNY) | AG13: (T+T0) 金额 (CNY) | AH13: (T+T0) 系数 | AI13: (Target Bonus+项目奖)金额 (CNY) | AJ13: (T+T0+项目奖) 系数 | AK13: 下发建议 (T+T0+项目奖) 系数 | AL13: VS 2024 (T+T0+项目奖) 金额 | AM13: (Target Bonus+项目奖)系数 | AN13: 下发建议 (Target Bonus+项目奖)系数 | AO13: ="下发"&CHAR(10)&AP1&"(CNY)" | AP13: ="提交"&CHAR(10)&AP1&"(CNY)" | AQ13: 合计金额 (CNY) | AR13: 国内合计系数 | AS13: VS 2024 合计金额 | AT13: 海外合计系数 | AU13: ="下发"&CHAR(10)&AV1&"(CNY)" | AV13: ="提交"&CHAR(10)&AV1&"(CNY)" | AW13: ="下发"&CHAR(10)&AX1&"(CNY)" | AX13: ="提交"&CHAR(10)&AX1&"(CNY)" | AY13: ="下发"&CHAR(10)&AZ1&"(CNY)" | AZ13: ="提交"&CHAR(10)&AZ1&"(CNY)" | BA13: 当前环节 分配备注 | BB13: 前序环节 分配备注 | BC13: 薪酬经理备注 | BD13: BP备注 | BE13: 薪酬与评价 匹配度 | BF13: 分配规则 校验信息 | BG13: 承诺奖金 (CNY) | BH13: 已发放奖金 (CNY) | BI13: 已发放奖金备注 | BJ13: 长假期天数占比(未影响时间系数) | BK13: 假期备注 | BL13: 2024 年终奖 时间系数 | BM13: 2024 年终奖 基数 (CNY) | BN13: 2024 Target Bonus基数 (CNY) | BO13: 2024月薪 (CNY) | BP13: 2024绩效 H1/H2 | BQ13: 2024 人才梯队 | BR13: 2024 Target Bonus 金额 (CNY) | BS13: 2024 (T+T0) 系数 | BT13: 2024 项目奖合计 (CNY) | BU13: 2024 (Target Bonus+项目奖)金额(CNY) | BV13: 2024 (T+T0+项目奖) 系数 | BW13: 2024 (Target Bonus+项目奖)系数 | BX13: 2024 增量激励 (如有) (CNY) | BY13: 2024 合计金额 (CNY) | BZ13: 2024 国内合计系数 | CA13: 2024 海外合计系数 | CB13: 2024 服务奖(CNY) | CC13: 2024增量项目激励 (如有) (CNY) | CD13: 2024年末特别授予(如有) (CNY) | CE13: 2024 长假期天数占比(未影响时间系数) | CF13: 2024全年 薪酬结构 变化标识 | CG13: 包名称 | CH13: 包负责人 | CI13: 全年 薪酬结构 变化标识 | CJ13: 拆表标签 | CK13: 地区分类 | CL13: 国家/地区 | CM13: 区域 | CN13: 本币汇率 | CO13: 离职/调动 标签 | CP13: 组织标签 | CQ13: 绩效标签 | CR13: 职级标签 | CS13: 梯队标签 | CT13: 试点体系标签 | CU13: 是否阳光行为违规 | CV13: 绩效综合G且业绩/行为评级U | CW13: 补充标签2 | CX13: 补充标签3 | CY13: 补充标签4 | CZ13: 补充标签5 | DA13: 补充标签6 | DB13: 补充标签7 | DC13: 补充标签8
A14: edwardXu(徐帆国) | C14: 57792341 | D14: 风险管理和内部控制 | E14: WXG风控中心 | G14: S2职能系统－财经线/风险管理和内部控制/WXG风控中心 | H14: 39707 | I14: 社会招聘 | J14: 财经类－FN | K14: 风险管理 | L14: S9 | N14: T1# | Q14: U,G | U14: 34220.45 | V14: 0.083333 | W14: CNY | X14: 1 | Y14: 32767.06 | Z14: 0 | AA14: 34220.45 | AF14: 0 | AG14: 147200.45 | AH14: 4.4923301 | AJ14: 4.4923301 | AK14: 4.4923301 | AQ14: 147200.45 | AR14: 4.4923301 | AS14: 0.64760427 | BL14: 1 | BM14: 30610 | BN14: 0 | BO14: 33125 | BP14: G,G | BQ14: T1# | BS14: 5.927638 | BT14: 45855 | BV14: 7.4256779 | BY14: 227300 | BZ14: 7.4256779 | CP14: 风险管理和内部控制 | CQ14: 3,1 | CR14: 9 | CS14: T1# | CT14: N
A15: savannahZhong(钟倩思) | C15: 78647818 | D15: 审计监察 | E15: 金融审计组 | G15: S2职能系统－财经线/审计监察/金融审计组 | H15: 45139 | I15: 高校招聘 | J15: 财经类－FN | K15: 风险管理 | L15: S5 | N15: T1# | Q15: G,U | U15: 23014.25 | V15: 0.083333 | W15: CNY | X15: 1 | Y15: 21659.73 | Z15: 0 | AA15: 69042.75 | AF15: 0 | AG15: 169102.75 | AH15: 7.8072418 | AJ15: 7.8072418 | AK15: 6.6578739 | AQ15: 169102.75 | AR15: 7.8072418 | AS15: 21.652081 | BL15: 0.41643836 | BM15: 18765 | BN15: 0 | BO15: 18765 | BP15: N,G | BQ15: T1# | BS15: 0.41620037 | BT15: 0 | BV15: 0.41620037 | BY15: 7810 | BZ15: 0.41620037 | CP15: 审计监察 | CQ15: 5,3 | CR15: 5 | CS15: T1# | CT15: N
A16: emmaZheng(郑苑) | C16: 37559092 | D16: 财会及报告管理部 | E16: 应收管理中心 | G16: S2职能系统－财经线/财会及报告管理部/应收管理中心 | H16: 41779 | I16: 社会招聘 | J16: 财经类－FN | K16: 会计 | L16: S11 | N16: T1# | Q16: G,G | U16: 53212.6 | V16: 0.083333 | W16: CNY | X16: 1 | Y16: 50216.55 | Z16: 0 | AA16: 106425.2 | AF16: 0 | AG16: 340800.2 | AH16: 6.7866112 | AJ16: 6.7866112 | AK16: 5.4371557 | AQ16: 340800.2 | AR16: 6.7866112 | AS16: 1.0573678 | BL16: 1 | BM16: 44240 | BN16: 0 | BO16: 46890 | BP16: G,G | BQ16: T1# | BS16: 5.3264014 | BT16: 86670 | BV16: 7.2854882 | BY16: 322310 | BZ16: 7.2854882 | CP16: 财会及报告管理部 | CQ16: 3,3 | CR16: 11 | CS16: T1# | CT16: N
A17: edwardJia(贾平华) | C17: 14198066 | D17: FiT财务管理 | E17: 业务支持与分析中心 | G17: S2职能系统－财经线/FiT财务管理/业务支持与分析中心 | H17: 37710 | I17: 社会招聘 | J17: 财经类－FN | K17: 财务管理 | L17: S6 | N17: T1 | Q17: O,G | U17: 27937.2 | V17: 0.083333 | W17: CNY | X17: 1 | Y17: 26626.57 | Z17: 0 | AA17: 111748.8 | AF17: 0 | AG17: 222923.8 | AH17: 8.3722312 | AJ17: 8.3722312 | AK17: 6.7747667 | AQ17: 222923.8 | AR17: 8.3722312 | AS17: 1.6884969 | BL17: 1 | BM17: 23850 | BN17: 0 | BO17: 25715 | BP17: G,G | BQ17: T1 | BS17: 3.3888889 | BT17: 51200 | BV17: 5.5356394 | BY17: 132025 | BZ17: 5.5356394 | CP17: FiT财务管理 | CQ17: 5,5 | CR17: 6 | CS17: T1 | CT17: N
A18: patrickJiang(姜彪国) | C18: 1336290 | D18: 风险管理和内部控制 | E18: CSIG风控中心 | G18: S2职能系统－财经线/风险管理和内部控制/CSIG风控中心 | H18: 42286 | I18: 社会招聘 | J18: 财经类－FN | K18: 风险管理 | L18: S9 | N18: T1 | Q18: O,G | U18: 54594.65 | V18: 0.083333 | W18: CNY | X18: 1 | Y18: 53257.31 | Z18: 0 | AA18: 109189.3 | AF18: 0 | AG18: 315779.3 | AH18: 5.9293137 | AJ18: 5.9293137 | AK18: 4.4958016 | AQ18: 315779.3 | AR18: 5.9293137 | AS18: 1.3897513 | BL18: 1 | BM18: 45345 | BN18: 0 | BO18: 49295 | BP18: G,G | BQ18: T1 | BS18: 3.4351086 | BT18: 71455 | BV18: 5.0109163 | BY18: 227220 | BZ18: 5.0109163 | CP18: 风险管理和内部控制 | CQ18: 3,3 | CR18: 9 | CS18: T1 | CT18: N
A19: chloeLin(林琴悦) | C19: 2185561 | D19: CSIG财务管理 | E19: 公线及费用财务管理中心 | G19: S2职能系统－财经线/CSIG财务管理/公线及费用财务管理中心 | H19: 43514 | I19: 社会招聘 | J19: 财经类－FN | K19: 财务管理 | L19: S8 | N19: T1 | Q19: O,G | U19: 46114.8 | V19: 0.083333 | W19: CNY | X19: 1 | Y19: 42227.05 | Z19: 0 | AA19: 138344.4 | AF19: 0 | AG19: 315254.4 | AH19: 7.4656979 | AJ19: 7.4656979 | AK19: 5.8512115 | AQ19: 315254.4 | AR19: 7.4656979 | AS19: 1.2007404 | BL19: 1 | BM19: 38825 | BN19: 0 | BO19: 40225 | BP19: G,G | BQ19: T1# | BS19: 5.6262717 | BT19: 44110 | BV19: 6.7623954 | BY19: 262550 | BZ19: 6.7623954 | CP19: CSIG财务管理 | CQ19: 5,3 | CR19: 8 | CS19: T1 | CT19: N
A20: abigailDong(董璐月) | C20: 15958390 | D20: 风险管理和内部控制 | E20: IEG风控中心 | G20: S2职能系统－财经线/风险管理和内部控制/IEG风控中心 | H20: 37998 | I20: 高校招聘 | J20: 财经类－FN | K20: 风险管理 | L20: S11 | N20: T1 | Q20: G,O | U20: 42014.3 | V20: 0.083333 | W20: CNY | X20: 1 | Y20: 40908.92 | Z20: 0 | AA20: 42014.3 | AF20: 0 | AG20: 146364.3 | AH20: 3.5778089 | AJ20: 3.5778089 | AK20: 3.5778089 | AQ20: 146364.3 | AR20: 3.5778089 | AS20: 0.5545993 | BL20: 1 | BM20: 35120 | BN20: 0 | BO20: 37910 | BP20: G,G | BQ20: T1# | BS20: 5.9212699 | BT20: 55955 | BV20: 7.5145216 | BY20: 263910 | BZ20: 7.5145216 | CP20: 风险管理和内部控制 | CQ20: 3,1 | CR20: 11 | CS20: T1 | CT20: N
A21: nicholasQiu(邱强) | C21: 19081982 | D21: 风险管理和内部控制 | E21: IEG风控中心 | G21: S2职能系统－财经线/风险管理和内部控制/IEG风控中心 | H21: 42461 | I21: 高校招聘 | J21: 财经类－FN | K21: 风险管理 | L21: S8 | N21: T2 | Q21: G,G | U21: 44043.7 | V21: 0.083333 | W21: CNY | X21: 1 | Y21: 41123.76 | Z21: 0 | AA21: 132131.1 | AF21: 0 | AG21: 183786.1 | AH21: 4.4690977 | AJ21: 4.4690977 | AK21: 4.4690977 | AQ21: 183786.1 | AR21: 4.4690977 | AS21: 1.1295317 | BL21: 1 | BM21: 35815 | BN21: 0 | BO21: 38760 | BP21: G,O | BQ21: T2 | BS21: 4.5430685 | BT21: 0 | BV21: 4.5430685 | BY21: 162710 | BZ21: 4.5430685 | CP21: 风险管理和内部控制 | CQ21: 5,3 | CR21: 8 | CS21: T2 | CT21: N
A22: matthewHou(侯勋宏) | C22: 81154958 | D22: 海外财经中心 | E22: 海外本地财务 | G22: S2职能系统－财经线/海外财经中心/海外本地财务 | H22: 41263 | I22: 社会招聘 | J22: 财经类－FN | K22: 财务管理 | L22: S11 | N22: T1 | Q22: G,G | U22: 51306.95 | V22: 0.083333 | W22: CNY | X22: 1 | Y22: 46207.44 | Z22: 0 | AA22: 102613.9 | AF22: 0 | AG22: 308873.9 | AH22: 6.6845058 | AJ22: 6.6845058 | AK22: 4.5615793 | AQ22: 308873.9 | AR22: 6.6845058 | AS22: 2.2710481 | BL22: 1 | BM22: 42530 | BN22: 0 | BO22: 44415 | BP22: U,O | BQ22: T1 | BS22: 3.1978603 | BT22: 0 | BV22: 3.1978603 | BY22: 136005 | BZ22: 3.1978603 | CP22: 海外财经中心 | CQ22: 3,3 | CR22: 11 | CS22: T1 | CT22: N
A23: lillianTian(田青) | C23: 21911153 | D23: 财经IT管理部 | E23: 平台建设中心 | G23: S2职能系统－财经线/财经IT管理部/平台建设中心 | H23: 43026 | I23: 高校招聘 | J23: 技术研发类－TRD | K23: 应用开发 | L23: T9 | N23: T1 | Q23: G,U | U23: 51577.2 | V23: 0.083333 | W23: CNY | X23: 1 | Y23: 47257.05 | Z23: 0 | AA23: 103154.4 | AF23: 0 | AG23: 292014.4 | AH23: 6.179277 | AJ23: 6.179277 | AK23: 4.8984099 | AQ23: 292014.4 | AR23: 6.179277 | AS23: 1.4390262 | BL23: 1 | BM23: 43545 | BN23: 0 | BO23: 46510 | BP23: G,G | BQ23: T1 | BS23: 3.2652429 | BT23: 60740 | BV23: 4.6601217 | BY23: 202925 | BZ23: 4.6601217 | CP23: 财经IT管理部 | CQ23: 3,3 | CR23: 9 | CS23: T1 | CT23: N
A24: louisYu(于梓) | C24: 60316002 | D24: 预算及职能系统财务管理部 | E24: 预算及职能系统财务管理部 | G24: S2职能系统－财经线/预算及职能系统财务管理部 | H24: 39619 | I24: 社会招聘 | J24: 财经类－FN | K24: 预算管理 | L24: S6 | N24: T1# | Q24: O,G | U24: 24152.75 | V24: 0.083333 | W24: CNY | X24: 1 | Y24: 22085.21 | Z24: 0 | AA24: 48305.5 | AF24: 0 | AG24: 171465.5 | AH24: 7.7638157 | AJ24: 7.7638157 | AK24: 5.8688824 | AQ24: 171465.5 | AR24: 7.7638157 | AS24: 1.0804379 | BL24: 1 | BM24: 21715 | BN24: 0 | BO24: 23560 | BP24: G,G | BQ24: T1# | BS24: 5.5664287 | BT24: 37825 | BV24: 7.3083122 | BY24: 158700 | BZ24: 7.3083122 | CP24: 预算及职能系统财务管理部 | CQ24: 3,3 | CR24: 6 | CS24: T1# | CT24: N
A25: ameliaNiu(牛佳娜) | C25: 82693967 | D25: 预算及职能系统财务管理部 | E25: 预算管理中心 | G25: S2职能系统－财经线/预算及职能系统财务管理部/预算管理中心 | H25: 43762 | I25: 社会招聘 | J25: 财经类－FN | K25: 预算管理 | L25: S6 | N25: T1# | Q25: U,G | U25: 30766.2 | V25: 0.083333 | W25: CNY | X25: 1 | Y25: 30214.76 | Z25: 0 | AA25: 92298.6 | AF25: 0 | AG25: 232853.6 | AH25: 7.7066176 | AJ25: 7.7066176 | AK25: 6.3170649 | AQ25: 232853.6 | AR25: 7.7066176 | AS25: 0.92457256 | BL25: 1 | BM25: 27535 | BN25: 0 | BO25: 29840 | BP25: O,G | BQ25: T1# | BS25: 6.9838388 | BT25: 59550 | BV25: 9.1465408 | BY25: 251850 | BZ25: 9.1465408 | CP25: 预算及职能系统财务管理部 | CQ25: 5,3 | CR25: 6 | CS25: T1# | CT25: N
... A39: wayneChang(常阳) | C39: 74666760 | D39: 预算及职能系统财务管理部 | E39: 预算管理中心 | G39: S2职能系统－财经线/预算及职能系统财务管理部/预算管理中心 | H39: 43256 | I39: 社会招聘 | J39: 财经类－FN | K39: 预算管理 | L39: S10 | N39: T1 | Q39: U,G | U39: 35677.4 | V39: 0.083333 | W39: CNY | X39: 1 | Y39: 34145.86 | Z39: 0 | AA39: 35677.4 | AF39: 0 | AG39: 122502.4 | AH39: 3.5876209 | AJ39: 3.5876209 | AK39: 3.5876209 | AQ39: 122502.4 | AR39: 3.5876209 | AS39: 0.9608785 | BL39: 1 | BM39: 28695 | BN39: 0 | BO39: 29060 | BP39: G,G | BQ39: T1 | BS39: 3.0899111 | BT39: 38825 | BV39: 4.4429343 | BY39: 127490 | BZ39: 4.4429343 | CP39: 预算及职能系统财务管理部 | CQ39: 3,1 | CR39: 10 | CS39: T1 | CT39: N
A40: kevinQian(钱峰阳) | C40: 91424281 | D40: 风险管理和内部控制 | E40: WXG风控中心 | G40: S2职能系统－财经线/风险管理和内部控制/WXG风控中心 | H40: 45377 | I40: 社会招聘 | J40: 财经类－FN | K40: 风险管理 | L40: S8 | N40: T2 | Q40: G,O | U40: 46653.7 | V40: 0.083333 | W40: CNY | X40: 0.767123 | Y40: 44279.38 | Z40: 0 | AA40: 35789.13 | AF40: 0 | AG40: 35789.13 | AH40: 0.80825725 | AJ40: 0.80825725 | AK40: 0.80825725 | AQ40: 35789.13 | AR40: 0.80825725 | BM40: 0 | BN40: 0 | BO40: 0 | BT40: 0 | BY40: 0 | CP40: 风险管理和内部控制 | CQ40: 5,3 | CR40: 8 | CS40: T2 | CT40: N
A41: ariaZeng(曾璐莉) | C41: 88685121 | D41: 财经IT管理部 | E41: 业务开发中心 | G41: S2职能系统－财经线/财经IT管理部/业务开发中心 | H41: 36550 | I41: 社会招聘 | J41: 技术研发类－TRD | K41: 应用开发 | L41: T11 | N41: T1 | Q41: G,G | U41: 54850.25 | V41: 0.083333 | W41: CNY | X41: 1 | Y41: 50436.78 | Z41: 0 | AA41: 109700.5 | AF41: 0 | AG41: 315960.5 | AH41: 6.264486 | AJ41: 6.264486 | AK41: 4.6241156 | AQ41: 315960.5 | AR41: 6.264486 | AS41: 0.94781989 | BL41: 1 | BM41: 46005 | BN41: 0 | BO41: 47660 | BP41: O,O | BQ41: T1 | BS41: 5.5600478 | BT41: 77565 | BV41: 7.2460602 | BY41: 333355 | BZ41: 7.2460602 | CP41: 财经IT管理部 | CQ41: 3,3 | CR41: 11 | CS41: T1 | CT41: N
A42: seanShi(施博力) | C42: 13692542 | D42: 财会及报告管理部 | E42: 账务中心 | G42: S2职能系统－财经线/财会及报告管理部/账务中心 | H42: 43674 | I42: 社会招聘 | J42: 财经类－FN | K42: 会计 | L42: S6 | N42: T1# | Q42: G,G | U42: 23356.65 | V42: 0.083333 | W42: CNY | X42: 1 | Y42: 21832.3 | Z42: 0 | AA42: 46713.3 | AF42: 0 | AG42: 146943.3 | AH42: 6.730546 | AJ42: 6.730546 | AK42: 5.3969715 | AQ42: 146943.3 | AR42: 6.730546 | AS42: 1.12209 | BL42: 1 | BM42: 19835 | BN42: 0 | BO42: 20055 | BP42: G,G | BQ42: T1# | BS42: 5.2513234 | BT42: 26795 | BV42: 6.6022183 | BY42: 130955 | BZ42: 6.6022183 | CP42: 财会及报告管理部 | CQ42: 3,3 | CR42: 6 | CS42: T1# | CT42: N
A43: kennethShi(施彪志) | C43: 83510684 | D43: FiT财务管理 | E43: 业务支持与分析中心 | G43: S2职能系统－财经线/FiT财务管理/业务支持与分析中心 | H43: 37145 | I43: 社会招聘 | J43: 财经类－FN | K43: 财务管理 | L43: S6 | N43: T1# | Q43: G,G | U43: 37008.1 | V43: 0.083333 | W43: CNY | X43: 1 | Y43: 34065.36 | Z43: 0 | AA43: 74016.2 | AF43: 0 | AG43: 257046.2 | AH43: 7.5456769 | AJ43: 7.5456769 | AK43: 5.458953 | AQ43: 257046.2 | AR43: 7.5456769 | AS43: 1.0672903 | BL43: 1 | BM43: 32010 | BN43: 0 | BO43: 32285 | BP43: O,G | BQ43: T1# | BS43: 6.1541706 | BT43: 43845 | BV43: 7.5238988 | BY43: 240840 | BZ43: 7.5238988 | CP43: FiT财务管理 | CQ43: 3,3 | CR43: 6 | CS43: T1# | CT43: N
A44: dianeGuo(郭怡) | C44: 34945004 | D44: CSIG财务管理 | E44: 产品财务管理中心 | G44: S2职能系统－财经线/CSIG财务管理/产品财务管理中心 | H44: 40737 | I44: 社会招聘 | J44: 财经类－FN | K44: 财务管理 | L44: S5 | N44: T2 | Q44: G,G | U44: 19312.85 | V44: 0.083333 | W44: CNY | X44: 1 | Y44: 18658.16 | Z44: 0 | AA44: 38625.7 | AF44: 0 | AG44: 66420.7 | AH44: 3.5598741 | AJ44: 3.5598741 | AK44: 3.5598741 | AQ44: 66420.7 | AR44: 3.5598741 | AS44: 1.1443952 | BL44: 1 | BM44: 15915 | BN44: 0 | BO44: 17085 | BP44: G,G | BQ44: T2 | BS44: 3.646874 | BT44: 0 | BV44: 3.646874 | BY44: 58040 | BZ44: 3.646874 | CP44: CSIG财务管理 | CQ44: 3,3 | CR44: 5 | CS44: T2 | CT44: N
A45: geraldJiang(江立) | C45: 47476377 | D45: 财经投资并购及管理部 | E45: 财经投资并购及管理部 | G45: S2职能系统－财经线/财经投资并购及管理部 | H45: 39276 | I45: 高校招聘 | J45: 财经类－FN | K45: 投资并购 | L45: S9 | N45: T2 | Q45: G,G | U45: 42167.25 | V45: 0.083333 | W45: CNY | X45: 1 | Y45: 41478.02 | Z45: 0 | AA45: 84334.5 | AF45: 0 | AG45: 136569.5 | AH45: 3.2925752 | AJ45: 3.2925752 | AK45: 3.2925752 | AQ45: 136569.5 | AR45: 3.2925752 | AS45: 0.9049132 | BL45: 1 | BM45: 36430 | BN45: 0 | BO45: 36930 | BP45: G,O | BQ45: T2 | BS45: 4.1427395 | BT45: 0 | BV45: 4.1427395 | BY45: 150920 | BZ45: 4.1427395 | CP45: 财经投资并购及管理部 | CQ45: 3,3 | CR45: 9 | CS45: T2 | CT45: N
A46: samanthaLu(卢娇) | C46: 16699560 | D46: CDG财务管理 | E46: 综合财务管理中心 | G46: S2职能系统－财经线/CDG财务管理/综合财务管理中心 | H46: 40499 | I46: 社会招聘 | J46: 财经类－FN | K46: 财务管理 | L46: S9 | N46: T2 | Q46: G,G | U46: 52890.75 | V46: 0.083333 | W46: CNY | X46: 1 | Y46: 52143.33 | Z46: 0 | AA46: 105781.5 | AF46: 0 | AG46: 177021.5 | AH46: 3.3949021 | AJ46: 3.3949021 | AK46: 3.3949021 | AQ46: 177021.5 | AR46: 3.3949021 | AS46: 0.88774855 | BL46: 1 | BM46: 47065 | BN46: 0 | BO46: 47475 | BP46: O,G | BQ46: T2 | BS46: 4.2368002 | BT46: 0 | BV46: 4.2368002 | BY46: 199405 | BZ46: 4.2368002 | CP46: CDG财务管理 | CQ46: 3,3 | CR46: 9 | CS46: T2 | CT46: N
A47: amandaHuang(黄琪) | C47: 53009758 | D47: 应收账款管理中心 | E47: 应收管理1组 | G47: S2职能系统－财经线/应收账款管理中心/应收管理1组 | H47: 42236 | I47: 社会招聘 | J47: 财经类－FN | K47: 会计 | L47: S9 | N47: T2 | Q47: G,G | U47: 40910.55 | V47: 0.083333 | W47: CNY | X47: 1 | Y47: 38691.58 | Z47: 0 | AA47: 81821.1 | AF47: 0 | AG47: 126201.1 | AH47: 3.26172 | AJ47: 3.26172 | AK47: 3.26172 | AQ47: 126201.1 | AR47: 3.26172 | AS47: 1.0202191 | BL47: 1 | BM47: 36280 | BN47: 0 | BO47: 39725 | BP47: G,G | BQ47: T2 | BS47: 3.4095921 | BT47: 0 | BV47: 3.4095921 | BY47: 123700 | BZ47: 3.4095921 | CP47: 应收账款管理中心 | CQ47: 3,3 | CR47: 9 | CS47: T2 | CT47: N
A48: rebeccaQin(秦娟茜) | C48: 73675670 | D48: 可持续社会价值事业部财务管理 | E48: 可持续社会价值事业部财务管理 | G48: S2职能系统－财经线/可持续社会价值事业部财务管理 | H48: 42222 | I48: 高校招聘 | J48: 财经类－FN | K48: 财务管理 | L48: S12 | M48: L1-2 | N48: T1# | Q48: G,O | U48: 74713.15 | V48: 0.083333 | W48: CNY | X48: 1 | Y48: 73759.27 | Z48: 0 | AA48: 224139.45 | AF48: 15650 | AG48: 555739.45 | AH48: 7.5345031 | AJ48: 7.7466798 | AK48: 6.3120805 | AQ48: 571389.45 | AR48: 7.7466798 | AS48: 1.0907085 | BL48: 1 | BM48: 66850 | BN48: 0 | BO48: 70875 | BP48: O,G | BQ48: T1# | BS48: 6.4285714 | BT48: 94120 | BV48: 7.8364996 | BY48: 523870 | BZ48: 7.8364996 | CP48: 可持续社会价值事业部财务管理 | CQ48: 5,3 | CR48: 12 | CS48: T1# | CT48: N
A49: stephenGao(高霖) | C49: 90270227 | D49: 董事会办公室 | E49: 董事会办公室 | G49: S2职能系统－财经线/董事会办公室 | H49: 37912 | I49: 社会招聘 | J49: 财经类－FN | K49: 公司秘书 | L49: S10 | N49: T1# | Q49: G,G | U49: 57296.75 | V49: 0.083333 | W49: CNY | X49: 1 | Y49: 52389.44 | Z49: 0 | AA49: 114593.5 | AF49: 0 | AG49: 375818.5 | AH49: 7.1735544 | AJ49: 7.1735544 | AK49: 5.5430732 | AQ49: 375818.5 | AR49: 7.1735544 | AS49: 1.1033852 | BL49: 1 | BM49: 46200 | BN49: 0 | BO49: 49720 | BP49: G,G | BQ49: T1# | BS49: 5.8064935 | BT49: 72345 | BV49: 7.3724026 | BY49: 340605 | BZ49: 7.3724026 | CP49: 董事会办公室 | CQ49: 3,3 | CR49: 10 | CS49: T1# | CT49: N
A50: aaliyahZheng(郑英红) | C50: 22423058 | D50: IEG财务管理 | E50: IEG Global Finance | G50: S2职能系统－财经线/IEG财务管理/IEG Global Finance | H50: 37919 | I50: 社会招聘 | J50: 财经类－FN | K50: 财务管理 | M50: L3-2 | N50: T1# | Q50: G,G | U50: 69269.75 | V50: 0.083333 | W50: CNY | X50: 1 | Y50: 66474.84 | Z50: 0 | AA50: 138539.5 | AF50: 35580 | AG50: 470534.5 | AH50: 7.0783848 | AJ50: 7.6136249 | AK50: 5.7933874 | AQ50: 506114.5 | AR50: 7.6136249 | AS50: 0.99965336 | BL50: 1 | BM50: 61615 | BN50: 0 | BO50: 64965 | BP50: G,O | BQ50: T1# | BS50: 6.540534 | BT50: 103295 | BV50: 8.2169926 | BY50: 506290 | BZ50: 8.2169926 | CP50: IEG财务管理 | CQ50: 3,3 | CR50: L3-2 | CS50: T1# | CT50: N
A51: walterQian(钱豪彤) | C51: 64672773 | D51: 预算及职能系统财务管理部 | E51: S系统财务管理组 | G51: S2职能系统－财经线/预算及职能系统财务管理部/S系统财务管理组 | H51: 39998 | I51: 高校招聘 | J51: 财经类－FN | K51: 预算管理 | L51: S9 | N51: T1# | Q51: G,O | U51: 56008.55 | V51: 0.083333 | W51: CNY | X51: 1 | Y51: 53386.03 | Z51: 0 | AA51: 168025.65 | AF51: 0 | AG51: 405490.65 | AH51: 7.5954449 | AJ51: 7.5954449 | AK51: 6.3781789 | AQ51: 405490.65 | AR51: 7.5954449 | AS51: 1.9558685 | BL51: 1 | BM51: 50355 | BN51: 0 | BO51: 51325 | BP51: G,U | BQ51: T1# | BS51: 4.1171681 | BT51: 0 | BV51: 4.1171681 | BY51: 207320 | BZ51: 4.1171681 | CP51: 预算及职能系统财务管理部 | CQ51: 5,3 | CR51: 9 | CS51: T1# | CT51: N
A52: juliaLiao(廖雪瑶) | C52: 31719584 | D52: 税务部 | E52: 印章及文档管理组 | G52: S2职能系统－财经线/税务部/印章及文档管理组 | H52: 39421 | I52: 高校招聘 | J52: 财经类－FN | K52: 税务 | L52: S8 | N52: T2 | Q52: G,G | U52: 28976.2 | V52: 0.083333 | W52: CNY | X52: 1 | Y52: 27708.19 | Z52: 0 | AA52: 57952.4 | AF52: 0 | AG52: 92897.4 | AH52: 3.3527055 | AJ52: 3.3527055 | AK52: 3.3527055 | AQ52: 92897.4 | AR52: 3.3527055 | AS52: 1.1078338 | BL52: 1 | BM52: 24100 | BN52: 0 | BO52: 26240 | BP52: U,O | BQ52: T2 | BS52: 3.4794606 | BT52: 0 | BV52: 3.4794606 | BY52: 83855 | BZ52: 3.4794606 | CP52: 税务部 | CQ52: 3,3 | CR52: 8 | CS52: T2 | CT52: N
A53: marcusWei(魏松坚) | C53: 76307882 | D53: 财经IT管理部 | E53: 业务开发中心 | G53: S2职能系统－财经线/财经IT管理部/业务开发中心 | H53: 41314 | I53: 社会招聘 | J53: 技术研发类－TRD | K53: 应用开发 | L53: T7 | N53: T1 | Q53: G,G | U53: 31298 | V53: 0.083333 | W53: CNY | X53: 1 | Y53: 29306.23 | Z53: 0 | AA53: 62596 | AF53: 0 | AG53: 172976 | AH53: 5.9023627 | AJ53: 5.9023627 | AK53: 4.6034922 | AQ53: 172976 | AR53: 5.9023627 | AS53: 1.2019735 | BL53: 1 | BM53: 27970 | BN53: 0 | BO53: 30180 | BP53: G,G | BQ53: T1 | BS53: 3.2390061 | BT53: 53315 | BV53: 5.1451555 | BY53: 143910 | BZ53: 5.1451555 | CP53: 财经IT管理部 | CQ53: 3,3 | CR53: 7 | CS53: T1 | CT53: N
A54: miaYu(于静) | C54: 59592158 | D54: CDG财务管理 | E54: 子公司财务管理组 | G54: S2职能系统－财经线/CDG财务管理/子公司财务管理组 | H54: 38797 | I54: 社会招聘 | J54: 财经类－FN | K54: 财务管理 | L54: S11 | N54: T1# | Q54: G,G | U54: 54160.8 | V54: 0.083333 | W54: CNY | X54: 1 | Y54: 50393.3 | Z54: 0 | AA54: 108321.6 | AF54: 0 | AG54: 344911.6 | AH54: 6.844394 | AJ54: 6.844394 | AK54: 5.7600237 | AQ54: 344911.6 | AR54: 6.844394 | AS54: 1.9294674 | BL54: 1 | BM54: 43645 | BN54: 0 | BO54: 44275 | BP54: G,U | BQ54: T1# | BS54: 4.0957727 | BT54: 0 | BV54: 4.0957727 | BY54: 178760 | BZ54: 4.0957727 | CP54: CDG财务管理 | CQ54: 3,3 | CR54: 11 | CS54: T1# | CT54: N
A55: ellaMa(马曦) | C55: 81821398 | D55: 风险管理和内部控制 | E55: PCG风控中心 | G55: S2职能系统－财经线/风险管理和内部控制/PCG风控中心 | H55: 45600 | I55: 社会招聘 | J55: 财经类－FN | K55: 风险管理 | L55: S7 | N55: T1# | Q55: N,N | U55: 40465.4 | V55: 0.083333 | W55: CNY | X55: 0.156164 | Y55: 40465.4 | Z55: 0 | AA55: 6319.24 | AF55: 0 | AG55: 6319.24 | AH55: 0.15616403 | AJ55: 0.15616403 | AK55: 0.15616403 | AQ55: 6319.24 | AR55: 0.15616403 | BM55: 0 | BN55: 0 | BO55: 0 | BT55: 0 | BY55: 0 | CP55: 风险管理和内部控制 | CR55: 7 | CS55: T1# | CT55: N
A56: evelynRen(任晶) | C56: 73942639 | D56: 行政支持中心 | E56: 秘书组 | G56: S2职能系统－财经线/行政支持中心/秘书组 | H56: 42099 | I56: 高校招聘 | J56: 财经类－FN | K56: 公司秘书 | L56: S8 | N56: T2 | Q56: G,G | U56: 44799.65 | V56: 0.083333 | W56: CNY | X56: 1 | Y56: 41547.05 | Z56: 0 | AA56: 89599.3 | AF56: 0 | AG56: 151854.3 | AH56: 3.654996 | AJ56: 3.654996 | AK56: 3.654996 | AQ56: 151854.3 | AR56: 3.654996 | AS56: 0.85880726 | BL56: 1 | BM56: 37995 | BN56: 0 | BO56: 39930 | BP56: O,G | BQ56: T2 | BS56: 4.6537702 | BT56: 0 | BV56: 4.6537702 | BY56: 176820 | BZ56: 4.6537702 | CP56: 行政支持中心 | CQ56: 3,3 | CR56: 8 | CS56: T2 | CT56: N
A57: penelopeGong(龚玲) | C57: 67957145 | D57: CFO办公室 | E57: 管理决策委员会 | G57: S2职能系统－财经线/CFO办公室/管理决策委员会 | H57: 45202 | I57: 社会招聘 | J57: 财经类－FN | K57: 投资者关系 | L57: S10 | N57: T1 | Q57: G,U | U57: 36092.25 | V57: 0.083333 | W57: CNY | X57: 1 | Y57: 34170.37 | Z57: 0 | AA57: 36092.25 | AF57: 0 | AG57: 112287.25 | AH57: 3.2860999 | AJ57: 3.2860999 | AK57: 3.2860999 | AQ57: 112287.25 | AR57: 3.2860999 | AS57: 14.842994 | BL57: 0.24383562 | BM57: 31040 | BN57: 0 | BO57: 31040 | BP57: N,G | BQ57: T1 | BS57: 0.24371778 | BT57: 0 | BV57: 0.24371778 | BY57: 7565 | BZ57: 0.24371778 | CP57: CFO办公室 | CQ57: 3,1 | CR57: 10 | CS57: T1 | CT57: N
A58: johnnyHong(洪国文) | C58: 1185225 | D58: 风险管理和内部控制 | E58: WXG风控中心 | G58: S2职能系统－财经线/风险管理和内部控制/WXG风控中心 | H58: 45140 | I58: 社会招聘 | J58: 财经类－FN | K58: 风险管理 | L58: S10 | N58: T2 | Q58: U,O | U58: 45198.7 | V58: 0.083333 | W58: CNY | X58: 1 | Y58: 44369.12 | Z58: 0 | AA58: 90397.4 | AF58: 0 | AG58: 150722.4 | AH58: 3.3970113 | AJ58: 3.3970113 | AK58: 3.3970113 | AQ58: 150722.4 | AR58: 3.3970113 | AS58: 9.3038519 | BL58: 0.41369863 | BM58: 39165 | BN58: 0 | BO58: 39165 | BP58: N,G | BQ58: T1# | BS58: 0.41363462 | BT58: 0 | BV58: 0.41363462 | BY58: 16200 | BZ58: 0.41363462 | CP58: 风险管理和内部控制 | CQ58: 5,1 | CR58: 10 | CS58: T2 | CT58: N
A59: elijahFan(范天骏) | C59: 1284819 | D59: S2人力资源中心 | E59: S2人力资源中心 | G59: S2职能系统－财经线/S2人力资源中心 | H59: 36501 | I59: 社会招聘 | J59: 财经类－FN | K59: 财经系统交付管理 | L59: S12 | N59: T2 | Q59: O,G | U59: 73282.2 | V59: 0.083333 | W59: CNY | X59: 1 | Y59: 66356.53 | Z59: 0 | AA59: 219846.6 | AF59: 0 | AG59: 307546.6 | AH59: 4.6347601 | AJ59: 4.6347601 | AK59: 4.6347601 | AQ59: 307546.6 | AR59: 4.6347601 | AS59: 1.997445 | BL59: 1 | BM59: 58965 | BN59: 0 | BO59: 64085 | BP59: G,U | BQ59: T2 | BS59: 2.61121 | BT59: 0 | BV59: 2.61121 | BY59: 153970 | BZ59: 2.61121 | CP59: S2人力资源中心 | CQ59: 5,3 | CR59: 12 | CS59: T2 | CT59: N
A60: katherineDuan(段畅苑) | C60: 90032706 | D60: 反舞弊调查部 | E60: 海外反舞弊工作组 | G60: S2职能系统－财经线/反舞弊调查部/海外反舞弊工作组 | H60: 43694 | I60: 高校招聘 | J60: 财经类－FN | K60: 风险管理 | L60: S5 | N60: T2 | Q60: O,G | U60: 17822.05 | V60: 0.083333 | W60: CNY | X60: 1 | Y60: 16296.29 | Z60: 0 | AA60: 53466.15 | AF60: 0 | AG60: 74401.15 | AH60: 4.5655269 | AJ60: 4.5655269 | AK60: 4.5655269 | AQ60: 74401.15 | AR60: 4.5655269 | AS60: 1.2665103 | BL60: 1 | BM60: 15605 | BN60: 0 | BO60: 16895 | BP60: U,O | BQ60: T2 | BS60: 3.7644986 | BT60: 0 | BV60: 3.7644986 | BY60: 58745 | BZ60: 3.7644986 | CP60: 反舞弊调查部 | CQ60: 5,3 | CR60: 5 | CS60: T2 | CT60: N
A61: richardWei(魏炜锐) | C61: 15306183 | D61: CSIG财务管理 | E61: 公线及费用财务管理中心 | G61: S2职能系统－财经线/CSIG财务管理/公线及费用财务管理中心 | H61: 41270 | I61: 高校招聘 | J61: 财经类－FN | K61: 财务管理 | L61: S9 | N61: T1 | Q61: O,G | U61: 55391.6 | V61: 0.083333 | W61: CNY | X61: 1 | Y61: 51738.61 | Z61: 0 | AA61: 166174.8 | AF61: 0 | AG61: 393429.8 | AH61: 7.6041819 | AJ61: 7.6041819 | AK61: 5.820311 | AQ61: 393429.8 | AR61: 7.6041819 | AS61: 2.9861844 | BL61: 1 | BM61: 49410 | BN61: 0 | BO61: 53475 | BP61: G,U | BQ61: T1 | BS61: 2.6664643 | BT61: 0 | BV61: 2.6664643 | BY61: 131750 | BZ61: 2.6664643 | CP61: CSIG财务管理 | CQ61: 5,3 | CR61: 9 | CS61: T1 | CT61: N
A62: carolYan(严梅) | C62: 68786878 | D62: FiT财务管理 | E62: 财经金融专项中心 | G62: S2职能系统－财经线/FiT财务管理/财经金融专项中心 | H62: 37672 | I62: 社会招聘 | J62: 财经类－FN | K62: 财务管理 | L62: S7 | N62: T1# | Q62: G,O | U62: 39345.25 | V62: 0.083333 | W62: CNY | X62: 1 | Y62: 36381.36 | Z62: 0 | AA62: 118035.75 | AF62: 0 | AG62: 312725.75 | AH62: 8.5957685 | AJ62: 8.5957685 | AK62: 6.5298755 | AQ62: 312725.75 | AR62: 8.5957685 | AS62: 2.4558328 | BL62: 1 | BM62: 34045 | BN62: 0 | BO62: 36515 | BP62: G,G | BQ62: T2 | BS62: 3.7403437 | BT62: 0 | BV62: 3.7403437 | BY62: 127340 | BZ62: 3.7403437 | CP62: FiT财务管理 | CQ62: 5,3 | CR62: 7 | CS62: T1# | CT62: N
A63: allisonYin(尹舒) | C63: 72479052 | D63: 财经投资并购及管理部 | E63: 行业及项目管理中心 | G63: S2职能系统－财经线/财经投资并购及管理部/行业及项目管理中心 | H63: 43149 | I63: 社会招聘 | J63: 财经类－FN | K63: 投资并购 | L63: S8 | N63: T1# | Q63: U,G | U63: 34567.75 | V63: 0.083333 | W63: CNY | X63: 1 | Y63: 31684.34 | Z63: 0 | AA63: 34567.75 | AF63: 0 | AG63: 145727.75 | AH63: 4.599362 | AJ63: 4.599362 | AK63: 4.599362 | AQ63: 145727.75 | AR63: 4.599362 | AS63: 0.76323225 | BL63: 1 | BM63: 27825 | BN63: 0 | BO63: 29130 | BP63: G,G | BQ63: T1# | BS63: 5.4920036 | BT63: 38120 | BV63: 6.8619946 | BY63: 190935 | BZ63: 6.8619946 | CP63: 财经投资并购及管理部 | CQ63: 3,1 | CR63: 8 | CS63: T1# | CT63: N
A64: hannahDuan(段婧) | C64: 30248804 | D64: 风险管理和内部控制 | E64: PCG风控中心 | G64: S2职能系统－财经线/风险管理和内部控制/PCG风控中心 | H64: 39548 | I64: 社会招聘 | J64: 财经类－FN | K64: 风险管理 | M64: L3-3 | N64: T1 | Q64: U,G | U64: 80887.8 | V64: 0.083333 | W64: CNY | X64: 1 | Y64: 79263.77 | Z64: 0 | AA64: 80887.8 | AF64: 8835 | AG64: 254177.8 | AH64: 3.2067337 | AJ64: 3.318197 | AK64: 3.318197 | AQ64: 263012.8 | AR64: 3.318197 | AS64: 1.700972 | BL64: 1 | BM64: 70515 | BN64: 0 | BO64: 74150 | BP64: U,G | BQ64: T1 | BS64: 2.1927959 | BT64: 0 | BV64: 2.1927959 | BY64: 154625 | BZ64: 2.1927959 | CP64: 风险管理和内部控制 | CQ64: 3,1 | CR64: L3-3 | CS64: T1 | CT64: N
A65: donaldXie(谢松) | C65: 8849775 | D65: 风险管理和内部控制 | E65: CSIG风控中心 | G65: S2职能系统－财经线/风险管理和内部控制/CSIG风控中心 | H65: 43768 | I65: 社会招聘 | J65: 财经类－FN | K65: 风险管理 | L65: S6 | N65: T1 | Q65: O,G | U65: 26913.15 | V65: 0.083333 | W65: CNY | X65: 1 | Y65: 25049.76 | Z65: 0 | AA65: 80739.45 | AF65: 0 | AG65: 194749.45 | AH65: 7.7745036 | AJ65: 7.7745036 | AK65: 5.8884576 | AQ65: 194749.45 | AR65: 7.7745036 | AS65: 1.447736 | BL65: 1 | BM65: 24180 | BN65: 0 | BO65: 25655 | BP65: G,G | BQ65: T1 | BS65: 3.4559553 | BT65: 50955 | BV65: 5.5632754 | BY65: 134520 | BZ65: 5.5632754 | CP65: 风险管理和内部控制 | CQ65: 5,3 | CR65: 6 | CS65: T1 | CT65: N
A66: sophieYe(叶姗) | C66: 21898482 | D66: CDG财务管理 | E66: AMS客户管理中心 | G66: S2职能系统－财经线/CDG财务管理/AMS客户管理中心 | H66: 41959 | I66: 社会招聘 | J66: 财经类－FN | K66: 财务管理 | L66: S7 | N66: T1# | Q66: G,G | U66: 32295.85 | V66: 0.083333 | W66: CNY | X66: 1 | Y66: 29479.95 | Z66: 0 | AA66: 64591.7 | AF66: 0 | AG66: 206556.7 | AH66: 7.0066842 | AJ66: 7.0066842 | AK66: 5.789925 | AQ66: 206556.7 | AR66: 7.0066842 | AS66: 1.5119067 | BL66: 1 | BM66: 26030 | BN66: 0 | BO66: 28275 | BP66: G,G | BQ66: T1 | BS66: 3.490972 | BT66: 45750 | BV66: 5.2485594 | BY66: 136620 | BZ66: 5.2485594 | CP66: CDG财务管理 | CQ66: 3,3 | CR66: 7 | CS66: T1# | CT66: N
A67: teresaQin(秦娜姗) | C67: 56287234 | D67: 财经IT管理部 | E67: 国际业务支持中心 | G67: S2职能系统－财经线/财经IT管理部/国际业务支持中心 | H67: 43578 | I67: 社会招聘 | J67: 技术研发类－TRD | K67: 应用开发 | L67: T8 | N67: T2 | Q67: G,G | U67: 40851.95 | V67: 0.083333 | W67: CNY | X67: 1 | Y67: 38290.87 | Z67: 0 | AA67: 81703.9 | AF67: 0 | AG67: 122953.9 | AH67: 3.21105 | AJ67: 3.21105 | AK67: 3.21105 | AQ67: 122953.9 | AR67: 3.21105 | AS67: 1.1392004 | BL67: 1 | BM67: 32710 | BN67: 0 | BO67: 32735 | BP67: G,G | BQ67: T2 | BS67: 3.2996026 | BT67: 0 | BV67: 3.2996026 | BY67: 107930 | BZ67: 3.2996026 | CP67: 财经IT管理部 | CQ67: 3,3 | CR67: 8 | CS67: T2 | CT67: N
A68: ellieCao(曹珊) | C68: 232081 | D68: CDG财务管理 | E68: CDG财务管理 | G68: S2职能系统－财经线/CDG财务管理 | H68: 38861 | I68: 高校招聘 | J68: 财经类－FN | K68: 财务管理 | L68: S6 | N68: T2 | Q68: G,G | U68: 26240.85 | V68: 0.083333 | W68: CNY | X68: 1 | Y68: 24685.06 | Z68: 0 | AA68: 52481.7 | AF68: 0 | AG68: 79236.7 | AH68: 3.2099051 | AJ68: 3.2099051 | AK68: 3.2099051 | AQ68: 79236.7 | AR68: 3.2099051 | AS68: 0.79304108 | BL68: 1 | BM68: 23075 | BN68: 0 | BO68: 24045 | BP68: O,G | BQ68: T2 | BS68: 4.3300108 | BT68: 0 | BV68: 4.3300108 | BY68: 99915 | BZ68: 4.3300108 | CP68: CDG财务管理 | CQ68: 3,3 | CR68: 6 | CS68: T2 | CT68: N
A69: aaliyahJia(贾静) | C69: 6715894 | D69: 风险管理和内部控制 | E69: WXG风控中心 | G69: S2职能系统－财经线/风险管理和内部控制/WXG风控中心 | H69: 44509 | I69: 社会招聘 | J69: 财经类－FN | K69: 风险管理 | L69: S7 | N69: T1# | Q69: G,G | U69: 27998.8 | V69: 0.083333 | W69: CNY | X69: 1 | Y69: 27506.56 | Z69: 0 | AA69: 55997.6 | AF69: 0 | AG69: 188107.6 | AH69: 6.838645 | AJ69: 6.838645 | AK69: 5.5244131 | AQ69: 188107.6 | AR69: 6.838645 | AS69: 1.7269461 | BL69: 1 | BM69: 23675 | BN69: 0 | BO69: 24345 | BP69: G,O | BQ69: T2 | BS69: 4.6008448 | BT69: 0 | BV69: 4.6008448 | BY69: 108925 | BZ69: 4.6008448 | CP69: 风险管理和内部控制 | CQ69: 3,3 | CR69: 7 | CS69: T1# | CT69: N
A70: judithShi(石茜青) | C70: 87007219 | D70: 财经投资并购及管理部 | E70: 行业及项目管理中心 | G70: S2职能系统－财经线/财经投资并购及管理部/行业及项目管理中心 | H70: 36341 | I70: 社会招聘 | J70: 财经类－FN | K70: 投资并购 | L70: S8 | N70: Others | Q70: G,G | U70: 50342.95 | V70: 0.083333 | W70: CNY | X70: 1 | Y70: 46146.18 | Z70: 0 | AA70: 100685.9 | AF70: 0 | AG70: 147005.9 | AH70: 3.185657 | AJ70: 3.185657 | AK70: 3.185657 | AQ70: 147005.9 | AR70: 3.185657 | AS70: 0.76739436 | BL70: 1 | BM70: 43800 | BN70: 0 | BO70: 47740 | BP70: G,O | BQ70: Others | BS70: 4.3736301 | BT70: 0 | BV70: 4.3736301 | BY70: 191565 | BZ70: 4.3736301 | CP70: 财经投资并购及管理部 | CQ70: 3,3 | CR70: 8 | CS70: Others | CT70: N
A71: dylanQin(秦宇胜) | C71: 97156558 | D71: 预算及职能系统财务管理部 | E71: 预算管理中心 | G71: S2职能系统－财经线/预算及职能系统财务管理部/预算管理中心 | H71: 41411 | I71: 社会招聘 | J71: 财经类－FN | K71: 预算管理 | L71: S5 | N71: T1 | Q71: U,G | U71: 19998.85 | V71: 0.083333 | W71: CNY | X71: 1 | Y71: 18479.36 | Z71: 0 | AA71: 19998.85 | AF71: 0 | AG71: 61358.85 | AH71: 3.3203991 | AJ71: 3.3203991 | AK71: 3.3203991 | AQ71: 61358.85 | AR71: 3.3203991 | AS71: 0.67135894 | BL71: 1 | BM71: 17550 | BN71: 0 | BO71: 18850 | BP71: G,G | BQ71: T1 | BS71: 3.4373219 | BT71: 31070 | BV71: 5.2076923 | BY71: 91395 | BZ71: 5.2076923 | CP71: 预算及职能系统财务管理部 | CQ71: 3,1 | CR71: 5 | CS71: T1 | CT71: N
A72: bryanCai(蔡彤博) | C72: 49464189 | D72: 财会及报告管理部 | E72: 账务中心 | G72: S2职能系统－财经线/财会及报告管理部/账务中心 | H72: 41280 | I72: 高校招聘 | J72: 财经类－FN | K72: 会计 | L72: S10 | N72: T2 | Q72: G,U | U72: 64701.95 | V72: 0.083333 | W72: CNY | X72: 1 | Y72: 63132.21 | Z72: 0 | AA72: 64701.95 | AF72: 0 | AG72: 157351.95 | AH72: 2.4924195 | AJ72: 2.4924195 | AK72: 2.4924195 | AQ72: 157351.95 | AR72: 2.4924195 | AS72: 0.82734082 | BL72: 1 | BM72: 57970 | BN72: 0 | BO72: 60340 | BP72: G,G | BQ72: T2 | BS72: 3.2808349 | BT72: 0 | BV72: 3.2808349 | BY72: 190190 | BZ72: 3.2808349 | CP72: 财会及报告管理部 | CQ72: 3,1 | CR72: 10 | CS72: T2 | CT72: N
A73: andrewSu(苏斌锋) | C73: 18789816 | D73: FiT财务管理 | E73: 结算支持中心 | G73: S2职能系统－财经线/FiT财务管理/结算支持中心 | H73: 41574 | I73: 社会招聘 | J73: 财经类－FN | K73: 财务管理 | L73: S8 | N73: T1# | Q73: O,G | U73: 45232.2 | V73: 0.083333 | W73: CNY | X73: 1 | Y73: 43458.61 | Z73: 0 | AA73: 135696.6 | AF73: 0 | AG73: 377886.6 | AH73: 8.6953218 | AJ73: 8.6953218 | AK73: 6.6409533 | AQ73: 377886.6 | AR73: 8.6953218 | AS73: 4.3853615 | BL73: 1 | BM73: 36395 | BN73: 0 | BO73: 37115 | BP73: G,U | BQ73: T2 | BS73: 2.3676329 | BT73: 0 | BV73: 2.3676329 | BY73: 86170 | BZ73: 2.3676329 | CP73: FiT财务管理 | CQ73: 5,3 | CR73: 8 | CS73: T1# | CT73: N
A74: harryHe(何松浩) | C74: 38943694 | D74: 风险管理和内部控制 | E74: IEG风控中心 | G74: S2职能系统－财经线/风险管理和内部控制/IEG风控中心 | H74: 38512 | I74: 高校招聘 | J74: 财经类－FN | K74: 风险管理 | L74: S7 | N74: Others | Q74: G,U | U74: 44533.85 | V74: 0.083333 | W74: CNY | X74: 1 | Y74: 41356.88 | Z74: 0 | AA74: 44533.85 | AF74: 0 | AG74: 85453.85 | AH74: 2.0662548 | AJ74: 2.0662548 | AK74: 2.0662548 | AQ74: 85453.85 | AR74: 2.0662548 | AS74: 0.46662944 | BL74: 1 | BM74: 38455 | BN74: 0 | BO74: 40980 | BP74: G,O | BQ74: T2 | BS74: 4.7621896 | BT74: 0 | BV74: 4.7621896 | BY74: 183130 | BZ74: 4.7621896 | CP74: 风险管理和内部控制 | CQ74: 3,1 | CR74: 7 | CS74: Others | CT74: N
A75: kyleJiang(江博宏) | C75: 41583343 | D75: 财经IT管理部 | E75: 公共支持中心 | G75: S2职能系统－财经线/财经IT管理部/公共支持中心 | H75: 38081 | I75: 社会招聘 | J75: 技术研发类－TRD | K75: 应用开发 | L75: T10 | N75: T1 | Q75: G,G | U75: 43452.1 | V75: 0.083333 | W75: CNY | X75: 1 | Y75: 41920.9 | Z75: 0 | AA75: 86904.2 | AF75: 0 | AG75: 226819.2 | AH75: 5.4106472 | AJ75: 5.4106472 | AK75: 4.3379126 | AQ75: 226819.2 | AR75: 5.4106472 | AS75: 1.4844188 | BL75: 1 | BM75: 35860 | BN75: 0 | BO75: 37275 | BP75: G,O | BQ75: Others | BS75: 4.2610151 | BT75: 0 | BV75: 4.2610151 | BY75: 152800 | BZ75: 4.2610151 | CP75: 财经IT管理部 | CQ75: 3,3 | CR75: 10 | CS75: T1 | CT75: N
A76: brooklynHu(胡青茹) | C76: 96303989 | D76: CFO办公室 | E76: 财经专业通道委员会 | G76: S2职能系统－财经线/CFO办公室/财经专业通道委员会 | H76: 37496 | I76: 社会招聘 | J76: 财经类－FN | K76: 投资者关系 | L76: S9 | N76: Others | Q76: G,O | U76: 40525.65 | V76: 0.083333 | W76: CNY | X76: 1 | Y76: 39383.95 | Z76: 0 | AA76: 121576.95 | AF76: 0 | AG76: 147236.95 | AH76: 3.7385013 | AJ76: 3.7385013 | AK76: 3.7385013 | AQ76: 147236.95 | AR76: 3.7385013 | AS76: 1.1891209 | BL76: 1 | BM76: 35100 | BN76: 0 | BO76: 36800 | BP76: G,G | BQ76: Others | BS76: 3.5276353 | BT76: 0 | BV76: 3.5276353 | BY76: 123820 | BZ76: 3.5276353 | CP76: CFO办公室 | CQ76: 5,3 | CR76: 9 | CS76: Others | CT76: N
... A85: sharonShao(邵红沁) | C85: 95581555 | D85: 财经IT管理部 | E85: 国际业务支持中心 | G85: S2职能系统－财经线/财经IT管理部/国际业务支持中心 | H85: 41880 | I85: 社会招聘 | J85: 技术研发类－TRD | K85: 应用开发 | L85: T11 | N85: T1 | Q85: O,O | U85: 51992.2 | V85: 0.083333 | W85: CNY | X85: 1 | Y85: 50755.01 | Z85: 0 | AA85: 207968.8 | AF85: 0 | AG85: 406993.8 | AH85: 8.0187907 | AJ85: 8.0187907 | AK85: 6.5264257 | AQ85: 406993.8 | AR85: 8.0187907 | AS85: 1.4554466 | BL85: 1 | BM85: 43680 | BN85: 0 | BO85: 47510 | BP85: G,O | BQ85: T1 | BS85: 4.5022894 | BT85: 82975 | BV85: 6.4019002 | BY85: 279635 | BZ85: 6.4019002 | CP85: 财经IT管理部 | CQ85: 5,5 | CR85: 11 | CS85: T1 | CT85: N
A86: frankWan(万刚) | C86: 70233595 | D86: PCG财务管理 | E86: 应用宝财务管理组 | G86: S2职能系统－财经线/PCG财务管理/应用宝财务管理组 | H86: 38079 | I86: 社会招聘 | J86: 财经类－FN | K86: 财务管理 | M86: L2-2 | N86: T1 | Q86: U,G | U86: 47380.1 | V86: 0.083333 | W86: CNY | X86: 1 | Y86: 44789.85 | Z86: 0 | AA86: 47380.1 | AF86: 13215 | AG86: 156475.1 | AH86: 3.4935393 | AJ86: 3.7885838 | AK86: 3.7885838 | AQ86: 169690.1 | AR86: 3.7885838 | AS86: 0.72069015 | BL86: 1 | BM86: 40595 | BN86: 0 | BO86: 41025 | BP86: O,G | BQ86: T1 | BS86: 4.4597857 | BT86: 54410 | BV86: 5.8000985 | BY86: 235455 | BZ86: 5.8000985 | CP86: PCG财务管理 | CQ86: 3,1 | CR86: L2-2 | CS86: T1 | CT86: N
A87: gabrielHu(胡雄) | C87: 24456997 | D87: 预算及职能系统财务管理部 | E87: S系统财务管理组 | G87: S2职能系统－财经线/预算及职能系统财务管理部/S系统财务管理组 | H87: 37761 | I87: 高校招聘 | J87: 财经类－FN | K87: 预算管理 | L87: S8 | N87: T2 | Q87: G,G | U87: 45698.5 | V87: 0.083333 | W87: CNY | X87: 1 | Y87: 44354.48 | Z87: 0 | AA87: 91397 | AF87: 0 | AG87: 150812 | AH87: 3.4001526 | AJ87: 3.4001526 | AK87: 3.4001526 | AQ87: 150812 | AR87: 3.4001526 | AS87: 1.2249188 | BL87: 1 | BM87: 36575 | BN87: 0 | BO87: 39985 | BP87: G,G | BQ87: Others | BS87: 3.3662338 | BT87: 0 | BV87: 3.3662338 | BY87: 123120 | BZ87: 3.3662338 | CP87: 预算及职能系统财务管理部 | CQ87: 3,3 | CR87: 8 | CS87: T2 | CT87: N
A88: marthaJia(贾薇) | C88: 16145259 | D88: 预算及职能系统财务管理部 | E88: 预算管理中心 | G88: S2职能系统－财经线/预算及职能系统财务管理部/预算管理中心 | H88: 37051 | I88: 社会招聘 | J88: 财经类－FN | K88: 预算管理 | L88: S11 | N88: Others | Q88: G,O | U88: 56930.05 | V88: 0.083333 | W88: CNY | X88: 1 | Y88: 51513.4 | Z88: 0 | AA88: 170790.15 | AF88: 0 | AG88: 209625.15 | AH88: 4.0693324 | AJ88: 4.0693324 | AK88: 4.0693324 | AQ88: 209625.15 | AR88: 4.0693324 | AS88: 1.2159231 | BL88: 1 | BM88: 46205 | BN88: 0 | BO88: 50070 | BP88: G,G | BQ88: Others | BS88: 3.7311979 | BT88: 0 | BV88: 3.7311979 | BY88: 172400 | BZ88: 3.7311979 | CP88: 预算及职能系统财务管理部 | CQ88: 5,3 | CR88: 11 | CS88: Others | CT88: N
A89: albertGong(龚炜骏) | C89: 47206082 | D89: 在线视频财务管理中心 | E89: OVB长视频财务管理组 | G89: S2职能系统－财经线/在线视频财务管理中心/OVB长视频财务管理组 | H89: 41079 | I89: 社会招聘 | J89: 财经类－FN | K89: 财务管理 | L89: S7 | N89: T1# | Q89: O,G | U89: 41942.2 | V89: 0.083333 | W89: CNY | X89: 1 | Y89: 41513.74 | Z89: 0 | AA89: 125826.6 | AF89: 0 | AG89: 317061.6 | AH89: 7.6375099 | AJ89: 7.6375099 | AK89: 6.3596197 | AQ89: 317061.6 | AR89: 7.6375099 | AS89: 2.2051857 | BL89: 1 | BM89: 35500 | BN89: 0 | BO89: 35550 | BP89: U,G | BQ89: T1# | BS89: 4.0501408 | BT89: 0 | BV89: 4.0501408 | BY89: 143780 | BZ89: 4.0501408 | CP89: 在线视频财务管理中心 | CQ89: 5,3 | CR89: 7 | CS89: T1# | CT89: N
A90: ericZhang(张辉健) | C90: 9332643 | D90: 风险管理和内部控制 | E90: CSIG风控中心 | G90: S2职能系统－财经线/风险管理和内部控制/CSIG风控中心 | H90: 43781 | I90: 社会招聘 | J90: 财经类－FN | K90: 风险管理 | L90: S8 | N90: T1 | Q90: G,G | U90: 29085.4 | V90: 0.083333 | W90: CNY | X90: 1 | Y90: 28255.85 | Z90: 0 | AA90: 58170.8 | AF90: 0 | AG90: 156605.8 | AH90: 5.5424204 | AJ90: 5.5424204 | AK90: 4.1538584 | AQ90: 156605.8 | AR90: 5.5424204 | AS90: 1.2746687 | BL90: 1 | BM90: 24880 | BN90: 0 | BO90: 26045 | BP90: G,G | BQ90: T1 | BS90: 3.3613344 | BT90: 39230 | BV90: 4.9381029 | BY90: 122860 | BZ90: 4.9381029 | CP90: 风险管理和内部控制 | CQ90: 3,3 | CR90: 8 | CS90: T1 | CT90: N
A91: ellaQian(钱瑶) | C91: 83816533 | D91: 风险管理和内部控制 | E91: WXG风控中心 | G91: S2职能系统－财经线/风险管理和内部控制/WXG风控中心 | H91: 38526 | I91: 社会招聘 | J91: 财经类－FN | K91: 风险管理 | L91: S6 | N91: T1# | Q91: O,G | U91: 28259.6 | V91: 0.083333 | W91: CNY | X91: 1 | Y91: 26478.39 | Z91: 0 | AA91: 84778.8 | AF91: 0 | AG91: 234108.8 | AH91: 8.8415043 | AJ91: 8.8415043 | AK91: 6.7467773 | AQ91: 234108.8 | AR91: 8.8415043 | AS91: 1.3298614 | BL91: 1 | BM91: 23170 | BN91: 0 | BO91: 23860 | BP91: O,G | BQ91: T1# | BS91: 6.5640915 | BT91: 23950 | BV91: 7.5977557 | BY91: 176040 | BZ91: 7.5977557 | CP91: 风险管理和内部控制 | CQ91: 5,3 | CR91: 6 | CS91: T1# | CT91: N
A92: harryWang(汪天) | C92: 80292865 | D92: 财经投资并购及管理部 | E92: 行业及项目管理中心 | G92: S2职能系统－财经线/财经投资并购及管理部/行业及项目管理中心 | H92: 36288 | I92: 高校招聘 | J92: 财经类－FN | K92: 投资并购 | L92: S6 | N92: T1 | Q92: G,G | U92: 28386.3 | V92: 0.083333 | W92: CNY | X92: 1 | Y92: 28008.74 | Z92: 0 | AA92: 56772.6 | AF92: 0 | AG92: 159157.6 | AH92: 5.6824263 | AJ92: 5.6824263 | AK92: 4.2573354 | AQ92: 159157.6 | AR92: 5.6824263 | AS92: 1.4370889 | BL92: 1 | BM92: 23940 | BN92: 0 | BO92: 24200 | BP92: G,G | BQ92: T1 | BS92: 3.2855054 | BT92: 32095 | BV92: 4.6261487 | BY92: 110750 | BZ92: 4.6261487 | CP92: 财经投资并购及管理部 | CQ92: 3,3 | CR92: 6 | CS92: T1 | CT92: N
A93: maryKong(孔慧) | C93: 67874412 | D93: CDG财务管理 | E93: AMS收入支持中心 | G93: S2职能系统－财经线/CDG财务管理/AMS收入支持中心 | H93: 36786 | I93: 社会招聘 | J93: 财经类－FN | K93: 财务管理 | L93: S6 | N93: T1# | Q93: G,G | U93: 34558.4 | V93: 0.083333 | W93: CNY | X93: 1 | Y93: 31140.68 | Z93: 0 | AA93: 69116.8 | AF93: 0 | AG93: 245681.8 | AH93: 7.8894167 | AJ93: 7.8894167 | AK93: 5.9374683 | AQ93: 245681.8 | AR93: 7.8894167 | AS93: 1.1904918 | BL93: 1 | BM93: 30525 | BN93: 0 | BO93: 31285 | BP93: G,G | BQ93: T1# | BS93: 5.4140868 | BT93: 41105 | BV93: 6.760688 | BY93: 206370 | BZ93: 6.760688 | CP93: CDG财务管理 | CQ93: 3,3 | CR93: 6 | CS93: T1# | CT93: N
A94: brooklynShao(邵芳薇) | C94: 57363896 | D94: CSIG财务管理 | E94: 综合财务管理中心 | G94: S2职能系统－财经线/CSIG财务管理/综合财务管理中心 | H94: 38079 | I94: 社会招聘 | J94: 财经类－FN | K94: 财务管理 | M94: L3-1 | N94: T1# | Q94: O,G | U94: 78638.05 | V94: 0.083333 | W94: CNY | X94: 1 | Y94: 76586.89 | Z94: 0 | AA94: 235914.15 | AF94: 72710 | AG94: 595384.15 | AH94: 7.7739695 | AJ94: 8.7233487 | AK94: 7.3321837 | AQ94: 668094.15 | AR94: 8.7233487 | AS94: 4.51766 | BL94: 1 | BM94: 62915 | BN94: 0 | BO94: 66620 | BP94: G,U | BQ94: T2 | BS94: 2.3505523 | BT94: 0 | BV94: 2.3505523 | BY94: 147885 | BZ94: 2.3505523 | CP94: CSIG财务管理 | CQ94: 5,3 | CR94: L3-1 | CS94: T1# | CT94: N
A95: natalieLei(雷薇琳) | C95: 98812364 | D95: 财经IT管理部 | E95: 国际业务支持中心 | G95: S2职能系统－财经线/财经IT管理部/国际业务支持中心 | H95: 40510 | I95: 社会招聘 | J95: 技术研发类－TRD | K95: 应用开发 | L95: T7 | N95: T1 | Q95: G,G | U95: 27845.5 | V95: 0.083333 | W95: CNY | X95: 1 | Y95: 26101.71 | Z95: 0 | AA95: 55691 | AF95: 0 | AG95: 175466 | AH95: 6.7223948 | AJ95: 6.7223948 | AK95: 4.745896 | AQ95: 175466 | AR95: 6.7223948 | AS95: 2.0213813 | BL95: 1 | BM95: 24605 | BN95: 0 | BO95: 26730 | BP95: G,G | BQ95: Others | BS95: 3.5279415 | BT95: 0 | BV95: 3.5279415 | BY95: 86805 | BZ95: 3.5279415 | CP95: 财经IT管理部 | CQ95: 3,3 | CR95: 7 | CS95: T1 | CT95: N
A96: avaLu(卢晗) | C96: 67313137 | D96: CDG财务管理 | E96: AMS客户管理中心 | G96: S2职能系统－财经线/CDG财务管理/AMS客户管理中心 | H96: 43605 | I96: 社会招聘 | J96: 财经类－FN | K96: 财务管理 | L96: S7 | N96: T1 | Q96: U,G | U96: 37585.4 | V96: 0.083333 | W96: CNY | X96: 1 | Y96: 34555.27 | Z96: 0 | AA96: 37585.4 | AF96: 0 | AG96: 128890.4 | AH96: 3.7299781 | AJ96: 3.7299781 | AK96: 3.7299781 | AQ96: 128890.4 | AR96: 3.7299781 | AS96: 0.70001575 | BL96: 1 | BM96: 31340 | BN96: 0 | BO96: 31625 | BP96: O,G | BQ96: T1 | BS96: 4.5226548 | BT96: 42385 | BV96: 5.8750798 | BY96: 184125 | BZ96: 5.8750798 | CP96: CDG财务管理 | CQ96: 3,1 | CR96: 7 | CS96: T1 | CT96: N
A97: rachelLiang(梁馨) | C97: 57318711 | D97: CSIG财务管理 | E97: 产品财务管理中心 | G97: S2职能系统－财经线/CSIG财务管理/产品财务管理中心 | H97: 41903 | I97: 社会招聘 | J97: 财经类－FN | K97: 财务管理 | L97: S9 | N97: T1 | Q97: G,G | U97: 49673.7 | V97: 0.083333 | W97: CNY | X97: 1 | Y97: 48753.32 | Z97: 0 | AA97: 99347.4 | AF97: 0 | AG97: 260207.4 | AH97: 5.3372242 | AJ97: 5.3372242 | AK97: 4.1243837 | AQ97: 260207.4 | AR97: 5.3372242 | AS97: 0.95711989 | BL97: 1 | BM97: 40060 | BN97: 0 | BO97: 43430 | BP97: O,G | BQ97: T1 | BS97: 4.8510984 | BT97: 77530 | BV97: 6.7864453 | BY97: 271865 | BZ97: 6.7864453 | CP97: CSIG财务管理 | CQ97: 3,3 | CR97: 9 | CS97: T1 | CT97: N
A98: carolineYe(叶茜) | C98: 61654480 | D98: 财经IT管理部 | E98: 业务开发中心 | G98: S2职能系统－财经线/财经IT管理部/业务开发中心 | H98: 40307 | I98: 社会招聘 | J98: 技术研发类－TRD | K98: 应用开发 | L98: T10 | N98: Others | Q98: G,U | U98: 46332.75 | V98: 0.083333 | W98: CNY | X98: 1 | Y98: 42147.05 | Z98: 0 | AA98: 46332.75 | AF98: 0 | AG98: 78367.75 | AH98: 1.8593887 | AJ98: 1.8593887 | AK98: 1.8593887 | AQ98: 78367.75 | AR98: 1.8593887 | AS98: 0.57874418 | BL98: 1 | BM98: 39895 | BN98: 0 | BO98: 41000 | BP98: G,G | BQ98: Others | BS98: 3.3941597 | BT98: 0 | BV98: 3.3941597 | BY98: 135410 | BZ98: 3.3941597 | CP98: 财经IT管理部 | CQ98: 3,1 | CR98: 10 | CS98: Others | CT98: N
A99: juliaGao(高嘉涵) | C99: 36653069 | D99: PCG财务管理 | E99: 在线视频财务管理中心 | G99: S2职能系统－财经线/PCG财务管理/在线视频财务管理中心 | H99: 43864 | I99: 社会招聘 | J99: 财经类－FN | K99: 财务管理 | L99: S6 | N99: T1 | Q99: U,G | U99: 33394.25 | V99: 0.083333 | W99: CNY | X99: 1 | Y99: 30338.72 | Z99: 0 | AA99: 33394.25 | AF99: 0 | AG99: 111624.25 | AH99: 3.679267 | AJ99: 3.679267 | AK99: 3.679267 | AQ99: 111624.25 | AR99: 3.679267 | AS99: 0.9480169 | BL99: 1 | BM99: 26955 | BN99: 0 | BO99: 28455 | BP99: O,G | BQ99: Others | BS99: 4.3682063 | BT99: 0 | BV99: 4.3682063 | BY99: 117745 | BZ99: 4.3682063 | CP99: PCG财务管理 | CQ99: 3,1 | CR99: 6 | CS99: T1 | CT99: N
A100: loganLuo(罗坚) | C100: 19695058 | D100: 资金管理 | E100: 资金结算及风险控制中心 | G100: S2职能系统－财经线/资金管理/资金结算及风险控制中心 | H100: 43979 | I100: 高校招聘 | J100: 财经类－FN | K100: 资金管理 | L100: S5 | N100: T2 | Q100: G,O | U100: 23474.1 | V100: 0.083333 | W100: CNY | X100: 1 | Y100: 21269.32 | Z100: 0 | AA100: 70422.3 | AF100: 0 | AG100: 96907.3 | AH100: 4.5562011 | AJ100: 4.5562011 | AK100: 4.5562011 | AQ100: 96907.3 | AR100: 4.5562011 | AS100: 1.5717671 | BL100: 1 | BM100: 19375 | BN100: 0 | BO100: 19625 | BP100: G,G | BQ100: T2 | BS100: 3.1821935 | BT100: 0 | BV100: 3.1821935 | BY100: 61655 | BZ100: 3.1821935 | CP100: 资金管理 | CQ100: 5,3 | CR100: 5 | CS100: T2 | CT100: N
A101: juanHe(何强) | C101: 67678333 | D101: 预算及职能系统财务管理部 | E101: 预算管理中心 | G101: S2职能系统－财经线/预算及职能系统财务管理部/预算管理中心 | H101: 43196 | I101: 社会招聘 | J101: 财经类－FN | K101: 预算管理 | L101: S7 | N101: T2 | Q101: G,G | U101: 34087.65 | V101: 0.083333 | W101: CNY | X101: 1 | Y101: 32306.54 | Z101: 0 | AA101: 68175.3 | AF101: 0 | AG101: 111305.3 | AH101: 3.4452869 | AJ101: 3.4452869 | AK101: 3.4452869 | AQ101: 111305.3 | AR101: 3.4452869 | AS101: 0.83773228 | BL101: 1 | BM101: 29865 | BN101: 0 | BO101: 31850 | BP101: O,G | BQ101: T2 | BS101: 4.4488532 | BT101: 0 | BV101: 4.4488532 | BY101: 132865 | BZ101: 4.4488532 | CP101: 预算及职能系统财务管理部 | CQ101: 3,3 | CR101: 7 | CS101: T2 | CT101: N
A102: rileyLiao(廖琪) | C102: 64687592 | D102: 财会及报告管理部 | E102: 海外财会管理中心 | G102: S2职能系统－财经线/财会及报告管理部/海外财会管理中心 | H102: 36779 | I102: 高校招聘 | J102: 财经类－FN | K102: 会计 | L102: S9 | N102: T1 | Q102: G,O | U102: 43009.9 | V102: 0.083333 | W102: CNY | X102: 1 | Y102: 42550.79 | Z102: 0 | AA102: 129029.7 | AF102: 0 | AG102: 270804.7 | AH102: 6.3642696 | AJ102: 6.3642696 | AK102: 5.1959012 | AQ102: 270804.7 | AR102: 6.3642696 | AS102: 1.4406038 | BL102: 1 | BM102: 36620 | BN102: 0 | BO102: 38495 | BP102: G,G | BQ102: T1 | BS102: 3.2818132 | BT102: 67800 | BV102: 5.1332605 | BY102: 187980 | BZ102: 5.1332605 | CP102: 财会及报告管理部 | CQ102: 5,3 | CR102: 9 | CS102: T1 | CT102: N
A103: lauraRen(任燕媛) | C103: 70106260 | D103: 审计监察 | E103: 海外业务审计组 | G103: S2职能系统－财经线/审计监察/海外业务审计组 | H103: 42815 | I103: 社会招聘 | J103: 财经类－FN | K103: 风险管理 | L103: S6 | N103: T2 | Q103: U,G | U103: 28624.45 | V103: 0.083333 | W103: CNY | X103: 1 | Y103: 26343.02 | Z103: 0 | AA103: 28624.45 | AF103: 0 | AG103: 57774.45 | AH103: 2.1931597 | AJ103: 2.1931597 | AK103: 2.1931597 | AQ103: 57774.45 | AR103: 2.1931597 | AS103: 0.51804035 | BL103: 1 | BM103: 23455 | BN103: 0 | BO103: 24930 | BP103: G,O | BQ103: T2 | BS103: 4.7548497 | BT103: 0 | BV103: 4.7548497 | BY103: 111525 | BZ103: 4.7548497 | CP103: 审计监察 | CQ103: 3,1 | CR103: 6 | CS103: T2 | CT103: N
A104: emilyHuang(黄雪) | C104: 74401342 | D104: 财会及报告管理部 | E104: 资产管理组 | G104: S2职能系统－财经线/财会及报告管理部/资产管理组 | H104: 37875 | I104: 社会招聘 | J104: 财经类－FN | K104: 会计 | L104: S5 | N104: T1# | Q104: U,G | U104: 29657.3 | V104: 0.083333 | W104: CNY | X104: 1 | Y104: 28200.75 | Z104: 0 | AA104: 29657.3 | AF104: 0 | AG104: 121352.3 | AH104: 4.3031586 | AJ104: 4.3031586 | AK104: 4.3031586 | AQ104: 121352.3 | AR104: 4.3031586 | AS104: 0.71339643 | BL104: 1 | BM104: 26000 | BN104: 0 | BO104: 26300 | BP104: G,G | BQ104: T1# | BS104: 5.0880769 | BT104: 37815 | BV104: 6.5425 | BY104: 170105 | BZ104: 6.5425 | CP104: 财会及报告管理部 | CQ104: 3,1 | CR104: 5 | CS104: T1# | CT104: N
A105: noraWang(王涵) | C105: 32477024 | D105: 财经IT管理部 | E105: 业务开发中心 | G105: S2职能系统－财经线/财经IT管理部/业务开发中心 | H105: 36861 | I105: 社会招聘 | J105: 技术研发类－TRD | K105: 应用开发 | L105: T12 | N105: T1 | Q105: G,G | U105: 61327.25 | V105: 0.083333 | W105: CNY | X105: 1 | Y105: 57608.93 | Z105: 0 | AA105: 122654.5 | AF105: 0 | AG105: 343824.5 | AH105: 5.9682501 | AJ105: 5.9682501 | AK105: 4.3103474 | AQ105: 343824.5 | AR105: 5.9682501 | AS105: 2.0504801 | BL105: 1 | BM105: 50155 | BN105: 0 | BO105: 51355 | BP105: U,O | BQ105: T1 | BS105: 3.343236 | BT105: 0 | BV105: 3.343236 | BY105: 167680 | BZ105: 3.343236 | CP105: 财经IT管理部 | CQ105: 3,3 | CR105: 12 | CS105: T1 | CT105: N
A106: richardHe(何宇刚) | C106: 50938378 | D106: 审计监察 | E106: 常规审计组 | G106: S2职能系统－财经线/审计监察/常规审计组 | H106: 45011 | I106: 社会招聘 | J106: 财经类－FN | K106: 风险管理 | M106: L2-2 | N106: T2 | Q106: O,G | U106: 75193.5 | V106: 0.083333 | W106: CNY | X106: 1 | Y106: 68804.8 | Z106: 0 | AA106: 225580.5 | AF106: 16975 | AG106: 337475.5 | AH106: 4.904825 | AJ106: 5.1515374 | AK106: 5.1515374 | AQ106: 354450.5 | AR106: 5.1515374 | AS106: 7.0306556 | BL106: 0.76712329 | BM106: 63385 | BN106: 0 | BO106: 65725 | BP106: G,O | BQ106: T2 | BS106: 0.79537746 | BT106: 0 | BV106: 0.79537746 | BY106: 50415 | BZ106: 0.79537746 | CP106: 审计监察 | CQ106: 5,3 | CR106: L2-2 | CS106: T2 | CT106: N
A107: gregoryLiang(梁华梓) | C107: 89699150 | D107: CDG财务管理 | E107: CDG财务管理 | G107: S2职能系统－财经线/CDG财务管理 | H107: 37347 | I107: 高校招聘 | J107: 财经类－FN | K107: 财务管理 | L107: S9 | N107: T1 | Q107: G,G | U107: 42870 | V107: 0.083333 | W107: CNY | X107: 1 | Y107: 41833.29 | Z107: 0 | AA107: 85740 | AF107: 0 | AG107: 261700 | AH107: 6.2557834 | AJ107: 6.2557834 | AK107: 4.5311999 | AQ107: 261700 | AR107: 6.2557834 | AS107: 1.5340876 | BL107: 1 | BM107: 34365 | BN107: 0 | BO107: 34615 | BP107: G,G | BQ107: T1 | BS107: 3.4535137 | BT107: 51910 | BV107: 4.9640623 | BY107: 170590 | BZ107: 4.9640623 | CP107: CDG财务管理 | CQ107: 3,3 | CR107: 9 | CS107: T1 | CT107: N
A108: karenQin(秦曼嫣) | C108: 96387865 | D108: FiT财务管理 | E108: 结算支持中心 | G108: S2职能系统－财经线/FiT财务管理/结算支持中心 | H108: 44788 | I108: 高校招聘 | J108: 财经类－FN | K108: 财务管理 | L108: S9 | N108: T1 | Q108: G,G | U108: 49212.75 | V108: 0.083333 | W108: CNY | X108: 1 | Y108: 45101.37 | Z108: 0 | AA108: 98425.5 | AF108: 0 | AG108: 273275.5 | AH108: 6.0591397 | AJ108: 6.0591397 | AK108: 4.6602908 | AQ108: 273275.5 | AR108: 6.0591397 | AS108: 3.0074891 | BL108: 1 | BM108: 41250 | BN108: 0 | BO108: 43785 | BP108: G,U | BQ108: T1 | BS108: 2.2027879 | BT108: 0 | BV108: 2.2027879 | BY108: 90865 | BZ108: 2.2027879 | CP108: FiT财务管理 | CQ108: 3,3 | CR108: 9 | CS108: T1 | CT108: N
A109: donnaGao(高慧) | C109: 58410706 | D109: 行政支持中心 | E109: 秘书组 | G109: S2职能系统－财经线/行政支持中心/秘书组 | H109: 43638 | I109: 高校招聘 | J109: 财经类－FN | K109: 公司秘书 | L109: S9 | N109: T1 | Q109: G,G | U109: 38387.1 | V109: 0.083333 | W109: CNY | X109: 1 | Y109: 37977.01 | Z109: 0 | AA109: 76774.2 | AF109: 0 | AG109: 218784.2 | AH109: 5.7609643 | AJ109: 5.7609643 | AK109: 4.275987 | AQ109: 218784.2 | AR109: 5.7609643 | AS109: 1.3966435 | BL109: 1 | BM109: 33365 | BN109: 0 | BO109: 34750 | BP109: G,G | BQ109: T1 | BS109: 3.3412258 | BT109: 45170 | BV109: 4.6950397 | BY109: 156650 | BZ109: 4.6950397 | CP109: 行政支持中心 | CQ109: 3,3 | CR109: 9 | CS109: T1 | CT109: N
A110: lauraYe(叶青) | C110: 75107083 | D110: 财会及报告管理部 | E110: 应收管理中心 | G110: S2职能系统－财经线/财会及报告管理部/应收管理中心 | H110: 36676 | I110: 社会招聘 | J110: 财经类－FN | K110: 会计 | L110: S7 | N110: T1 | Q110: O,G | U110: 36803.3 | V110: 0.083333 | W110: CNY | X110: 1 | Y110: 35816.59 | Z110: 0 | AA110: 110409.9 | AF110: 0 | AG110: 231999.9 | AH110: 6.4774424 | AJ110: 6.4774424 | AK110: 5.1900502 | AQ110: 231999.9 | AR110: 6.4774424 | AS110: 1.3340611 | BL110: 1 | BM110: 29945 | BN110: 0 | BO110: 30985 | BP110: G,O | BQ110: T1 | BS110: 4.31274 | BT110: 44760 | BV110: 5.8074804 | BY110: 173905 | BZ110: 5.8074804 | CP110: 财会及报告管理部 | CQ110: 5,3 | CR110: 7 | CS110: T1 | CT110: N
A111: sophiaLi(李玉梦) | C111: 50280560 | D111: 财经投资并购及管理部 | E111: 行业及项目管理中心 | G111: S2职能系统－财经线/财经投资并购及管理部/行业及项目管理中心 | H111: 40062 | I111: 社会招聘 | J111: 财经类－FN | K111: 投资并购 | L111: S5 | N111: Others | Q111: O,G | U111: 26400.8 | V111: 0.083333 | W111: CNY | X111: 1 | Y111: 25727.4 | Z111: 0 | AA111: 79202.4 | AF111: 0 | AG111: 101467.4 | AH111: 3.943943 | AJ111: 3.943943 | AK111: 3.943943 | AQ111: 101467.4 | AR111: 3.943943 | AS111: 0.64883077 | BL111: 1 | BM111: 21280 | BN111: 0 | BO111: 22365 | BP111: G,G | BQ111: T1# | BS111: 5.3895677 | BT111: 41695 | BV111: 7.3489192 | BY111: 156385 | BZ111: 7.3489192 | CP111: 财经投资并购及管理部 | CQ111: 5,3 | CR111: 5 | CS111: Others | CT111: N
A112: kathrynLong(龙琳) | C112: 87603918 | D112: 财会及报告管理部 | E112: 应收管理中心 | G112: S2职能系统－财经线/财会及报告管理部/应收管理中心 | H112: 41264 | I112: 高校招聘 | J112: 财经类－FN | K112: 会计 | L112: S11 | N112: T1# | Q112: G,G | U112: 58206.55 | V112: 0.083333 | W112: CNY | X112: 1 | Y112: 52975.86 | Z112: 0 | AA112: 116413.1 | AF112: 0 | AG112: 408133.1 | AH112: 7.7041335 | AJ112: 7.7041335 | AK112: 5.7863733 | AQ112: 408133.1 | AR112: 7.7041335 | AS112: 1.9151737 | BL112: 1 | BM112: 51105 | BN112: 0 | BO112: 51670 | BP112: U,G | BQ112: T1# | BS112: 4.1699442 | BT112: 0 | BV112: 4.1699442 | BY112: 213105 | BZ112: 4.1699442 | CP112: 财会及报告管理部 | CQ112: 3,3 | CR112: 11 | CS112: T1# | CT112: N
A113: elenaTan(谭涵) | C113: 37988504 | D113: 财会及报告管理部 | E113: 员工报销服务中心 | G113: S2职能系统－财经线/财会及报告管理部/员工报销服务中心 | H113: 43351 | I113: 高校招聘 | J113: 财经类－FN | K113: 会计 | L113: S11 | N113: T1 | Q113: G,O | U113: 49332.5 | V113: 0.083333 | W113: CNY | X113: 1 | Y113: 47536.53 | Z113: 0 | AA113: 147997.5 | AF113: 0 | AG113: 345502.5 | AH113: 7.2681473 | AJ113: 7.2681473 | AK113: 5.2490685 | AQ113: 345502.5 | AR113: 7.2681473 | AS113: 1.4429305 | BL113: 1 | BM113: 41780 | BN113: 0 | BO113: 45010 | BP113: G,G | BQ113: T1 | BS113: 3.6998564 | BT113: 84865 | BV113: 5.7310914 | BY113: 239445 | BZ113: 5.7310914 | CP113: 财会及报告管理部 | CQ113: 5,3 | CR113: 11 | CS113: T1 | CT113: N
A114: ryanHong(洪海) | C114: 87411951 | D114: PCG财务管理 | E114: 财务规划及分析组 | G114: S2职能系统－财经线/PCG财务管理/财务规划及分析组 | H114: 40590 | I114: 高校招聘 | J114: 财经类－FN | K114: 财务管理 | L114: S7 | N114: Others | Q114: G,G | U114: 30366.15 | V114: 0.083333 | W114: CNY | X114: 1 | Y114: 27977.26 | Z114: 0 | AA114: 60732.3 | AF114: 0 | AG114: 82152.3 | AH114: 2.9363955 | AJ114: 2.9363955 | AK114: 2.9363955 | AQ114: 82152.3 | AR114: 2.9363955 | AS114: 2.1352125 | BL114: 1 | BM114: 25535 | BN114: 0 | BO114: 27695 | BP114: U,U | BQ114: Others | BS114: 1.5067554 | BT114: 0 | BV114: 1.5067554 | BY114: 38475 | BZ114: 1.5067554 | CP114: PCG财务管理 | CQ114: 3,3 | CR114: 7 | CS114: Others | CT114: N
A115: brooklynJiang(姜琴) | C115: 66031275 | D115: 应收账款管理中心 | E115: 应收管理2组 | G115: S2职能系统－财经线/应收账款管理中心/应收管理2组 | H115: 39907 | I115: 社会招聘 | J115: 财经类－FN | K115: 会计 | L115: S6 | N115: T1# | Q115: G,G | U115: 23903.55 | V115: 0.083333 | W115: CNY | X115: 1 | Y115: 22824.63 | Z115: 0 | AA115: 47807.1 | AF115: 0 | AG115: 155752.1 | AH115: 6.8238609 | AJ115: 6.8238609 | AK115: 5.7051133 | AQ115: 155752.1 | AR115: 6.8238609 | AS115: 1.3896511 | BL115: 1 | BM115: 21425 | BN115: 0 | BO115: 23345 | BP115: G,G | BQ115: T1 | BS115: 3.6252042 | BT115: 34410 | BV115: 5.2312719 | BY115: 112080 | BZ115: 5.2312719 | CP115: 应收账款管理中心 | CQ115: 3,3 | CR115: 6 | CS115: T1# | CT115: N
A116: emilyHe(何诗) | C116: 31549065 | D116: IEG财务管理 | E116: 发行线财务管理组 | G116: S2职能系统－财经线/IEG财务管理/发行线财务管理组 | H116: 36964 | I116: 社会招聘 | J116: 财经类－FN | K116: 财务管理 | L116: S7 | N116: Others | Q116: G,O | U116: 41266.15 | V116: 0.083333 | W116: CNY | X116: 1 | Y116: 40601.33 | Z116: 0 | AA116: 123798.45 | AF116: 0 | AG116: 152068.45 | AH116: 3.7454056 | AJ116: 3.7454056 | AK116: 3.7454056 | AQ116: 152068.45 | AR116: 3.7454056 | AS116: 1.4117667 | BL116: 1 | BM116: 34420 | BN116: 0 | BO116: 35255 | BP116: G,G | BQ116: Others | BS116: 3.1294306 | BT116: 0 | BV116: 3.1294306 | BY116: 107715 | BZ116: 3.1294306 | CP116: IEG财务管理 | CQ116: 5,3 | CR116: 7 | CS116: Others | CT116: N
A117: dennisLv(吕华锐) | C117: 16709043 | D117: WXG财务管理 | E117: WXG财务管理 | G117: S2职能系统－财经线/WXG财务管理 | H117: 38985 | I117: 高校招聘 | J117: 财经类－FN | K117: 财务管理 | L117: S10 | N117: T1 | Q117: G,G | U117: 36422.85 | V117: 0.083333 | W117: CNY | X117: 1 | Y117: 35144.12 | Z117: 0 | AA117: 72845.7 | AF117: 0 | AG117: 193360.7 | AH117: 5.501936 | AJ117: 5.501936 | AK117: 4.4236618 | AQ117: 193360.7 | AR117: 5.501936 | AS117: 1.0695321 | BL117: 1 | BM117: 30250 | BN117: 0 | BO117: 32065 | BP117: O,G | BQ117: T1 | BS117: 4.3396694 | BT117: 49515 | BV117: 5.9765289 | BY117: 180790 | BZ117: 5.9765289 | CP117: WXG财务管理 | CQ117: 3,3 | CR117: 10 | CS117: T1 | CT117: N
A118: walterDong(董超晨) | C118: 30880325 | D118: 财经IT管理部 | E118: 业务开发中心 | G118: S2职能系统－财经线/财经IT管理部/业务开发中心 | H118: 38852 | I118: 社会招聘 | J118: 技术研发类－TRD | K118: 应用开发 | L118: T7 | N118: T1# | Q118: G,G | U118: 31733.55 | V118: 0.083333 | W118: CNY | X118: 1 | Y118: 29159.21 | Z118: 0 | AA118: 63467.1 | AF118: 0 | AG118: 221977.1 | AH118: 7.6125896 | AJ118: 7.6125896 | AK118: 5.4648977 | AQ118: 221977.1 | AR118: 7.6125896 | AS118: 1.2398877 | BL118: 1 | BM118: 28060 | BN118: 0 | BO118: 28745 | BP118: G,G | BQ118: T1# | BS118: 5.1593015 | BT118: 34260 | BV118: 6.3802566 | BY118: 179030 | BZ118: 6.3802566 | CP118: 财经IT管理部 | CQ118: 3,3 | CR118: 7 | CS118: T1# | CT118: N
... A132: ethanNiu(牛勇志) | C132: 53964320 | D132: PCG财务管理 | E132: 在线视频财务管理中心 | G132: S2职能系统－财经线/PCG财务管理/在线视频财务管理中心 | H132: 42787 | I132: 高校招聘 | J132: 财经类－FN | K132: 财务管理 | L132: S5 | N132: T1 | Q132: G,G | U132: 30340.25 | V132: 0.083333 | W132: CNY | X132: 1 | Y132: 28324.33 | Z132: 0 | AA132: 60680.5 | AF132: 0 | AG132: 163720.5 | AH132: 5.7802073 | AJ132: 5.7802073 | AK132: 4.3431036 | AQ132: 163720.5 | AR132: 5.7802073 | AS132: 2.0695298 | BL132: 1 | BM132: 25000 | BN132: 0 | BO132: 25390 | BP132: G,G | BQ132: T2 | BS132: 3.1644 | BT132: 0 | BV132: 3.1644 | BY132: 79110 | BZ132: 3.1644 | CP132: PCG财务管理 | CQ132: 3,3 | CR132: 5 | CS132: T1 | CT132: N
A133: ralphTan(谭波) | C133: 70522497 | D133: 风险管理和内部控制 | E133: S系统风控组 | G133: S2职能系统－财经线/风险管理和内部控制/S系统风控组 | H133: 43895 | I133: 社会招聘 | J133: 财经类－FN | K133: 风险管理 | M133: L2-1 | N133: T2 | Q133: G,G | U133: 69362 | V133: 0.083333 | W133: CNY | X133: 1 | Y133: 67849.63 | Z133: 0 | AA133: 138724 | AF133: 14740 | AG133: 214479 | AH133: 3.1610931 | AJ133: 3.3783382 | AK133: 3.3783382 | AQ133: 229219 | AR133: 3.3783382 | AS133: 1.3170478 | BL133: 1 | BM133: 56765 | BN133: 0 | BO133: 57500 | BP133: G,G | BQ133: T2 | BS133: 3.0659738 | BT133: 0 | BV133: 3.0659738 | BY133: 174040 | BZ133: 3.0659738 | CP133: 风险管理和内部控制 | CQ133: 3,3 | CR133: L2-1 | CS133: T2 | CT133: N
A134: rebeccaWu(吴冰) | C134: 32997973 | D134: CSIG财务管理 | E134: 综合财务管理中心 | G134: S2职能系统－财经线/CSIG财务管理/综合财务管理中心 | H134: 38030 | I134: 高校招聘 | J134: 财经类－FN | K134: 财务管理 | L134: S10 | N134: T1 | Q134: G,G | U134: 46576.55 | V134: 0.083333 | W134: CNY | X134: 1 | Y134: 41936.75 | Z134: 0 | AA134: 93153.1 | AF134: 0 | AG134: 244318.1 | AH134: 5.8258711 | AJ134: 5.8258711 | AK134: 4.6164307 | AQ134: 244318.1 | AR134: 5.8258711 | AS134: 0.82345163 | BL134: 1 | BM134: 41540 | BN134: 0 | BO134: 44095 | BP134: O,O | BQ134: T1 | BS134: 5.6783823 | BT134: 60820 | BV134: 7.1425132 | BY134: 296700 | BZ134: 7.1425132 | CP134: CSIG财务管理 | CQ134: 3,3 | CR134: 10 | CS134: T1 | CT134: N
...

Sheet 汇率
A1: 本币 | B1: 本币转CNY汇率
A2: CNY | B2: 1
A3: CNY | B3: 1
A4: SGD | B4: 5.4589
A5: USD | B5: 7.0789
